Workbook

Sheet 00_README
A1: PFI RM Lumbar - 36-month editable financial model
A3: Purpose | B3: Editable academic financial model for the lumbar MRI MVP business/economic chapter.
A4: Currency | B4: USD
A5: Horizon | B5: 36 months
A6: Scenario selector | B6: Cell 01_ASSUMPTIONS!B2 controls the active model.
A7: Scenarios | B7: Pesimista / Base / Optimista
A8: Important limitation | B8: All prices, costs, conversion, churn and demand assumptions are provisional and require external validation.
A9: Clinical/commercial status | B9: The model does not claim clinical adoption, reimbursability, procurement approval or productive availability.
A10: Editable sheets | B10: 01_ASSUMPTIONS, 02_PRICING, 04_CASH_FLOW
A11: Formula sheets | B11: 04_CASH_FLOW, 05_KPIS, 06_BREAK_EVEN, 07_SENSITIVITY
A12: Non-functional scope | B12: No LaTeX update, no code change, no macros.
A13: Validation note | B13: Generated and checked programmatically; open in Excel/LibreOffice to recalculate after manual edits.
A14: Repository note | B14: This workbook is documentation/business-model evidence only.

Sheet 01_ASSUMPTIONS
A1: Category | B1: Variable | C1: Pesimista | D1: Base | E1: Optimista | F1: Unit | G1: Type | H1: Justification | I1: Source / pending | J1: Active value
A2: Active scenario | B2: Base | D2: Monthly discount rate | E2: =(1+INDEX($J$5:$J$39,MATCH("annual_discount_rate",$B$5:$B$39,0)))^(1/12)-1
A4: Category | B4: Variable | C4: Pesimista | D4: Base | E4: Optimista | F4: Unit | G4: Type | H4: Justification | I4: Source / pending | J4: Active value
A5: General | B5: horizon_months | C5: 36 | D5: 36 | E5: 36 | F5: months | G5: input | H5: Model horizon requested for the business plan. | I5: Defined by scope; validate with thesis committee. | J5: =CHOOSE(MATCH($B$2,$C$4:$E$4,0),C5,D5,E5)
A6: General | B6: annual_discount_rate | C6: 0.35 | D6: 0.25 | E6: 0.18 | F6: % | G6: input | H6: Risk-adjusted prototype-stage discount rate. | I6: Pending local WACC/risk benchmark. | J6: =CHOOSE(MATCH($B$2,$C$4:$E$4,0),C6,D6,E6)
A7: General | B7: fx_usd_ars | C7: 1000 | D7: 1000 | E7: 1000 | F7: ARS/USD | G7: memo | H7: Reference FX only; workbook currency is USD. | I7: Pending finance source at decision date. | J7: =CHOOSE(MATCH($B$2,$C$4:$E$4,0),C7,D7,E7)
A8: Pricing | B8: starter_fee | C8: 400 | D8: 600 | E8: 900 | F8: USD/month | G8: input | H8: Entry institutional pilot package. | I8: Pending willingness-to-pay interviews. | J8: =CHOOSE(MATCH($B$2,$C$4:$E$4,0),C8,D8,E8)
A9: Pricing | B9: starter_included_studies | C9: 80 | D9: 120 | E9: 180 | F9: studies/month | G9: input | H9: Included volume for entry package. | I9: Pending real usage distribution. | J9: =CHOOSE(MATCH($B$2,$C$4:$E$4,0),C9,D9,E9)
A10: Pricing | B10: starter_overage_fee | C10: 6 | D10: 8 | E10: 10 | F10: USD/study | G10: input | H10: Overage per processed study. | I10: Pending commercial validation. | J10: =CHOOSE(MATCH($B$2,$C$4:$E$4,0),C10,D10,E10)
A11: Pricing | B11: professional_fee | C11: 1100 | D11: 1600 | E11: 2300 | F11: USD/month | G11: input | H11: Mid-tier institutional subscription. | I11: Pending willingness-to-pay interviews. | J11: =CHOOSE(MATCH($B$2,$C$4:$E$4,0),C11,D11,E11)
A12: Pricing | B12: professional_included_studies | C12: 300 | D12: 500 | E12: 750 | F12: studies/month | G12: input | H12: Included volume for mid-tier package. | I12: Pending real usage distribution. | J12: =CHOOSE(MATCH($B$2,$C$4:$E$4,0),C12,D12,E12)
A13: Pricing | B13: professional_overage_fee | C13: 4.5 | D13: 6 | E13: 8 | F13: USD/study | G13: input | H13: Mid-tier overage price. | I13: Pending commercial validation. | J13: =CHOOSE(MATCH($B$2,$C$4:$E$4,0),C13,D13,E13)
A14: Pricing | B14: enterprise_fee | C14: 3000 | D14: 4500 | E14: 7000 | F14: USD/month | G14: input | H14: Large-center subscription. | I14: Pending enterprise procurement validation. | J14: =CHOOSE(MATCH($B$2,$C$4:$E$4,0),C14,D14,E14)
A15: Pricing | B15: enterprise_included_studies | C15: 900 | D15: 1500 | E15: 2400 | F15: studies/month | G15: input | H15: Included volume for large-center package. | I15: Pending real usage distribution. | J15: =CHOOSE(MATCH($B$2,$C$4:$E$4,0),C15,D15,E15)
A16: Pricing | B16: enterprise_overage_fee | C16: 3 | D16: 4 | E16: 5 | F16: USD/study | G16: input | H16: Large-tier overage price. | I16: Pending commercial validation. | J16: =CHOOSE(MATCH($B$2,$C$4:$E$4,0),C16,D16,E16)
... A39: Investment | B39: launch_setup | C39: 500 | D39: 2500 | E39: 7000 | F39: USD upfront | G39: input | H39: Launch material, legal, onboarding setup. | I39: Pending launch plan. | J39: =CHOOSE(MATCH($B$2,$C$4:$E$4,0),C39,D39,E39)

Sheet 02_PRICING
A1: Tier | B1: Monthly fee | C1: Included studies | D1: Overage fee | E1: Target user | F1: Validation status
A2: Starter | B2: =INDEX('01_ASSUMPTIONS'!$J$5:$J$39,MATCH("starter_fee",'01_ASSUMPTIONS'!$B$5:$B$39,0)) | C2: =INDEX('01_ASSUMPTIONS'!$J$5:$J$39,MATCH("starter_included_studies",'01_ASSUMPTIONS'!$B$5:$B$39,0)) | D2: =INDEX('01_ASSUMPTIONS'!$J$5:$J$39,MATCH("starter_overage_fee",'01_ASSUMPTIONS'!$B$5:$B$39,0)) | E2: Small pilot / low-volume center | F2: Provisional
A3: Professional | B3: =INDEX('01_ASSUMPTIONS'!$J$5:$J$39,MATCH("professional_fee",'01_ASSUMPTIONS'!$B$5:$B$39,0)) | C3: =INDEX('01_ASSUMPTIONS'!$J$5:$J$39,MATCH("professional_included_studies",'01_ASSUMPTIONS'!$B$5:$B$39,0)) | D3: =INDEX('01_ASSUMPTIONS'!$J$5:$J$39,MATCH("professional_overage_fee",'01_ASSUMPTIONS'!$B$5:$B$39,0)) | E3: Clinical center / teaching hospital | F3: Provisional
A4: Enterprise | B4: =INDEX('01_ASSUMPTIONS'!$J$5:$J$39,MATCH("enterprise_fee",'01_ASSUMPTIONS'!$B$5:$B$39,0)) | C4: =INDEX('01_ASSUMPTIONS'!$J$5:$J$39,MATCH("enterprise_included_studies",'01_ASSUMPTIONS'!$B$5:$B$39,0)) | D4: =INDEX('01_ASSUMPTIONS'!$J$5:$J$39,MATCH("enterprise_overage_fee",'01_ASSUMPTIONS'!$B$5:$B$39,0)) | E4: Large institution / network | F4: Provisional

Sheet 04_CASH_FLOW
A1: Month | B1: Active customers Starter | C1: Active customers Professional | D1: Active customers Enterprise | E1: Total customers | F1: Studies Starter | G1: Studies Professional | H1: Studies Enterprise | I1: Total studies | J1: Subscription revenue | K1: Overage revenue | L1: Total revenue | M1: Cloud cost | N1: Storage cost | O1: AI processing cost | P1: Variable support | Q1: Total variable costs | R1: Fixed infrastructure | S1: Maintenance | T1: Base support | U1: Admin | V1: Commercial/marketing | W1: Other fixed | X1: Total fixed costs | Y1: EBITDA / operating result | Z1: Initial investment | AA1: Net cash flow | AB1: Discount factor | AC1: Discounted cash flow | AD1: Cumulative cash flow | AE1: Operating break-even flag | AF1: Payback flag
A2: =1 | B2: =INDEX('01_ASSUMPTIONS'!$J$5:$J$39,MATCH("starter_initial_customers",'01_ASSUMPTIONS'!$B$5:$B$39,0))+INDEX('01_ASSUMPTIONS'!$J$5:$J$39,MATCH("starter_monthly_acquisition",'01_ASSUMPTIONS'!$B$5:$B$39,0)) | C2: =INDEX('01_ASSUMPTIONS'!$J$5:$J$39,MATCH("professional_initial_customers",'01_ASSUMPTIONS'!$B$5:$B$39,0))+INDEX('01_ASSUMPTIONS'!$J$5:$J$39,MATCH("professional_monthly_acquisition",'01_ASSUMPTIONS'!$B$5:$B$39,0)) | D2: =INDEX('01_ASSUMPTIONS'!$J$5:$J$39,MATCH("enterprise_initial_customers",'01_ASSUMPTIONS'!$B$5:$B$39,0))+INDEX('01_ASSUMPTIONS'!$J$5:$J$39,MATCH("enterprise_monthly_acquisition",'01_ASSUMPTIONS'!$B$5:$B$39,0)) | E2: =SUM(B2:D2) | F2: =B2*INDEX('01_ASSUMPTIONS'!$J$5:$J$39,MATCH("starter_studies_per_customer",'01_ASSUMPTIONS'!$B$5:$B$39,0)) | G2: =C2*INDEX('01_ASSUMPTIONS'!$J$5:$J$39,MATCH("professional_studies_per_customer",'01_ASSUMPTIONS'!$B$5:$B$39,0)) | H2: =D2*INDEX('01_ASSUMPTIONS'!$J$5:$J$39,MATCH("enterprise_studies_per_customer",'01_ASSUMPTIONS'!$B$5:$B$39,0)) | I2: =SUM(F2:H2) | J2: =B2*INDEX('01_ASSUMPTIONS'!$J$5:$J$39,MATCH("starter_fee",'01_ASSUMPTIONS'!$B$5:$B$39,0))+C2*INDEX('01_ASSUMPTIONS'!$J$5:$J$39,MATCH("professional_fee",'01_ASSUMPTIONS'!$B$5:$B$39,0))+D2*INDEX('01_ASSUMPTIONS'!$J$5:$J$39,MATCH("enterprise_fee",'01_ASSUMPTIONS'!$B$5:$B$39,0)) | K2: =MAX(F2-B2*INDEX('01_ASSUMPTIONS'!$J$5:$J$39,MATCH("starter_included_studies",'01_ASSUMPTIONS'!$B$5:$B$39,0)),0)*INDEX('01_ASSUMPTIONS'!$J$5:$J$39,MATCH("starter_overage_fee",'01_ASSUMPTIONS'!$B$5:$B$39,0))+MAX(G2-C2*INDEX('01_ASSUMPTIONS'!$J$5:$J$39,MATCH("professional_included_studies",'01_ASSUMPTIONS'!$B$5:$B$39,0)),0)*INDEX('01_ASSUMPTIONS'!$J$5:$J$39,MATCH("professional_overage_fee",'01_ASSUMPTIONS'!$B$5:$B$39,0))+MAX(H2-D2*INDEX('01_ASSUMPTIONS'!$J$5:$J$39,MATCH("enterprise_included_studies",'01_ASSUMPTIONS'!$B$5:$B$39,0)),0)*INDEX('01_ASSUMPTIONS'!$J$5:$J$39,MATCH("enterprise_overage_fee",'01_ASSUMPTIONS'!$B$5:$B$39,0)) | L2: =J2+K2 | M2: =I2*INDEX('01_ASSUMPTIONS'!$J$5:$J$39,MATCH("cloud_cost_per_study",'01_ASSUMPTIONS'!$B$5:$B$39,0)) | N2: =I2*INDEX('01_ASSUMPTIONS'!$J$5:$J$39,MATCH("storage_cost_per_study",'01_ASSUMPTIONS'!$B$5:$B$39,0)) | O2: =I2*INDEX('01_ASSUMPTIONS'!$J$5:$J$39,MATCH("ai_processing_cost_per_study",'01_ASSUMPTIONS'!$B$5:$B$39,0)) | P2: =E2*INDEX('01_ASSUMPTIONS'!$J$5:$J$39,MATCH("variable_support_per_customer",'01_ASSUMPTIONS'!$B$5:$B$39,0)) | Q2: =SUM(M2:P2) | R2: =INDEX('01_ASSUMPTIONS'!$J$5:$J$39,MATCH("fixed_infra",'01_ASSUMPTIONS'!$B$5:$B$39,0)) | S2: =INDEX('01_ASSUMPTIONS'!$J$5:$J$39,MATCH("software_maintenance",'01_ASSUMPTIONS'!$B$5:$B$39,0)) | T2: =INDEX('01_ASSUMPTIONS'!$J$5:$J$39,MATCH("base_support",'01_ASSUMPTIONS'!$B$5:$B$39,0)) | U2: =INDEX('01_ASSUMPTIONS'!$J$5:$J$39,MATCH("admin",'01_ASSUMPTIONS'!$B$5:$B$39,0)) | V2: =INDEX('01_ASSUMPTIONS'!$J$5:$J$39,MATCH("commercial_marketing",'01_ASSUMPTIONS'!$B$5:$B$39,0)) | W2: =INDEX('01_ASSUMPTIONS'!$J$5:$J$39,MATCH("other_fixed",'01_ASSUMPTIONS'!$B$5:$B$39,0)) | X2: =SUM(R2:W2) | Y2: =L2-Q2-X2 | Z2: =INDEX('01_ASSUMPTIONS'!$J$5:$J$39,MATCH("development_investment",'01_ASSUMPTIONS'!$B$5:$B$39,0))+INDEX('01_ASSUMPTIONS'!$J$5:$J$39,MATCH("cloud_setup",'01_ASSUMPTIONS'!$B$5:$B$39,0))+INDEX('01_ASSUMPTIONS'!$J$5:$J$39,MATCH("launch_setup",'01_ASSUMPTIONS'!$B$5:$B$39,0)) | AA2: =Y2-Z2 | AB2: =1/(1+'01_ASSUMPTIONS'!$E$2)^A2 | AC2: =AA2*AB2 | AD2: =AA2 | AE2: =IF(Y2>=0,"Yes","No") | AF2: =IF(AD2>=0,"Yes","No")
A3: =2 | B3: =B2*(1-INDEX('01_ASSUMPTIONS'!$J$5:$J$39,MATCH("monthly_churn",'01_ASSUMPTIONS'!$B$5:$B$39,0)))+INDEX('01_ASSUMPTIONS'!$J$5:$J$39,MATCH("starter_monthly_acquisition",'01_ASSUMPTIONS'!$B$5:$B$39,0)) | C3: =C2*(1-INDEX('01_ASSUMPTIONS'!$J$5:$J$39,MATCH("monthly_churn",'01_ASSUMPTIONS'!$B$5:$B$39,0)))+INDEX('01_ASSUMPTIONS'!$J$5:$J$39,MATCH("professional_monthly_acquisition",'01_ASSUMPTIONS'!$B$5:$B$39,0)) | D3: =D2*(1-INDEX('01_ASSUMPTIONS'!$J$5:$J$39,MATCH("monthly_churn",'01_ASSUMPTIONS'!$B$5:$B$39,0)))+INDEX('01_ASSUMPTIONS'!$J$5:$J$39,MATCH("enterprise_monthly_acquisition",'01_ASSUMPTIONS'!$B$5:$B$39,0)) | E3: =SUM(B3:D3) | F3: =B3*INDEX('01_ASSUMPTIONS'!$J$5:$J$39,MATCH("starter_studies_per_customer",'01_ASSUMPTIONS'!$B$5:$B$39,0)) | G3: =C3*INDEX('01_ASSUMPTIONS'!$J$5:$J$39,MATCH("professional_studies_per_customer",'01_ASSUMPTIONS'!$B$5:$B$39,0)) | H3: =D3*INDEX('01_ASSUMPTIONS'!$J$5:$J$39,MATCH("enterprise_studies_per_customer",'01_ASSUMPTIONS'!$B$5:$B$39,0)) | I3: =SUM(F3:H3) | J3: =B3*INDEX('01_ASSUMPTIONS'!$J$5:$J$39,MATCH("starter_fee",'01_ASSUMPTIONS'!$B$5:$B$39,0))+C3*INDEX('01_ASSUMPTIONS'!$J$5:$J$39,MATCH("professional_fee",'01_ASSUMPTIONS'!$B$5:$B$39,0))+D3*INDEX('01_ASSUMPTIONS'!$J$5:$J$39,MATCH("enterprise_fee",'01_ASSUMPTIONS'!$B$5:$B$39,0)) | K3: =MAX(F3-B3*INDEX('01_ASSUMPTIONS'!$J$5:$J$39,MATCH("starter_included_studies",'01_ASSUMPTIONS'!$B$5:$B$39,0)),0)*INDEX('01_ASSUMPTIONS'!$J$5:$J$39,MATCH("starter_overage_fee",'01_ASSUMPTIONS'!$B$5:$B$39,0))+MAX(G3-C3*INDEX('01_ASSUMPTIONS'!$J$5:$J$39,MATCH("professional_included_studies",'01_ASSUMPTIONS'!$B$5:$B$39,0)),0)*INDEX('01_ASSUMPTIONS'!$J$5:$J$39,MATCH("professional_overage_fee",'01_ASSUMPTIONS'!$B$5:$B$39,0))+MAX(H3-D3*INDEX('01_ASSUMPTIONS'!$J$5:$J$39,MATCH("enterprise_included_studies",'01_ASSUMPTIONS'!$B$5:$B$39,0)),0)*INDEX('01_ASSUMPTIONS'!$J$5:$J$39,MATCH("enterprise_overage_fee",'01_ASSUMPTIONS'!$B$5:$B$39,0)) | L3: =J3+K3 | M3: =I3*INDEX('01_ASSUMPTIONS'!$J$5:$J$39,MATCH("cloud_cost_per_study",'01_ASSUMPTIONS'!$B$5:$B$39,0)) | N3: =I3*INDEX('01_ASSUMPTIONS'!$J$5:$J$39,MATCH("storage_cost_per_study",'01_ASSUMPTIONS'!$B$5:$B$39,0)) | O3: =I3*INDEX('01_ASSUMPTIONS'!$J$5:$J$39,MATCH("ai_processing_cost_per_study",'01_ASSUMPTIONS'!$B$5:$B$39,0)) | P3: =E3*INDEX('01_ASSUMPTIONS'!$J$5:$J$39,MATCH("variable_support_per_customer",'01_ASSUMPTIONS'!$B$5:$B$39,0)) | Q3: =SUM(M3:P3) | R3: =INDEX('01_ASSUMPTIONS'!$J$5:$J$39,MATCH("fixed_infra",'01_ASSUMPTIONS'!$B$5:$B$39,0)) | S3: =INDEX('01_ASSUMPTIONS'!$J$5:$J$39,MATCH("software_maintenance",'01_ASSUMPTIONS'!$B$5:$B$39,0)) | T3: =INDEX('01_ASSUMPTIONS'!$J$5:$J$39,MATCH("base_support",'01_ASSUMPTIONS'!$B$5:$B$39,0)) | U3: =INDEX('01_ASSUMPTIONS'!$J$5:$J$39,MATCH("admin",'01_ASSUMPTIONS'!$B$5:$B$39,0)) | V3: =INDEX('01_ASSUMPTIONS'!$J$5:$J$39,MATCH("commercial_marketing",'01_ASSUMPTIONS'!$B$5:$B$39,0)) | W3: =INDEX('01_ASSUMPTIONS'!$J$5:$J$39,MATCH("other_fixed",'01_ASSUMPTIONS'!$B$5:$B$39,0)) | X3: =SUM(R3:W3) | Y3: =L3-Q3-X3 | Z3: =0 | AA3: =Y3-Z3 | AB3: =1/(1+'01_ASSUMPTIONS'!$E$2)^A3 | AC3: =AA3*AB3 | AD3: =AD2+AA3 | AE3: =IF(Y3>=0,"Yes","No") | AF3: =IF(AD3>=0,"Yes","No")
A4: =3 | B4: =B3*(1-INDEX('01_ASSUMPTIONS'!$J$5:$J$39,MATCH("monthly_churn",'01_ASSUMPTIONS'!$B$5:$B$39,0)))+INDEX('01_ASSUMPTIONS'!$J$5:$J$39,MATCH("starter_monthly_acquisition",'01_ASSUMPTIONS'!$B$5:$B$39,0)) | C4: =C3*(1-INDEX('01_ASSUMPTIONS'!$J$5:$J$39,MATCH("monthly_churn",'01_ASSUMPTIONS'!$B$5:$B$39,0)))+INDEX('01_ASSUMPTIONS'!$J$5:$J$39,MATCH("professional_monthly_acquisition",'01_ASSUMPTIONS'!$B$5:$B$39,0)) | D4: =D3*(1-INDEX('01_ASSUMPTIONS'!$J$5:$J$39,MATCH("monthly_churn",'01_ASSUMPTIONS'!$B$5:$B$39,0)))+INDEX('01_ASSUMPTIONS'!$J$5:$J$39,MATCH("enterprise_monthly_acquisition",'01_ASSUMPTIONS'!$B$5:$B$39,0)) | E4: =SUM(B4:D4) | F4: =B4*INDEX('01_ASSUMPTIONS'!$J$5:$J$39,MATCH("starter_studies_per_customer",'01_ASSUMPTIONS'!$B$5:$B$39,0)) | G4: =C4*INDEX('01_ASSUMPTIONS'!$J$5:$J$39,MATCH("professional_studies_per_customer",'01_ASSUMPTIONS'!$B$5:$B$39,0)) | H4: =D4*INDEX('01_ASSUMPTIONS'!$J$5:$J$39,MATCH("enterprise_studies_per_customer",'01_ASSUMPTIONS'!$B$5:$B$39,0)) | I4: =SUM(F4:H4) | J4: =B4*INDEX('01_ASSUMPTIONS'!$J$5:$J$39,MATCH("starter_fee",'01_ASSUMPTIONS'!$B$5:$B$39,0))+C4*INDEX('01_ASSUMPTIONS'!$J$5:$J$39,MATCH("professional_fee",'01_ASSUMPTIONS'!$B$5:$B$39,0))+D4*INDEX('01_ASSUMPTIONS'!$J$5:$J$39,MATCH("enterprise_fee",'01_ASSUMPTIONS'!$B$5:$B$39,0)) | K4: =MAX(F4-B4*INDEX('01_ASSUMPTIONS'!$J$5:$J$39,MATCH("starter_included_studies",'01_ASSUMPTIONS'!$B$5:$B$39,0)),0)*INDEX('01_ASSUMPTIONS'!$J$5:$J$39,MATCH("starter_overage_fee",'01_ASSUMPTIONS'!$B$5:$B$39,0))+MAX(G4-C4*INDEX('01_ASSUMPTIONS'!$J$5:$J$39,MATCH("professional_included_studies",'01_ASSUMPTIONS'!$B$5:$B$39,0)),0)*INDEX('01_ASSUMPTIONS'!$J$5:$J$39,MATCH("professional_overage_fee",'01_ASSUMPTIONS'!$B$5:$B$39,0))+MAX(H4-D4*INDEX('01_ASSUMPTIONS'!$J$5:$J$39,MATCH("enterprise_included_studies",'01_ASSUMPTIONS'!$B$5:$B$39,0)),0)*INDEX('01_ASSUMPTIONS'!$J$5:$J$39,MATCH("enterprise_overage_fee",'01_ASSUMPTIONS'!$B$5:$B$39,0)) | L4: =J4+K4 | M4: =I4*INDEX('01_ASSUMPTIONS'!$J$5:$J$39,MATCH("cloud_cost_per_study",'01_ASSUMPTIONS'!$B$5:$B$39,0)) | N4: =I4*INDEX('01_ASSUMPTIONS'!$J$5:$J$39,MATCH("storage_cost_per_study",'01_ASSUMPTIONS'!$B$5:$B$39,0)) | O4: =I4*INDEX('01_ASSUMPTIONS'!$J$5:$J$39,MATCH("ai_processing_cost_per_study",'01_ASSUMPTIONS'!$B$5:$B$39,0)) | P4: =E4*INDEX('01_ASSUMPTIONS'!$J$5:$J$39,MATCH("variable_support_per_customer",'01_ASSUMPTIONS'!$B$5:$B$39,0)) | Q4: =SUM(M4:P4) | R4: =INDEX('01_ASSUMPTIONS'!$J$5:$J$39,MATCH("fixed_infra",'01_ASSUMPTIONS'!$B$5:$B$39,0)) | S4: =INDEX('01_ASSUMPTIONS'!$J$5:$J$39,MATCH("software_maintenance",'01_ASSUMPTIONS'!$B$5:$B$39,0)) | T4: =INDEX('01_ASSUMPTIONS'!$J$5:$J$39,MATCH("base_support",'01_ASSUMPTIONS'!$B$5:$B$39,0)) | U4: =INDEX('01_ASSUMPTIONS'!$J$5:$J$39,MATCH("admin",'01_ASSUMPTIONS'!$B$5:$B$39,0)) | V4: =INDEX('01_ASSUMPTIONS'!$J$5:$J$39,MATCH("commercial_marketing",'01_ASSUMPTIONS'!$B$5:$B$39,0)) | W4: =INDEX('01_ASSUMPTIONS'!$J$5:$J$39,MATCH("other_fixed",'01_ASSUMPTIONS'!$B$5:$B$39,0)) | X4: =SUM(R4:W4) | Y4: =L4-Q4-X4 | Z4: =0 | AA4: =Y4-Z4 | AB4: =1/(1+'01_ASSUMPTIONS'!$E$2)^A4 | AC4: =AA4*AB4 | AD4: =AD3+AA4 | AE4: =IF(Y4>=0,"Yes","No") | AF4: =IF(AD4>=0,"Yes","No")
A5: =4 | B5: =B4*(1-INDEX('01_ASSUMPTIONS'!$J$5:$J$39,MATCH("monthly_churn",'01_ASSUMPTIONS'!$B$5:$B$39,0)))+INDEX('01_ASSUMPTIONS'!$J$5:$J$39,MATCH("starter_monthly_acquisition",'01_ASSUMPTIONS'!$B$5:$B$39,0)) | C5: =C4*(1-INDEX('01_ASSUMPTIONS'!$J$5:$J$39,MATCH("monthly_churn",'01_ASSUMPTIONS'!$B$5:$B$39,0)))+INDEX('01_ASSUMPTIONS'!$J$5:$J$39,MATCH("professional_monthly_acquisition",'01_ASSUMPTIONS'!$B$5:$B$39,0)) | D5: =D4*(1-INDEX('01_ASSUMPTIONS'!$J$5:$J$39,MATCH("monthly_churn",'01_ASSUMPTIONS'!$B$5:$B$39,0)))+INDEX('01_ASSUMPTIONS'!$J$5:$J$39,MATCH("enterprise_monthly_acquisition",'01_ASSUMPTIONS'!$B$5:$B$39,0)) | E5: =SUM(B5:D5) | F5: =B5*INDEX('01_ASSUMPTIONS'!$J$5:$J$39,MATCH("starter_studies_per_customer",'01_ASSUMPTIONS'!$B$5:$B$39,0)) | G5: =C5*INDEX('01_ASSUMPTIONS'!$J$5:$J$39,MATCH("professional_studies_per_customer",'01_ASSUMPTIONS'!$B$5:$B$39,0)) | H5: =D5*INDEX('01_ASSUMPTIONS'!$J$5:$J$39,MATCH("enterprise_studies_per_customer",'01_ASSUMPTIONS'!$B$5:$B$39,0)) | I5: =SUM(F5:H5) | J5: =B5*INDEX('01_ASSUMPTIONS'!$J$5:$J$39,MATCH("starter_fee",'01_ASSUMPTIONS'!$B$5:$B$39,0))+C5*INDEX('01_ASSUMPTIONS'!$J$5:$J$39,MATCH("professional_fee",'01_ASSUMPTIONS'!$B$5:$B$39,0))+D5*INDEX('01_ASSUMPTIONS'!$J$5:$J$39,MATCH("enterprise_fee",'01_ASSUMPTIONS'!$B$5:$B$39,0)) | K5: =MAX(F5-B5*INDEX('01_ASSUMPTIONS'!$J$5:$J$39,MATCH("starter_included_studies",'01_ASSUMPTIONS'!$B$5:$B$39,0)),0)*INDEX('01_ASSUMPTIONS'!$J$5:$J$39,MATCH("starter_overage_fee",'01_ASSUMPTIONS'!$B$5:$B$39,0))+MAX(G5-C5*INDEX('01_ASSUMPTIONS'!$J$5:$J$39,MATCH("professional_included_studies",'01_ASSUMPTIONS'!$B$5:$B$39,0)),0)*INDEX('01_ASSUMPTIONS'!$J$5:$J$39,MATCH("professional_overage_fee",'01_ASSUMPTIONS'!$B$5:$B$39,0))+MAX(H5-D5*INDEX('01_ASSUMPTIONS'!$J$5:$J$39,MATCH("enterprise_included_studies",'01_ASSUMPTIONS'!$B$5:$B$39,0)),0)*INDEX('01_ASSUMPTIONS'!$J$5:$J$39,MATCH("enterprise_overage_fee",'01_ASSUMPTIONS'!$B$5:$B$39,0)) | L5: =J5+K5 | M5: =I5*INDEX('01_ASSUMPTIONS'!$J$5:$J$39,MATCH("cloud_cost_per_study",'01_ASSUMPTIONS'!$B$5:$B$39,0)) | N5: =I5*INDEX('01_ASSUMPTIONS'!$J$5:$J$39,MATCH("storage_cost_per_study",'01_ASSUMPTIONS'!$B$5:$B$39,0)) | O5: =I5*INDEX('01_ASSUMPTIONS'!$J$5:$J$39,MATCH("ai_processing_cost_per_study",'01_ASSUMPTIONS'!$B$5:$B$39,0)) | P5: =E5*INDEX('01_ASSUMPTIONS'!$J$5:$J$39,MATCH("variable_support_per_customer",'01_ASSUMPTIONS'!$B$5:$B$39,0)) | Q5: =SUM(M5:P5) | R5: =INDEX('01_ASSUMPTIONS'!$J$5:$J$39,MATCH("fixed_infra",'01_ASSUMPTIONS'!$B$5:$B$39,0)) | S5: =INDEX('01_ASSUMPTIONS'!$J$5:$J$39,MATCH("software_maintenance",'01_ASSUMPTIONS'!$B$5:$B$39,0)) | T5: =INDEX('01_ASSUMPTIONS'!$J$5:$J$39,MATCH("base_support",'01_ASSUMPTIONS'!$B$5:$B$39,0)) | U5: =INDEX('01_ASSUMPTIONS'!$J$5:$J$39,MATCH("admin",'01_ASSUMPTIONS'!$B$5:$B$39,0)) | V5: =INDEX('01_ASSUMPTIONS'!$J$5:$J$39,MATCH("commercial_marketing",'01_ASSUMPTIONS'!$B$5:$B$39,0)) | W5: =INDEX('01_ASSUMPTIONS'!$J$5:$J$39,MATCH("other_fixed",'01_ASSUMPTIONS'!$B$5:$B$39,0)) | X5: =SUM(R5:W5) | Y5: =L5-Q5-X5 | Z5: =0 | AA5: =Y5-Z5 | AB5: =1/(1+'01_ASSUMPTIONS'!$E$2)^A5 | AC5: =AA5*AB5 | AD5: =AD4+AA5 | AE5: =IF(Y5>=0,"Yes","No") | AF5: =IF(AD5>=0,"Yes","No")
A6: =5 | B6: =B5*(1-INDEX('01_ASSUMPTIONS'!$J$5:$J$39,MATCH("monthly_churn",'01_ASSUMPTIONS'!$B$5:$B$39,0)))+INDEX('01_ASSUMPTIONS'!$J$5:$J$39,MATCH("starter_monthly_acquisition",'01_ASSUMPTIONS'!$B$5:$B$39,0)) | C6: =C5*(1-INDEX('01_ASSUMPTIONS'!$J$5:$J$39,MATCH("monthly_churn",'01_ASSUMPTIONS'!$B$5:$B$39,0)))+INDEX('01_ASSUMPTIONS'!$J$5:$J$39,MATCH("professional_monthly_acquisition",'01_ASSUMPTIONS'!$B$5:$B$39,0)) | D6: =D5*(1-INDEX('01_ASSUMPTIONS'!$J$5:$J$39,MATCH("monthly_churn",'01_ASSUMPTIONS'!$B$5:$B$39,0)))+INDEX('01_ASSUMPTIONS'!$J$5:$J$39,MATCH("enterprise_monthly_acquisition",'01_ASSUMPTIONS'!$B$5:$B$39,0)) | E6: =SUM(B6:D6) | F6: =B6*INDEX('01_ASSUMPTIONS'!$J$5:$J$39,MATCH("starter_studies_per_customer",'01_ASSUMPTIONS'!$B$5:$B$39,0)) | G6: =C6*INDEX('01_ASSUMPTIONS'!$J$5:$J$39,MATCH("professional_studies_per_customer",'01_ASSUMPTIONS'!$B$5:$B$39,0)) | H6: =D6*INDEX('01_ASSUMPTIONS'!$J$5:$J$39,MATCH("enterprise_studies_per_customer",'01_ASSUMPTIONS'!$B$5:$B$39,0)) | I6: =SUM(F6:H6) | J6: =B6*INDEX('01_ASSUMPTIONS'!$J$5:$J$39,MATCH("starter_fee",'01_ASSUMPTIONS'!$B$5:$B$39,0))+C6*INDEX('01_ASSUMPTIONS'!$J$5:$J$39,MATCH("professional_fee",'01_ASSUMPTIONS'!$B$5:$B$39,0))+D6*INDEX('01_ASSUMPTIONS'!$J$5:$J$39,MATCH("enterprise_fee",'01_ASSUMPTIONS'!$B$5:$B$39,0)) | K6: =MAX(F6-B6*INDEX('01_ASSUMPTIONS'!$J$5:$J$39,MATCH("starter_included_studies",'01_ASSUMPTIONS'!$B$5:$B$39,0)),0)*INDEX('01_ASSUMPTIONS'!$J$5:$J$39,MATCH("starter_overage_fee",'01_ASSUMPTIONS'!$B$5:$B$39,0))+MAX(G6-C6*INDEX('01_ASSUMPTIONS'!$J$5:$J$39,MATCH("professional_included_studies",'01_ASSUMPTIONS'!$B$5:$B$39,0)),0)*INDEX('01_ASSUMPTIONS'!$J$5:$J$39,MATCH("professional_overage_fee",'01_ASSUMPTIONS'!$B$5:$B$39,0))+MAX(H6-D6*INDEX('01_ASSUMPTIONS'!$J$5:$J$39,MATCH("enterprise_included_studies",'01_ASSUMPTIONS'!$B$5:$B$39,0)),0)*INDEX('01_ASSUMPTIONS'!$J$5:$J$39,MATCH("enterprise_overage_fee",'01_ASSUMPTIONS'!$B$5:$B$39,0)) | L6: =J6+K6 | M6: =I6*INDEX('01_ASSUMPTIONS'!$J$5:$J$39,MATCH("cloud_cost_per_study",'01_ASSUMPTIONS'!$B$5:$B$39,0)) | N6: =I6*INDEX('01_ASSUMPTIONS'!$J$5:$J$39,MATCH("storage_cost_per_study",'01_ASSUMPTIONS'!$B$5:$B$39,0)) | O6: =I6*INDEX('01_ASSUMPTIONS'!$J$5:$J$39,MATCH("ai_processing_cost_per_study",'01_ASSUMPTIONS'!$B$5:$B$39,0)) | P6: =E6*INDEX('01_ASSUMPTIONS'!$J$5:$J$39,MATCH("variable_support_per_customer",'01_ASSUMPTIONS'!$B$5:$B$39,0)) | Q6: =SUM(M6:P6) | R6: =INDEX('01_ASSUMPTIONS'!$J$5:$J$39,MATCH("fixed_infra",'01_ASSUMPTIONS'!$B$5:$B$39,0)) | S6: =INDEX('01_ASSUMPTIONS'!$J$5:$J$39,MATCH("software_maintenance",'01_ASSUMPTIONS'!$B$5:$B$39,0)) | T6: =INDEX('01_ASSUMPTIONS'!$J$5:$J$39,MATCH("base_support",'01_ASSUMPTIONS'!$B$5:$B$39,0)) | U6: =INDEX('01_ASSUMPTIONS'!$J$5:$J$39,MATCH("admin",'01_ASSUMPTIONS'!$B$5:$B$39,0)) | V6: =INDEX('01_ASSUMPTIONS'!$J$5:$J$39,MATCH("commercial_marketing",'01_ASSUMPTIONS'!$B$5:$B$39,0)) | W6: =INDEX('01_ASSUMPTIONS'!$J$5:$J$39,MATCH("other_fixed",'01_ASSUMPTIONS'!$B$5:$B$39,0)) | X6: =SUM(R6:W6) | Y6: =L6-Q6-X6 | Z6: =0 | AA6: =Y6-Z6 | AB6: =1/(1+'01_ASSUMPTIONS'!$E$2)^A6 | AC6: =AA6*AB6 | AD6: =AD5+AA6 | AE6: =IF(Y6>=0,"Yes","No") | AF6: =IF(AD6>=0,"Yes","No")
A7: =6 | B7: =B6*(1-INDEX('01_ASSUMPTIONS'!$J$5:$J$39,MATCH("monthly_churn",'01_ASSUMPTIONS'!$B$5:$B$39,0)))+INDEX('01_ASSUMPTIONS'!$J$5:$J$39,MATCH("starter_monthly_acquisition",'01_ASSUMPTIONS'!$B$5:$B$39,0)) | C7: =C6*(1-INDEX('01_ASSUMPTIONS'!$J$5:$J$39,MATCH("monthly_churn",'01_ASSUMPTIONS'!$B$5:$B$39,0)))+INDEX('01_ASSUMPTIONS'!$J$5:$J$39,MATCH("professional_monthly_acquisition",'01_ASSUMPTIONS'!$B$5:$B$39,0)) | D7: =D6*(1-INDEX('01_ASSUMPTIONS'!$J$5:$J$39,MATCH("monthly_churn",'01_ASSUMPTIONS'!$B$5:$B$39,0)))+INDEX('01_ASSUMPTIONS'!$J$5:$J$39,MATCH("enterprise_monthly_acquisition",'01_ASSUMPTIONS'!$B$5:$B$39,0)) | E7: =SUM(B7:D7) | F7: =B7*INDEX('01_ASSUMPTIONS'!$J$5:$J$39,MATCH("starter_studies_per_customer",'01_ASSUMPTIONS'!$B$5:$B$39,0)) | G7: =C7*INDEX('01_ASSUMPTIONS'!$J$5:$J$39,MATCH("professional_studies_per_customer",'01_ASSUMPTIONS'!$B$5:$B$39,0)) | H7: =D7*INDEX('01_ASSUMPTIONS'!$J$5:$J$39,MATCH("enterprise_studies_per_customer",'01_ASSUMPTIONS'!$B$5:$B$39,0)) | I7: =SUM(F7:H7) | J7: =B7*INDEX('01_ASSUMPTIONS'!$J$5:$J$39,MATCH("starter_fee",'01_ASSUMPTIONS'!$B$5:$B$39,0))+C7*INDEX('01_ASSUMPTIONS'!$J$5:$J$39,MATCH("professional_fee",'01_ASSUMPTIONS'!$B$5:$B$39,0))+D7*INDEX('01_ASSUMPTIONS'!$J$5:$J$39,MATCH("enterprise_fee",'01_ASSUMPTIONS'!$B$5:$B$39,0)) | K7: =MAX(F7-B7*INDEX('01_ASSUMPTIONS'!$J$5:$J$39,MATCH("starter_included_studies",'01_ASSUMPTIONS'!$B$5:$B$39,0)),0)*INDEX('01_ASSUMPTIONS'!$J$5:$J$39,MATCH("starter_overage_fee",'01_ASSUMPTIONS'!$B$5:$B$39,0))+MAX(G7-C7*INDEX('01_ASSUMPTIONS'!$J$5:$J$39,MATCH("professional_included_studies",'01_ASSUMPTIONS'!$B$5:$B$39,0)),0)*INDEX('01_ASSUMPTIONS'!$J$5:$J$39,MATCH("professional_overage_fee",'01_ASSUMPTIONS'!$B$5:$B$39,0))+MAX(H7-D7*INDEX('01_ASSUMPTIONS'!$J$5:$J$39,MATCH("enterprise_included_studies",'01_ASSUMPTIONS'!$B$5:$B$39,0)),0)*INDEX('01_ASSUMPTIONS'!$J$5:$J$39,MATCH("enterprise_overage_fee",'01_ASSUMPTIONS'!$B$5:$B$39,0)) | L7: =J7+K7 | M7: =I7*INDEX('01_ASSUMPTIONS'!$J$5:$J$39,MATCH("cloud_cost_per_study",'01_ASSUMPTIONS'!$B$5:$B$39,0)) | N7: =I7*INDEX('01_ASSUMPTIONS'!$J$5:$J$39,MATCH("storage_cost_per_study",'01_ASSUMPTIONS'!$B$5:$B$39,0)) | O7: =I7*INDEX('01_ASSUMPTIONS'!$J$5:$J$39,MATCH("ai_processing_cost_per_study",'01_ASSUMPTIONS'!$B$5:$B$39,0)) | P7: =E7*INDEX('01_ASSUMPTIONS'!$J$5:$J$39,MATCH("variable_support_per_customer",'01_ASSUMPTIONS'!$B$5:$B$39,0)) | Q7: =SUM(M7:P7) | R7: =INDEX('01_ASSUMPTIONS'!$J$5:$J$39,MATCH("fixed_infra",'01_ASSUMPTIONS'!$B$5:$B$39,0)) | S7: =INDEX('01_ASSUMPTIONS'!$J$5:$J$39,MATCH("software_maintenance",'01_ASSUMPTIONS'!$B$5:$B$39,0)) | T7: =INDEX('01_ASSUMPTIONS'!$J$5:$J$39,MATCH("base_support",'01_ASSUMPTIONS'!$B$5:$B$39,0)) | U7: =INDEX('01_ASSUMPTIONS'!$J$5:$J$39,MATCH("admin",'01_ASSUMPTIONS'!$B$5:$B$39,0)) | V7: =INDEX('01_ASSUMPTIONS'!$J$5:$J$39,MATCH("commercial_marketing",'01_ASSUMPTIONS'!$B$5:$B$39,0)) | W7: =INDEX('01_ASSUMPTIONS'!$J$5:$J$39,MATCH("other_fixed",'01_ASSUMPTIONS'!$B$5:$B$39,0)) | X7: =SUM(R7:W7) | Y7: =L7-Q7-X7 | Z7: =0 | AA7: =Y7-Z7 | AB7: =1/(1+'01_ASSUMPTIONS'!$E$2)^A7 | AC7: =AA7*AB7 | AD7: =AD6+AA7 | AE7: =IF(Y7>=0,"Yes","No") | AF7: =IF(AD7>=0,"Yes","No")
A8: =7 | B8: =B7*(1-INDEX('01_ASSUMPTIONS'!$J$5:$J$39,MATCH("monthly_churn",'01_ASSUMPTIONS'!$B$5:$B$39,0)))+INDEX('01_ASSUMPTIONS'!$J$5:$J$39,MATCH("starter_monthly_acquisition",'01_ASSUMPTIONS'!$B$5:$B$39,0)) | C8: =C7*(1-INDEX('01_ASSUMPTIONS'!$J$5:$J$39,MATCH("monthly_churn",'01_ASSUMPTIONS'!$B$5:$B$39,0)))+INDEX('01_ASSUMPTIONS'!$J$5:$J$39,MATCH("professional_monthly_acquisition",'01_ASSUMPTIONS'!$B$5:$B$39,0)) | D8: =D7*(1-INDEX('01_ASSUMPTIONS'!$J$5:$J$39,MATCH("monthly_churn",'01_ASSUMPTIONS'!$B$5:$B$39,0)))+INDEX('01_ASSUMPTIONS'!$J$5:$J$39,MATCH("enterprise_monthly_acquisition",'01_ASSUMPTIONS'!$B$5:$B$39,0)) | E8: =SUM(B8:D8) | F8: =B8*INDEX('01_ASSUMPTIONS'!$J$5:$J$39,MATCH("starter_studies_per_customer",'01_ASSUMPTIONS'!$B$5:$B$39,0)) | G8: =C8*INDEX('01_ASSUMPTIONS'!$J$5:$J$39,MATCH("professional_studies_per_customer",'01_ASSUMPTIONS'!$B$5:$B$39,0)) | H8: =D8*INDEX('01_ASSUMPTIONS'!$J$5:$J$39,MATCH("enterprise_studies_per_customer",'01_ASSUMPTIONS'!$B$5:$B$39,0)) | I8: =SUM(F8:H8) | J8: =B8*INDEX('01_ASSUMPTIONS'!$J$5:$J$39,MATCH("starter_fee",'01_ASSUMPTIONS'!$B$5:$B$39,0))+C8*INDEX('01_ASSUMPTIONS'!$J$5:$J$39,MATCH("professional_fee",'01_ASSUMPTIONS'!$B$5:$B$39,0))+D8*INDEX('01_ASSUMPTIONS'!$J$5:$J$39,MATCH("enterprise_fee",'01_ASSUMPTIONS'!$B$5:$B$39,0)) | K8: =MAX(F8-B8*INDEX('01_ASSUMPTIONS'!$J$5:$J$39,MATCH("starter_included_studies",'01_ASSUMPTIONS'!$B$5:$B$39,0)),0)*INDEX('01_ASSUMPTIONS'!$J$5:$J$39,MATCH("starter_overage_fee",'01_ASSUMPTIONS'!$B$5:$B$39,0))+MAX(G8-C8*INDEX('01_ASSUMPTIONS'!$J$5:$J$39,MATCH("professional_included_studies",'01_ASSUMPTIONS'!$B$5:$B$39,0)),0)*INDEX('01_ASSUMPTIONS'!$J$5:$J$39,MATCH("professional_overage_fee",'01_ASSUMPTIONS'!$B$5:$B$39,0))+MAX(H8-D8*INDEX('01_ASSUMPTIONS'!$J$5:$J$39,MATCH("enterprise_included_studies",'01_ASSUMPTIONS'!$B$5:$B$39,0)),0)*INDEX('01_ASSUMPTIONS'!$J$5:$J$39,MATCH("enterprise_overage_fee",'01_ASSUMPTIONS'!$B$5:$B$39,0)) | L8: =J8+K8 | M8: =I8*INDEX('01_ASSUMPTIONS'!$J$5:$J$39,MATCH("cloud_cost_per_study",'01_ASSUMPTIONS'!$B$5:$B$39,0)) | N8: =I8*INDEX('01_ASSUMPTIONS'!$J$5:$J$39,MATCH("storage_cost_per_study",'01_ASSUMPTIONS'!$B$5:$B$39,0)) | O8: =I8*INDEX('01_ASSUMPTIONS'!$J$5:$J$39,MATCH("ai_processing_cost_per_study",'01_ASSUMPTIONS'!$B$5:$B$39,0)) | P8: =E8*INDEX('01_ASSUMPTIONS'!$J$5:$J$39,MATCH("variable_support_per_customer",'01_ASSUMPTIONS'!$B$5:$B$39,0)) | Q8: =SUM(M8:P8) | R8: =INDEX('01_ASSUMPTIONS'!$J$5:$J$39,MATCH("fixed_infra",'01_ASSUMPTIONS'!$B$5:$B$39,0)) | S8: =INDEX('01_ASSUMPTIONS'!$J$5:$J$39,MATCH("software_maintenance",'01_ASSUMPTIONS'!$B$5:$B$39,0)) | T8: =INDEX('01_ASSUMPTIONS'!$J$5:$J$39,MATCH("base_support",'01_ASSUMPTIONS'!$B$5:$B$39,0)) | U8: =INDEX('01_ASSUMPTIONS'!$J$5:$J$39,MATCH("admin",'01_ASSUMPTIONS'!$B$5:$B$39,0)) | V8: =INDEX('01_ASSUMPTIONS'!$J$5:$J$39,MATCH("commercial_marketing",'01_ASSUMPTIONS'!$B$5:$B$39,0)) | W8: =INDEX('01_ASSUMPTIONS'!$J$5:$J$39,MATCH("other_fixed",'01_ASSUMPTIONS'!$B$5:$B$39,0)) | X8: =SUM(R8:W8) | Y8: =L8-Q8-X8 | Z8: =0 | AA8: =Y8-Z8 | AB8: =1/(1+'01_ASSUMPTIONS'!$E$2)^A8 | AC8: =AA8*AB8 | AD8: =AD7+AA8 | AE8: =IF(Y8>=0,"Yes","No") | AF8: =IF(AD8>=0,"Yes","No")
A9: =8 | B9: =B8*(1-INDEX('01_ASSUMPTIONS'!$J$5:$J$39,MATCH("monthly_churn",'01_ASSUMPTIONS'!$B$5:$B$39,0)))+INDEX('01_ASSUMPTIONS'!$J$5:$J$39,MATCH("starter_monthly_acquisition",'01_ASSUMPTIONS'!$B$5:$B$39,0)) | C9: =C8*(1-INDEX('01_ASSUMPTIONS'!$J$5:$J$39,MATCH("monthly_churn",'01_ASSUMPTIONS'!$B$5:$B$39,0)))+INDEX('01_ASSUMPTIONS'!$J$5:$J$39,MATCH("professional_monthly_acquisition",'01_ASSUMPTIONS'!$B$5:$B$39,0)) | D9: =D8*(1-INDEX('01_ASSUMPTIONS'!$J$5:$J$39,MATCH("monthly_churn",'01_ASSUMPTIONS'!$B$5:$B$39,0)))+INDEX('01_ASSUMPTIONS'!$J$5:$J$39,MATCH("enterprise_monthly_acquisition",'01_ASSUMPTIONS'!$B$5:$B$39,0)) | E9: =SUM(B9:D9) | F9: =B9*INDEX('01_ASSUMPTIONS'!$J$5:$J$39,MATCH("starter_studies_per_customer",'01_ASSUMPTIONS'!$B$5:$B$39,0)) | G9: =C9*INDEX('01_ASSUMPTIONS'!$J$5:$J$39,MATCH("professional_studies_per_customer",'01_ASSUMPTIONS'!$B$5:$B$39,0)) | H9: =D9*INDEX('01_ASSUMPTIONS'!$J$5:$J$39,MATCH("enterprise_studies_per_customer",'01_ASSUMPTIONS'!$B$5:$B$39,0)) | I9: =SUM(F9:H9) | J9: =B9*INDEX('01_ASSUMPTIONS'!$J$5:$J$39,MATCH("starter_fee",'01_ASSUMPTIONS'!$B$5:$B$39,0))+C9*INDEX('01_ASSUMPTIONS'!$J$5:$J$39,MATCH("professional_fee",'01_ASSUMPTIONS'!$B$5:$B$39,0))+D9*INDEX('01_ASSUMPTIONS'!$J$5:$J$39,MATCH("enterprise_fee",'01_ASSUMPTIONS'!$B$5:$B$39,0)) | K9: =MAX(F9-B9*INDEX('01_ASSUMPTIONS'!$J$5:$J$39,MATCH("starter_included_studies",'01_ASSUMPTIONS'!$B$5:$B$39,0)),0)*INDEX('01_ASSUMPTIONS'!$J$5:$J$39,MATCH("starter_overage_fee",'01_ASSUMPTIONS'!$B$5:$B$39,0))+MAX(G9-C9*INDEX('01_ASSUMPTIONS'!$J$5:$J$39,MATCH("professional_included_studies",'01_ASSUMPTIONS'!$B$5:$B$39,0)),0)*INDEX('01_ASSUMPTIONS'!$J$5:$J$39,MATCH("professional_overage_fee",'01_ASSUMPTIONS'!$B$5:$B$39,0))+MAX(H9-D9*INDEX('01_ASSUMPTIONS'!$J$5:$J$39,MATCH("enterprise_included_studies",'01_ASSUMPTIONS'!$B$5:$B$39,0)),0)*INDEX('01_ASSUMPTIONS'!$J$5:$J$39,MATCH("enterprise_overage_fee",'01_ASSUMPTIONS'!$B$5:$B$39,0)) | L9: =J9+K9 | M9: =I9*INDEX('01_ASSUMPTIONS'!$J$5:$J$39,MATCH("cloud_cost_per_study",'01_ASSUMPTIONS'!$B$5:$B$39,0)) | N9: =I9*INDEX('01_ASSUMPTIONS'!$J$5:$J$39,MATCH("storage_cost_per_study",'01_ASSUMPTIONS'!$B$5:$B$39,0)) | O9: =I9*INDEX('01_ASSUMPTIONS'!$J$5:$J$39,MATCH("ai_processing_cost_per_study",'01_ASSUMPTIONS'!$B$5:$B$39,0)) | P9: =E9*INDEX('01_ASSUMPTIONS'!$J$5:$J$39,MATCH("variable_support_per_customer",'01_ASSUMPTIONS'!$B$5:$B$39,0)) | Q9: =SUM(M9:P9) | R9: =INDEX('01_ASSUMPTIONS'!$J$5:$J$39,MATCH("fixed_infra",'01_ASSUMPTIONS'!$B$5:$B$39,0)) | S9: =INDEX('01_ASSUMPTIONS'!$J$5:$J$39,MATCH("software_maintenance",'01_ASSUMPTIONS'!$B$5:$B$39,0)) | T9: =INDEX('01_ASSUMPTIONS'!$J$5:$J$39,MATCH("base_support",'01_ASSUMPTIONS'!$B$5:$B$39,0)) | U9: =INDEX('01_ASSUMPTIONS'!$J$5:$J$39,MATCH("admin",'01_ASSUMPTIONS'!$B$5:$B$39,0)) | V9: =INDEX('01_ASSUMPTIONS'!$J$5:$J$39,MATCH("commercial_marketing",'01_ASSUMPTIONS'!$B$5:$B$39,0)) | W9: =INDEX('01_ASSUMPTIONS'!$J$5:$J$39,MATCH("other_fixed",'01_ASSUMPTIONS'!$B$5:$B$39,0)) | X9: =SUM(R9:W9) | Y9: =L9-Q9-X9 | Z9: =0 | AA9: =Y9-Z9 | AB9: =1/(1+'01_ASSUMPTIONS'!$E$2)^A9 | AC9: =AA9*AB9 | AD9: =AD8+AA9 | AE9: =IF(Y9>=0,"Yes","No") | AF9: =IF(AD9>=0,"Yes","No")
A10: =9 | B10: =B9*(1-INDEX('01_ASSUMPTIONS'!$J$5:$J$39,MATCH("monthly_churn",'01_ASSUMPTIONS'!$B$5:$B$39,0)))+INDEX('01_ASSUMPTIONS'!$J$5:$J$39,MATCH("starter_monthly_acquisition",'01_ASSUMPTIONS'!$B$5:$B$39,0)) | C10: =C9*(1-INDEX('01_ASSUMPTIONS'!$J$5:$J$39,MATCH("monthly_churn",'01_ASSUMPTIONS'!$B$5:$B$39,0)))+INDEX('01_ASSUMPTIONS'!$J$5:$J$39,MATCH("professional_monthly_acquisition",'01_ASSUMPTIONS'!$B$5:$B$39,0)) | D10: =D9*(1-INDEX('01_ASSUMPTIONS'!$J$5:$J$39,MATCH("monthly_churn",'01_ASSUMPTIONS'!$B$5:$B$39,0)))+INDEX('01_ASSUMPTIONS'!$J$5:$J$39,MATCH("enterprise_monthly_acquisition",'01_ASSUMPTIONS'!$B$5:$B$39,0)) | E10: =SUM(B10:D10) | F10: =B10*INDEX('01_ASSUMPTIONS'!$J$5:$J$39,MATCH("starter_studies_per_customer",'01_ASSUMPTIONS'!$B$5:$B$39,0)) | G10: =C10*INDEX('01_ASSUMPTIONS'!$J$5:$J$39,MATCH("professional_studies_per_customer",'01_ASSUMPTIONS'!$B$5:$B$39,0)) | H10: =D10*INDEX('01_ASSUMPTIONS'!$J$5:$J$39,MATCH("enterprise_studies_per_customer",'01_ASSUMPTIONS'!$B$5:$B$39,0)) | I10: =SUM(F10:H10) | J10: =B10*INDEX('01_ASSUMPTIONS'!$J$5:$J$39,MATCH("starter_fee",'01_ASSUMPTIONS'!$B$5:$B$39,0))+C10*INDEX('01_ASSUMPTIONS'!$J$5:$J$39,MATCH("professional_fee",'01_ASSUMPTIONS'!$B$5:$B$39,0))+D10*INDEX('01_ASSUMPTIONS'!$J$5:$J$39,MATCH("enterprise_fee",'01_ASSUMPTIONS'!$B$5:$B$39,0)) | K10: =MAX(F10-B10*INDEX('01_ASSUMPTIONS'!$J$5:$J$39,MATCH("starter_included_studies",'01_ASSUMPTIONS'!$B$5:$B$39,0)),0)*INDEX('01_ASSUMPTIONS'!$J$5:$J$39,MATCH("starter_overage_fee",'01_ASSUMPTIONS'!$B$5:$B$39,0))+MAX(G10-C10*INDEX('01_ASSUMPTIONS'!$J$5:$J$39,MATCH("professional_included_studies",'01_ASSUMPTIONS'!$B$5:$B$39,0)),0)*INDEX('01_ASSUMPTIONS'!$J$5:$J$39,MATCH("professional_overage_fee",'01_ASSUMPTIONS'!$B$5:$B$39,0))+MAX(H10-D10*INDEX('01_ASSUMPTIONS'!$J$5:$J$39,MATCH("enterprise_included_studies",'01_ASSUMPTIONS'!$B$5:$B$39,0)),0)*INDEX('01_ASSUMPTIONS'!$J$5:$J$39,MATCH("enterprise_overage_fee",'01_ASSUMPTIONS'!$B$5:$B$39,0)) | L10: =J10+K10 | M10: =I10*INDEX('01_ASSUMPTIONS'!$J$5:$J$39,MATCH("cloud_cost_per_study",'01_ASSUMPTIONS'!$B$5:$B$39,0)) | N10: =I10*INDEX('01_ASSUMPTIONS'!$J$5:$J$39,MATCH("storage_cost_per_study",'01_ASSUMPTIONS'!$B$5:$B$39,0)) | O10: =I10*INDEX('01_ASSUMPTIONS'!$J$5:$J$39,MATCH("ai_processing_cost_per_study",'01_ASSUMPTIONS'!$B$5:$B$39,0)) | P10: =E10*INDEX('01_ASSUMPTIONS'!$J$5:$J$39,MATCH("variable_support_per_customer",'01_ASSUMPTIONS'!$B$5:$B$39,0)) | Q10: =SUM(M10:P10) | R10: =INDEX('01_ASSUMPTIONS'!$J$5:$J$39,MATCH("fixed_infra",'01_ASSUMPTIONS'!$B$5:$B$39,0)) | S10: =INDEX('01_ASSUMPTIONS'!$J$5:$J$39,MATCH("software_maintenance",'01_ASSUMPTIONS'!$B$5:$B$39,0)) | T10: =INDEX('01_ASSUMPTIONS'!$J$5:$J$39,MATCH("base_support",'01_ASSUMPTIONS'!$B$5:$B$39,0)) | U10: =INDEX('01_ASSUMPTIONS'!$J$5:$J$39,MATCH("admin",'01_ASSUMPTIONS'!$B$5:$B$39,0)) | V10: =INDEX('01_ASSUMPTIONS'!$J$5:$J$39,MATCH("commercial_marketing",'01_ASSUMPTIONS'!$B$5:$B$39,0)) | W10: =INDEX('01_ASSUMPTIONS'!$J$5:$J$39,MATCH("other_fixed",'01_ASSUMPTIONS'!$B$5:$B$39,0)) | X10: =SUM(R10:W10) | Y10: =L10-Q10-X10 | Z10: =0 | AA10: =Y10-Z10 | AB10: =1/(1+'01_ASSUMPTIONS'!$E$2)^A10 | AC10: =AA10*AB10 | AD10: =AD9+AA10 | AE10: =IF(Y10>=0,"Yes","No") | AF10: =IF(AD10>=0,"Yes","No")
A11: =10 | B11: =B10*(1-INDEX('01_ASSUMPTIONS'!$J$5:$J$39,MATCH("monthly_churn",'01_ASSUMPTIONS'!$B$5:$B$39,0)))+INDEX('01_ASSUMPTIONS'!$J$5:$J$39,MATCH("starter_monthly_acquisition",'01_ASSUMPTIONS'!$B$5:$B$39,0)) | C11: =C10*(1-INDEX('01_ASSUMPTIONS'!$J$5:$J$39,MATCH("monthly_churn",'01_ASSUMPTIONS'!$B$5:$B$39,0)))+INDEX('01_ASSUMPTIONS'!$J$5:$J$39,MATCH("professional_monthly_acquisition",'01_ASSUMPTIONS'!$B$5:$B$39,0)) | D11: =D10*(1-INDEX('01_ASSUMPTIONS'!$J$5:$J$39,MATCH("monthly_churn",'01_ASSUMPTIONS'!$B$5:$B$39,0)))+INDEX('01_ASSUMPTIONS'!$J$5:$J$39,MATCH("enterprise_monthly_acquisition",'01_ASSUMPTIONS'!$B$5:$B$39,0)) | E11: =SUM(B11:D11) | F11: =B11*INDEX('01_ASSUMPTIONS'!$J$5:$J$39,MATCH("starter_studies_per_customer",'01_ASSUMPTIONS'!$B$5:$B$39,0)) | G11: =C11*INDEX('01_ASSUMPTIONS'!$J$5:$J$39,MATCH("professional_studies_per_customer",'01_ASSUMPTIONS'!$B$5:$B$39,0)) | H11: =D11*INDEX('01_ASSUMPTIONS'!$J$5:$J$39,MATCH("enterprise_studies_per_customer",'01_ASSUMPTIONS'!$B$5:$B$39,0)) | I11: =SUM(F11:H11) | J11: =B11*INDEX('01_ASSUMPTIONS'!$J$5:$J$39,MATCH("starter_fee",'01_ASSUMPTIONS'!$B$5:$B$39,0))+C11*INDEX('01_ASSUMPTIONS'!$J$5:$J$39,MATCH("professional_fee",'01_ASSUMPTIONS'!$B$5:$B$39,0))+D11*INDEX('01_ASSUMPTIONS'!$J$5:$J$39,MATCH("enterprise_fee",'01_ASSUMPTIONS'!$B$5:$B$39,0)) | K11: =MAX(F11-B11*INDEX('01_ASSUMPTIONS'!$J$5:$J$39,MATCH("starter_included_studies",'01_ASSUMPTIONS'!$B$5:$B$39,0)),0)*INDEX('01_ASSUMPTIONS'!$J$5:$J$39,MATCH("starter_overage_fee",'01_ASSUMPTIONS'!$B$5:$B$39,0))+MAX(G11-C11*INDEX('01_ASSUMPTIONS'!$J$5:$J$39,MATCH("professional_included_studies",'01_ASSUMPTIONS'!$B$5:$B$39,0)),0)*INDEX('01_ASSUMPTIONS'!$J$5:$J$39,MATCH("professional_overage_fee",'01_ASSUMPTIONS'!$B$5:$B$39,0))+MAX(H11-D11*INDEX('01_ASSUMPTIONS'!$J$5:$J$39,MATCH("enterprise_included_studies",'01_ASSUMPTIONS'!$B$5:$B$39,0)),0)*INDEX('01_ASSUMPTIONS'!$J$5:$J$39,MATCH("enterprise_overage_fee",'01_ASSUMPTIONS'!$B$5:$B$39,0)) | L11: =J11+K11 | M11: =I11*INDEX('01_ASSUMPTIONS'!$J$5:$J$39,MATCH("cloud_cost_per_study",'01_ASSUMPTIONS'!$B$5:$B$39,0)) | N11: =I11*INDEX('01_ASSUMPTIONS'!$J$5:$J$39,MATCH("storage_cost_per_study",'01_ASSUMPTIONS'!$B$5:$B$39,0)) | O11: =I11*INDEX('01_ASSUMPTIONS'!$J$5:$J$39,MATCH("ai_processing_cost_per_study",'01_ASSUMPTIONS'!$B$5:$B$39,0)) | P11: =E11*INDEX('01_ASSUMPTIONS'!$J$5:$J$39,MATCH("variable_support_per_customer",'01_ASSUMPTIONS'!$B$5:$B$39,0)) | Q11: =SUM(M11:P11) | R11: =INDEX('01_ASSUMPTIONS'!$J$5:$J$39,MATCH("fixed_infra",'01_ASSUMPTIONS'!$B$5:$B$39,0)) | S11: =INDEX('01_ASSUMPTIONS'!$J$5:$J$39,MATCH("software_maintenance",'01_ASSUMPTIONS'!$B$5:$B$39,0)) | T11: =INDEX('01_ASSUMPTIONS'!$J$5:$J$39,MATCH("base_support",'01_ASSUMPTIONS'!$B$5:$B$39,0)) | U11: =INDEX('01_ASSUMPTIONS'!$J$5:$J$39,MATCH("admin",'01_ASSUMPTIONS'!$B$5:$B$39,0)) | V11: =INDEX('01_ASSUMPTIONS'!$J$5:$J$39,MATCH("commercial_marketing",'01_ASSUMPTIONS'!$B$5:$B$39,0)) | W11: =INDEX('01_ASSUMPTIONS'!$J$5:$J$39,MATCH("other_fixed",'01_ASSUMPTIONS'!$B$5:$B$39,0)) | X11: =SUM(R11:W11) | Y11: =L11-Q11-X11 | Z11: =0 | AA11: =Y11-Z11 | AB11: =1/(1+'01_ASSUMPTIONS'!$E$2)^A11 | AC11: =AA11*AB11 | AD11: =AD10+AA11 | AE11: =IF(Y11>=0,"Yes","No") | AF11: =IF(AD11>=0,"Yes","No")
A12: =11 | B12: =B11*(1-INDEX('01_ASSUMPTIONS'!$J$5:$J$39,MATCH("monthly_churn",'01_ASSUMPTIONS'!$B$5:$B$39,0)))+INDEX('01_ASSUMPTIONS'!$J$5:$J$39,MATCH("starter_monthly_acquisition",'01_ASSUMPTIONS'!$B$5:$B$39,0)) | C12: =C11*(1-INDEX('01_ASSUMPTIONS'!$J$5:$J$39,MATCH("monthly_churn",'01_ASSUMPTIONS'!$B$5:$B$39,0)))+INDEX('01_ASSUMPTIONS'!$J$5:$J$39,MATCH("professional_monthly_acquisition",'01_ASSUMPTIONS'!$B$5:$B$39,0)) | D12: =D11*(1-INDEX('01_ASSUMPTIONS'!$J$5:$J$39,MATCH("monthly_churn",'01_ASSUMPTIONS'!$B$5:$B$39,0)))+INDEX('01_ASSUMPTIONS'!$J$5:$J$39,MATCH("enterprise_monthly_acquisition",'01_ASSUMPTIONS'!$B$5:$B$39,0)) | E12: =SUM(B12:D12) | F12: =B12*INDEX('01_ASSUMPTIONS'!$J$5:$J$39,MATCH("starter_studies_per_customer",'01_ASSUMPTIONS'!$B$5:$B$39,0)) | G12: =C12*INDEX('01_ASSUMPTIONS'!$J$5:$J$39,MATCH("professional_studies_per_customer",'01_ASSUMPTIONS'!$B$5:$B$39,0)) | H12: =D12*INDEX('01_ASSUMPTIONS'!$J$5:$J$39,MATCH("enterprise_studies_per_customer",'01_ASSUMPTIONS'!$B$5:$B$39,0)) | I12: =SUM(F12:H12) | J12: =B12*INDEX('01_ASSUMPTIONS'!$J$5:$J$39,MATCH("starter_fee",'01_ASSUMPTIONS'!$B$5:$B$39,0))+C12*INDEX('01_ASSUMPTIONS'!$J$5:$J$39,MATCH("professional_fee",'01_ASSUMPTIONS'!$B$5:$B$39,0))+D12*INDEX('01_ASSUMPTIONS'!$J$5:$J$39,MATCH("enterprise_fee",'01_ASSUMPTIONS'!$B$5:$B$39,0)) | K12: =MAX(F12-B12*INDEX('01_ASSUMPTIONS'!$J$5:$J$39,MATCH("starter_included_studies",'01_ASSUMPTIONS'!$B$5:$B$39,0)),0)*INDEX('01_ASSUMPTIONS'!$J$5:$J$39,MATCH("starter_overage_fee",'01_ASSUMPTIONS'!$B$5:$B$39,0))+MAX(G12-C12*INDEX('01_ASSUMPTIONS'!$J$5:$J$39,MATCH("professional_included_studies",'01_ASSUMPTIONS'!$B$5:$B$39,0)),0)*INDEX('01_ASSUMPTIONS'!$J$5:$J$39,MATCH("professional_overage_fee",'01_ASSUMPTIONS'!$B$5:$B$39,0))+MAX(H12-D12*INDEX('01_ASSUMPTIONS'!$J$5:$J$39,MATCH("enterprise_included_studies",'01_ASSUMPTIONS'!$B$5:$B$39,0)),0)*INDEX('01_ASSUMPTIONS'!$J$5:$J$39,MATCH("enterprise_overage_fee",'01_ASSUMPTIONS'!$B$5:$B$39,0)) | L12: =J12+K12 | M12: =I12*INDEX('01_ASSUMPTIONS'!$J$5:$J$39,MATCH("cloud_cost_per_study",'01_ASSUMPTIONS'!$B$5:$B$39,0)) | N12: =I12*INDEX('01_ASSUMPTIONS'!$J$5:$J$39,MATCH("storage_cost_per_study",'01_ASSUMPTIONS'!$B$5:$B$39,0)) | O12: =I12*INDEX('01_ASSUMPTIONS'!$J$5:$J$39,MATCH("ai_processing_cost_per_study",'01_ASSUMPTIONS'!$B$5:$B$39,0)) | P12: =E12*INDEX('01_ASSUMPTIONS'!$J$5:$J$39,MATCH("variable_support_per_customer",'01_ASSUMPTIONS'!$B$5:$B$39,0)) | Q12: =SUM(M12:P12) | R12: =INDEX('01_ASSUMPTIONS'!$J$5:$J$39,MATCH("fixed_infra",'01_ASSUMPTIONS'!$B$5:$B$39,0)) | S12: =INDEX('01_ASSUMPTIONS'!$J$5:$J$39,MATCH("software_maintenance",'01_ASSUMPTIONS'!$B$5:$B$39,0)) | T12: =INDEX('01_ASSUMPTIONS'!$J$5:$J$39,MATCH("base_support",'01_ASSUMPTIONS'!$B$5:$B$39,0)) | U12: =INDEX('01_ASSUMPTIONS'!$J$5:$J$39,MATCH("admin",'01_ASSUMPTIONS'!$B$5:$B$39,0)) | V12: =INDEX('01_ASSUMPTIONS'!$J$5:$J$39,MATCH("commercial_marketing",'01_ASSUMPTIONS'!$B$5:$B$39,0)) | W12: =INDEX('01_ASSUMPTIONS'!$J$5:$J$39,MATCH("other_fixed",'01_ASSUMPTIONS'!$B$5:$B$39,0)) | X12: =SUM(R12:W12) | Y12: =L12-Q12-X12 | Z12: =0 | AA12: =Y12-Z12 | AB12: =1/(1+'01_ASSUMPTIONS'!$E$2)^A12 | AC12: =AA12*AB12 | AD12: =AD11+AA12 | AE12: =IF(Y12>=0,"Yes","No") | AF12: =IF(AD12>=0,"Yes","No")
A13: =12 | B13: =B12*(1-INDEX('01_ASSUMPTIONS'!$J$5:$J$39,MATCH("monthly_churn",'01_ASSUMPTIONS'!$B$5:$B$39,0)))+INDEX('01_ASSUMPTIONS'!$J$5:$J$39,MATCH("starter_monthly_acquisition",'01_ASSUMPTIONS'!$B$5:$B$39,0)) | C13: =C12*(1-INDEX('01_ASSUMPTIONS'!$J$5:$J$39,MATCH("monthly_churn",'01_ASSUMPTIONS'!$B$5:$B$39,0)))+INDEX('01_ASSUMPTIONS'!$J$5:$J$39,MATCH("professional_monthly_acquisition",'01_ASSUMPTIONS'!$B$5:$B$39,0)) | D13: =D12*(1-INDEX('01_ASSUMPTIONS'!$J$5:$J$39,MATCH("monthly_churn",'01_ASSUMPTIONS'!$B$5:$B$39,0)))+INDEX('01_ASSUMPTIONS'!$J$5:$J$39,MATCH("enterprise_monthly_acquisition",'01_ASSUMPTIONS'!$B$5:$B$39,0)) | E13: =SUM(B13:D13) | F13: =B13*INDEX('01_ASSUMPTIONS'!$J$5:$J$39,MATCH("starter_studies_per_customer",'01_ASSUMPTIONS'!$B$5:$B$39,0)) | G13: =C13*INDEX('01_ASSUMPTIONS'!$J$5:$J$39,MATCH("professional_studies_per_customer",'01_ASSUMPTIONS'!$B$5:$B$39,0)) | H13: =D13*INDEX('01_ASSUMPTIONS'!$J$5:$J$39,MATCH("enterprise_studies_per_customer",'01_ASSUMPTIONS'!$B$5:$B$39,0)) | I13: =SUM(F13:H13) | J13: =B13*INDEX('01_ASSUMPTIONS'!$J$5:$J$39,MATCH("starter_fee",'01_ASSUMPTIONS'!$B$5:$B$39,0))+C13*INDEX('01_ASSUMPTIONS'!$J$5:$J$39,MATCH("professional_fee",'01_ASSUMPTIONS'!$B$5:$B$39,0))+D13*INDEX('01_ASSUMPTIONS'!$J$5:$J$39,MATCH("enterprise_fee",'01_ASSUMPTIONS'!$B$5:$B$39,0)) | K13: =MAX(F13-B13*INDEX('01_ASSUMPTIONS'!$J$5:$J$39,MATCH("starter_included_studies",'01_ASSUMPTIONS'!$B$5:$B$39,0)),0)*INDEX('01_ASSUMPTIONS'!$J$5:$J$39,MATCH("starter_overage_fee",'01_ASSUMPTIONS'!$B$5:$B$39,0))+MAX(G13-C13*INDEX('01_ASSUMPTIONS'!$J$5:$J$39,MATCH("professional_included_studies",'01_ASSUMPTIONS'!$B$5:$B$39,0)),0)*INDEX('01_ASSUMPTIONS'!$J$5:$J$39,MATCH("professional_overage_fee",'01_ASSUMPTIONS'!$B$5:$B$39,0))+MAX(H13-D13*INDEX('01_ASSUMPTIONS'!$J$5:$J$39,MATCH("enterprise_included_studies",'01_ASSUMPTIONS'!$B$5:$B$39,0)),0)*INDEX('01_ASSUMPTIONS'!$J$5:$J$39,MATCH("enterprise_overage_fee",'01_ASSUMPTIONS'!$B$5:$B$39,0)) | L13: =J13+K13 | M13: =I13*INDEX('01_ASSUMPTIONS'!$J$5:$J$39,MATCH("cloud_cost_per_study",'01_ASSUMPTIONS'!$B$5:$B$39,0)) | N13: =I13*INDEX('01_ASSUMPTIONS'!$J$5:$J$39,MATCH("storage_cost_per_study",'01_ASSUMPTIONS'!$B$5:$B$39,0)) | O13: =I13*INDEX('01_ASSUMPTIONS'!$J$5:$J$39,MATCH("ai_processing_cost_per_study",'01_ASSUMPTIONS'!$B$5:$B$39,0)) | P13: =E13*INDEX('01_ASSUMPTIONS'!$J$5:$J$39,MATCH("variable_support_per_customer",'01_ASSUMPTIONS'!$B$5:$B$39,0)) | Q13: =SUM(M13:P13) | R13: =INDEX('01_ASSUMPTIONS'!$J$5:$J$39,MATCH("fixed_infra",'01_ASSUMPTIONS'!$B$5:$B$39,0)) | S13: =INDEX('01_ASSUMPTIONS'!$J$5:$J$39,MATCH("software_maintenance",'01_ASSUMPTIONS'!$B$5:$B$39,0)) | T13: =INDEX('01_ASSUMPTIONS'!$J$5:$J$39,MATCH("base_support",'01_ASSUMPTIONS'!$B$5:$B$39,0)) | U13: =INDEX('01_ASSUMPTIONS'!$J$5:$J$39,MATCH("admin",'01_ASSUMPTIONS'!$B$5:$B$39,0)) | V13: =INDEX('01_ASSUMPTIONS'!$J$5:$J$39,MATCH("commercial_marketing",'01_ASSUMPTIONS'!$B$5:$B$39,0)) | W13: =INDEX('01_ASSUMPTIONS'!$J$5:$J$39,MATCH("other_fixed",'01_ASSUMPTIONS'!$B$5:$B$39,0)) | X13: =SUM(R13:W13) | Y13: =L13-Q13-X13 | Z13: =0 | AA13: =Y13-Z13 | AB13: =1/(1+'01_ASSUMPTIONS'!$E$2)^A13 | AC13: =AA13*AB13 | AD13: =AD12+AA13 | AE13: =IF(Y13>=0,"Yes","No") | AF13: =IF(AD13>=0,"Yes","No")
A14: =13 | B14: =B13*(1-INDEX('01_ASSUMPTIONS'!$J$5:$J$39,MATCH("monthly_churn",'01_ASSUMPTIONS'!$B$5:$B$39,0)))+INDEX('01_ASSUMPTIONS'!$J$5:$J$39,MATCH("starter_monthly_acquisition",'01_ASSUMPTIONS'!$B$5:$B$39,0)) | C14: =C13*(1-INDEX('01_ASSUMPTIONS'!$J$5:$J$39,MATCH("monthly_churn",'01_ASSUMPTIONS'!$B$5:$B$39,0)))+INDEX('01_ASSUMPTIONS'!$J$5:$J$39,MATCH("professional_monthly_acquisition",'01_ASSUMPTIONS'!$B$5:$B$39,0)) | D14: =D13*(1-INDEX('01_ASSUMPTIONS'!$J$5:$J$39,MATCH("monthly_churn",'01_ASSUMPTIONS'!$B$5:$B$39,0)))+INDEX('01_ASSUMPTIONS'!$J$5:$J$39,MATCH("enterprise_monthly_acquisition",'01_ASSUMPTIONS'!$B$5:$B$39,0)) | E14: =SUM(B14:D14) | F14: =B14*INDEX('01_ASSUMPTIONS'!$J$5:$J$39,MATCH("starter_studies_per_customer",'01_ASSUMPTIONS'!$B$5:$B$39,0)) | G14: =C14*INDEX('01_ASSUMPTIONS'!$J$5:$J$39,MATCH("professional_studies_per_customer",'01_ASSUMPTIONS'!$B$5:$B$39,0)) | H14: =D14*INDEX('01_ASSUMPTIONS'!$J$5:$J$39,MATCH("enterprise_studies_per_customer",'01_ASSUMPTIONS'!$B$5:$B$39,0)) | I14: =SUM(F14:H14) | J14: =B14*INDEX('01_ASSUMPTIONS'!$J$5:$J$39,MATCH("starter_fee",'01_ASSUMPTIONS'!$B$5:$B$39,0))+C14*INDEX('01_ASSUMPTIONS'!$J$5:$J$39,MATCH("professional_fee",'01_ASSUMPTIONS'!$B$5:$B$39,0))+D14*INDEX('01_ASSUMPTIONS'!$J$5:$J$39,MATCH("enterprise_fee",'01_ASSUMPTIONS'!$B$5:$B$39,0)) | K14: =MAX(F14-B14*INDEX('01_ASSUMPTIONS'!$J$5:$J$39,MATCH("starter_included_studies",'01_ASSUMPTIONS'!$B$5:$B$39,0)),0)*INDEX('01_ASSUMPTIONS'!$J$5:$J$39,MATCH("starter_overage_fee",'01_ASSUMPTIONS'!$B$5:$B$39,0))+MAX(G14-C14*INDEX('01_ASSUMPTIONS'!$J$5:$J$39,MATCH("professional_included_studies",'01_ASSUMPTIONS'!$B$5:$B$39,0)),0)*INDEX('01_ASSUMPTIONS'!$J$5:$J$39,MATCH("professional_overage_fee",'01_ASSUMPTIONS'!$B$5:$B$39,0))+MAX(H14-D14*INDEX('01_ASSUMPTIONS'!$J$5:$J$39,MATCH("enterprise_included_studies",'01_ASSUMPTIONS'!$B$5:$B$39,0)),0)*INDEX('01_ASSUMPTIONS'!$J$5:$J$39,MATCH("enterprise_overage_fee",'01_ASSUMPTIONS'!$B$5:$B$39,0)) | L14: =J14+K14 | M14: =I14*INDEX('01_ASSUMPTIONS'!$J$5:$J$39,MATCH("cloud_cost_per_study",'01_ASSUMPTIONS'!$B$5:$B$39,0)) | N14: =I14*INDEX('01_ASSUMPTIONS'!$J$5:$J$39,MATCH("storage_cost_per_study",'01_ASSUMPTIONS'!$B$5:$B$39,0)) | O14: =I14*INDEX('01_ASSUMPTIONS'!$J$5:$J$39,MATCH("ai_processing_cost_per_study",'01_ASSUMPTIONS'!$B$5:$B$39,0)) | P14: =E14*INDEX('01_ASSUMPTIONS'!$J$5:$J$39,MATCH("variable_support_per_customer",'01_ASSUMPTIONS'!$B$5:$B$39,0)) | Q14: =SUM(M14:P14) | R14: =INDEX('01_ASSUMPTIONS'!$J$5:$J$39,MATCH("fixed_infra",'01_ASSUMPTIONS'!$B$5:$B$39,0)) | S14: =INDEX('01_ASSUMPTIONS'!$J$5:$J$39,MATCH("software_maintenance",'01_ASSUMPTIONS'!$B$5:$B$39,0)) | T14: =INDEX('01_ASSUMPTIONS'!$J$5:$J$39,MATCH("base_support",'01_ASSUMPTIONS'!$B$5:$B$39,0)) | U14: =INDEX('01_ASSUMPTIONS'!$J$5:$J$39,MATCH("admin",'01_ASSUMPTIONS'!$B$5:$B$39,0)) | V14: =INDEX('01_ASSUMPTIONS'!$J$5:$J$39,MATCH("commercial_marketing",'01_ASSUMPTIONS'!$B$5:$B$39,0)) | W14: =INDEX('01_ASSUMPTIONS'!$J$5:$J$39,MATCH("other_fixed",'01_ASSUMPTIONS'!$B$5:$B$39,0)) | X14: =SUM(R14:W14) | Y14: =L14-Q14-X14 | Z14: =0 | AA14: =Y14-Z14 | AB14: =1/(1+'01_ASSUMPTIONS'!$E$2)^A14 | AC14: =AA14*AB14 | AD14: =AD13+AA14 | AE14: =IF(Y14>=0,"Yes","No") | AF14: =IF(AD14>=0,"Yes","No")
A15: =14 | B15: =B14*(1-INDEX('01_ASSUMPTIONS'!$J$5:$J$39,MATCH("monthly_churn",'01_ASSUMPTIONS'!$B$5:$B$39,0)))+INDEX('01_ASSUMPTIONS'!$J$5:$J$39,MATCH("starter_monthly_acquisition",'01_ASSUMPTIONS'!$B$5:$B$39,0)) | C15: =C14*(1-INDEX('01_ASSUMPTIONS'!$J$5:$J$39,MATCH("monthly_churn",'01_ASSUMPTIONS'!$B$5:$B$39,0)))+INDEX('01_ASSUMPTIONS'!$J$5:$J$39,MATCH("professional_monthly_acquisition",'01_ASSUMPTIONS'!$B$5:$B$39,0)) | D15: =D14*(1-INDEX('01_ASSUMPTIONS'!$J$5:$J$39,MATCH("monthly_churn",'01_ASSUMPTIONS'!$B$5:$B$39,0)))+INDEX('01_ASSUMPTIONS'!$J$5:$J$39,MATCH("enterprise_monthly_acquisition",'01_ASSUMPTIONS'!$B$5:$B$39,0)) | E15: =SUM(B15:D15) | F15: =B15*INDEX('01_ASSUMPTIONS'!$J$5:$J$39,MATCH("starter_studies_per_customer",'01_ASSUMPTIONS'!$B$5:$B$39,0)) | G15: =C15*INDEX('01_ASSUMPTIONS'!$J$5:$J$39,MATCH("professional_studies_per_customer",'01_ASSUMPTIONS'!$B$5:$B$39,0)) | H15: =D15*INDEX('01_ASSUMPTIONS'!$J$5:$J$39,MATCH("enterprise_studies_per_customer",'01_ASSUMPTIONS'!$B$5:$B$39,0)) | I15: =SUM(F15:H15) | J15: =B15*INDEX('01_ASSUMPTIONS'!$J$5:$J$39,MATCH("starter_fee",'01_ASSUMPTIONS'!$B$5:$B$39,0))+C15*INDEX('01_ASSUMPTIONS'!$J$5:$J$39,MATCH("professional_fee",'01_ASSUMPTIONS'!$B$5:$B$39,0))+D15*INDEX('01_ASSUMPTIONS'!$J$5:$J$39,MATCH("enterprise_fee",'01_ASSUMPTIONS'!$B$5:$B$39,0)) | K15: =MAX(F15-B15*INDEX('01_ASSUMPTIONS'!$J$5:$J$39,MATCH("starter_included_studies",'01_ASSUMPTIONS'!$B$5:$B$39,0)),0)*INDEX('01_ASSUMPTIONS'!$J$5:$J$39,MATCH("starter_overage_fee",'01_ASSUMPTIONS'!$B$5:$B$39,0))+MAX(G15-C15*INDEX('01_ASSUMPTIONS'!$J$5:$J$39,MATCH("professional_included_studies",'01_ASSUMPTIONS'!$B$5:$B$39,0)),0)*INDEX('01_ASSUMPTIONS'!$J$5:$J$39,MATCH("professional_overage_fee",'01_ASSUMPTIONS'!$B$5:$B$39,0))+MAX(H15-D15*INDEX('01_ASSUMPTIONS'!$J$5:$J$39,MATCH("enterprise_included_studies",'01_ASSUMPTIONS'!$B$5:$B$39,0)),0)*INDEX('01_ASSUMPTIONS'!$J$5:$J$39,MATCH("enterprise_overage_fee",'01_ASSUMPTIONS'!$B$5:$B$39,0)) | L15: =J15+K15 | M15: =I15*INDEX('01_ASSUMPTIONS'!$J$5:$J$39,MATCH("cloud_cost_per_study",'01_ASSUMPTIONS'!$B$5:$B$39,0)) | N15: =I15*INDEX('01_ASSUMPTIONS'!$J$5:$J$39,MATCH("storage_cost_per_study",'01_ASSUMPTIONS'!$B$5:$B$39,0)) | O15: =I15*INDEX('01_ASSUMPTIONS'!$J$5:$J$39,MATCH("ai_processing_cost_per_study",'01_ASSUMPTIONS'!$B$5:$B$39,0)) | P15: =E15*INDEX('01_ASSUMPTIONS'!$J$5:$J$39,MATCH("variable_support_per_customer",'01_ASSUMPTIONS'!$B$5:$B$39,0)) | Q15: =SUM(M15:P15) | R15: =INDEX('01_ASSUMPTIONS'!$J$5:$J$39,MATCH("fixed_infra",'01_ASSUMPTIONS'!$B$5:$B$39,0)) | S15: =INDEX('01_ASSUMPTIONS'!$J$5:$J$39,MATCH("software_maintenance",'01_ASSUMPTIONS'!$B$5:$B$39,0)) | T15: =INDEX('01_ASSUMPTIONS'!$J$5:$J$39,MATCH("base_support",'01_ASSUMPTIONS'!$B$5:$B$39,0)) | U15: =INDEX('01_ASSUMPTIONS'!$J$5:$J$39,MATCH("admin",'01_ASSUMPTIONS'!$B$5:$B$39,0)) | V15: =INDEX('01_ASSUMPTIONS'!$J$5:$J$39,MATCH("commercial_marketing",'01_ASSUMPTIONS'!$B$5:$B$39,0)) | W15: =INDEX('01_ASSUMPTIONS'!$J$5:$J$39,MATCH("other_fixed",'01_ASSUMPTIONS'!$B$5:$B$39,0)) | X15: =SUM(R15:W15) | Y15: =L15-Q15-X15 | Z15: =0 | AA15: =Y15-Z15 | AB15: =1/(1+'01_ASSUMPTIONS'!$E$2)^A15 | AC15: =AA15*AB15 | AD15: =AD14+AA15 | AE15: =IF(Y15>=0,"Yes","No") | AF15: =IF(AD15>=0,"Yes","No")
A16: =15 | B16: =B15*(1-INDEX('01_ASSUMPTIONS'!$J$5:$J$39,MATCH("monthly_churn",'01_ASSUMPTIONS'!$B$5:$B$39,0)))+INDEX('01_ASSUMPTIONS'!$J$5:$J$39,MATCH("starter_monthly_acquisition",'01_ASSUMPTIONS'!$B$5:$B$39,0)) | C16: =C15*(1-INDEX('01_ASSUMPTIONS'!$J$5:$J$39,MATCH("monthly_churn",'01_ASSUMPTIONS'!$B$5:$B$39,0)))+INDEX('01_ASSUMPTIONS'!$J$5:$J$39,MATCH("professional_monthly_acquisition",'01_ASSUMPTIONS'!$B$5:$B$39,0)) | D16: =D15*(1-INDEX('01_ASSUMPTIONS'!$J$5:$J$39,MATCH("monthly_churn",'01_ASSUMPTIONS'!$B$5:$B$39,0)))+INDEX('01_ASSUMPTIONS'!$J$5:$J$39,MATCH("enterprise_monthly_acquisition",'01_ASSUMPTIONS'!$B$5:$B$39,0)) | E16: =SUM(B16:D16) | F16: =B16*INDEX('01_ASSUMPTIONS'!$J$5:$J$39,MATCH("starter_studies_per_customer",'01_ASSUMPTIONS'!$B$5:$B$39,0)) | G16: =C16*INDEX('01_ASSUMPTIONS'!$J$5:$J$39,MATCH("professional_studies_per_customer",'01_ASSUMPTIONS'!$B$5:$B$39,0)) | H16: =D16*INDEX('01_ASSUMPTIONS'!$J$5:$J$39,MATCH("enterprise_studies_per_customer",'01_ASSUMPTIONS'!$B$5:$B$39,0)) | I16: =SUM(F16:H16) | J16: =B16*INDEX('01_ASSUMPTIONS'!$J$5:$J$39,MATCH("starter_fee",'01_ASSUMPTIONS'!$B$5:$B$39,0))+C16*INDEX('01_ASSUMPTIONS'!$J$5:$J$39,MATCH("professional_fee",'01_ASSUMPTIONS'!$B$5:$B$39,0))+D16*INDEX('01_ASSUMPTIONS'!$J$5:$J$39,MATCH("enterprise_fee",'01_ASSUMPTIONS'!$B$5:$B$39,0)) | K16: =MAX(F16-B16*INDEX('01_ASSUMPTIONS'!$J$5:$J$39,MATCH("starter_included_studies",'01_ASSUMPTIONS'!$B$5:$B$39,0)),0)*INDEX('01_ASSUMPTIONS'!$J$5:$J$39,MATCH("starter_overage_fee",'01_ASSUMPTIONS'!$B$5:$B$39,0))+MAX(G16-C16*INDEX('01_ASSUMPTIONS'!$J$5:$J$39,MATCH("professional_included_studies",'01_ASSUMPTIONS'!$B$5:$B$39,0)),0)*INDEX('01_ASSUMPTIONS'!$J$5:$J$39,MATCH("professional_overage_fee",'01_ASSUMPTIONS'!$B$5:$B$39,0))+MAX(H16-D16*INDEX('01_ASSUMPTIONS'!$J$5:$J$39,MATCH("enterprise_included_studies",'01_ASSUMPTIONS'!$B$5:$B$39,0)),0)*INDEX('01_ASSUMPTIONS'!$J$5:$J$39,MATCH("enterprise_overage_fee",'01_ASSUMPTIONS'!$B$5:$B$39,0)) | L16: =J16+K16 | M16: =I16*INDEX('01_ASSUMPTIONS'!$J$5:$J$39,MATCH("cloud_cost_per_study",'01_ASSUMPTIONS'!$B$5:$B$39,0)) | N16: =I16*INDEX('01_ASSUMPTIONS'!$J$5:$J$39,MATCH("storage_cost_per_study",'01_ASSUMPTIONS'!$B$5:$B$39,0)) | O16: =I16*INDEX('01_ASSUMPTIONS'!$J$5:$J$39,MATCH("ai_processing_cost_per_study",'01_ASSUMPTIONS'!$B$5:$B$39,0)) | P16: =E16*INDEX('01_ASSUMPTIONS'!$J$5:$J$39,MATCH("variable_support_per_customer",'01_ASSUMPTIONS'!$B$5:$B$39,0)) | Q16: =SUM(M16:P16) | R16: =INDEX('01_ASSUMPTIONS'!$J$5:$J$39,MATCH("fixed_infra",'01_ASSUMPTIONS'!$B$5:$B$39,0)) | S16: =INDEX('01_ASSUMPTIONS'!$J$5:$J$39,MATCH("software_maintenance",'01_ASSUMPTIONS'!$B$5:$B$39,0)) | T16: =INDEX('01_ASSUMPTIONS'!$J$5:$J$39,MATCH("base_support",'01_ASSUMPTIONS'!$B$5:$B$39,0)) | U16: =INDEX('01_ASSUMPTIONS'!$J$5:$J$39,MATCH("admin",'01_ASSUMPTIONS'!$B$5:$B$39,0)) | V16: =INDEX('01_ASSUMPTIONS'!$J$5:$J$39,MATCH("commercial_marketing",'01_ASSUMPTIONS'!$B$5:$B$39,0)) | W16: =INDEX('01_ASSUMPTIONS'!$J$5:$J$39,MATCH("other_fixed",'01_ASSUMPTIONS'!$B$5:$B$39,0)) | X16: =SUM(R16:W16) | Y16: =L16-Q16-X16 | Z16: =0 | AA16: =Y16-Z16 | AB16: =1/(1+'01_ASSUMPTIONS'!$E$2)^A16 | AC16: =AA16*AB16 | AD16: =AD15+AA16 | AE16: =IF(Y16>=0,"Yes","No") | AF16: =IF(AD16>=0,"Yes","No")
A17: =16 | B17: =B16*(1-INDEX('01_ASSUMPTIONS'!$J$5:$J$39,MATCH("monthly_churn",'01_ASSUMPTIONS'!$B$5:$B$39,0)))+INDEX('01_ASSUMPTIONS'!$J$5:$J$39,MATCH("starter_monthly_acquisition",'01_ASSUMPTIONS'!$B$5:$B$39,0)) | C17: =C16*(1-INDEX('01_ASSUMPTIONS'!$J$5:$J$39,MATCH("monthly_churn",'01_ASSUMPTIONS'!$B$5:$B$39,0)))+INDEX('01_ASSUMPTIONS'!$J$5:$J$39,MATCH("professional_monthly_acquisition",'01_ASSUMPTIONS'!$B$5:$B$39,0)) | D17: =D16*(1-INDEX('01_ASSUMPTIONS'!$J$5:$J$39,MATCH("monthly_churn",'01_ASSUMPTIONS'!$B$5:$B$39,0)))+INDEX('01_ASSUMPTIONS'!$J$5:$J$39,MATCH("enterprise_monthly_acquisition",'01_ASSUMPTIONS'!$B$5:$B$39,0)) | E17: =SUM(B17:D17) | F17: =B17*INDEX('01_ASSUMPTIONS'!$J$5:$J$39,MATCH("starter_studies_per_customer",'01_ASSUMPTIONS'!$B$5:$B$39,0)) | G17: =C17*INDEX('01_ASSUMPTIONS'!$J$5:$J$39,MATCH("professional_studies_per_customer",'01_ASSUMPTIONS'!$B$5:$B$39,0)) | H17: =D17*INDEX('01_ASSUMPTIONS'!$J$5:$J$39,MATCH("enterprise_studies_per_customer",'01_ASSUMPTIONS'!$B$5:$B$39,0)) | I17: =SUM(F17:H17) | J17: =B17*INDEX('01_ASSUMPTIONS'!$J$5:$J$39,MATCH("starter_fee",'01_ASSUMPTIONS'!$B$5:$B$39,0))+C17*INDEX('01_ASSUMPTIONS'!$J$5:$J$39,MATCH("professional_fee",'01_ASSUMPTIONS'!$B$5:$B$39,0))+D17*INDEX('01_ASSUMPTIONS'!$J$5:$J$39,MATCH("enterprise_fee",'01_ASSUMPTIONS'!$B$5:$B$39,0)) | K17: =MAX(F17-B17*INDEX('01_ASSUMPTIONS'!$J$5:$J$39,MATCH("starter_included_studies",'01_ASSUMPTIONS'!$B$5:$B$39,0)),0)*INDEX('01_ASSUMPTIONS'!$J$5:$J$39,MATCH("starter_overage_fee",'01_ASSUMPTIONS'!$B$5:$B$39,0))+MAX(G17-C17*INDEX('01_ASSUMPTIONS'!$J$5:$J$39,MATCH("professional_included_studies",'01_ASSUMPTIONS'!$B$5:$B$39,0)),0)*INDEX('01_ASSUMPTIONS'!$J$5:$J$39,MATCH("professional_overage_fee",'01_ASSUMPTIONS'!$B$5:$B$39,0))+MAX(H17-D17*INDEX('01_ASSUMPTIONS'!$J$5:$J$39,MATCH("enterprise_included_studies",'01_ASSUMPTIONS'!$B$5:$B$39,0)),0)*INDEX('01_ASSUMPTIONS'!$J$5:$J$39,MATCH("enterprise_overage_fee",'01_ASSUMPTIONS'!$B$5:$B$39,0)) | L17: =J17+K17 | M17: =I17*INDEX('01_ASSUMPTIONS'!$J$5:$J$39,MATCH("cloud_cost_per_study",'01_ASSUMPTIONS'!$B$5:$B$39,0)) | N17: =I17*INDEX('01_ASSUMPTIONS'!$J$5:$J$39,MATCH("storage_cost_per_study",'01_ASSUMPTIONS'!$B$5:$B$39,0)) | O17: =I17*INDEX('01_ASSUMPTIONS'!$J$5:$J$39,MATCH("ai_processing_cost_per_study",'01_ASSUMPTIONS'!$B$5:$B$39,0)) | P17: =E17*INDEX('01_ASSUMPTIONS'!$J$5:$J$39,MATCH("variable_support_per_customer",'01_ASSUMPTIONS'!$B$5:$B$39,0)) | Q17: =SUM(M17:P17) | R17: =INDEX('01_ASSUMPTIONS'!$J$5:$J$39,MATCH("fixed_infra",'01_ASSUMPTIONS'!$B$5:$B$39,0)) | S17: =INDEX('01_ASSUMPTIONS'!$J$5:$J$39,MATCH("software_maintenance",'01_ASSUMPTIONS'!$B$5:$B$39,0)) | T17: =INDEX('01_ASSUMPTIONS'!$J$5:$J$39,MATCH("base_support",'01_ASSUMPTIONS'!$B$5:$B$39,0)) | U17: =INDEX('01_ASSUMPTIONS'!$J$5:$J$39,MATCH("admin",'01_ASSUMPTIONS'!$B$5:$B$39,0)) | V17: =INDEX('01_ASSUMPTIONS'!$J$5:$J$39,MATCH("commercial_marketing",'01_ASSUMPTIONS'!$B$5:$B$39,0)) | W17: =INDEX('01_ASSUMPTIONS'!$J$5:$J$39,MATCH("other_fixed",'01_ASSUMPTIONS'!$B$5:$B$39,0)) | X17: =SUM(R17:W17) | Y17: =L17-Q17-X17 | Z17: =0 | AA17: =Y17-Z17 | AB17: =1/(1+'01_ASSUMPTIONS'!$E$2)^A17 | AC17: =AA17*AB17 | AD17: =AD16+AA17 | AE17: =IF(Y17>=0,"Yes","No") | AF17: =IF(AD17>=0,"Yes","No")
A18: =17 | B18: =B17*(1-INDEX('01_ASSUMPTIONS'!$J$5:$J$39,MATCH("monthly_churn",'01_ASSUMPTIONS'!$B$5:$B$39,0)))+INDEX('01_ASSUMPTIONS'!$J$5:$J$39,MATCH("starter_monthly_acquisition",'01_ASSUMPTIONS'!$B$5:$B$39,0)) | C18: =C17*(1-INDEX('01_ASSUMPTIONS'!$J$5:$J$39,MATCH("monthly_churn",'01_ASSUMPTIONS'!$B$5:$B$39,0)))+INDEX('01_ASSUMPTIONS'!$J$5:$J$39,MATCH("professional_monthly_acquisition",'01_ASSUMPTIONS'!$B$5:$B$39,0)) | D18: =D17*(1-INDEX('01_ASSUMPTIONS'!$J$5:$J$39,MATCH("monthly_churn",'01_ASSUMPTIONS'!$B$5:$B$39,0)))+INDEX('01_ASSUMPTIONS'!$J$5:$J$39,MATCH("enterprise_monthly_acquisition",'01_ASSUMPTIONS'!$B$5:$B$39,0)) | E18: =SUM(B18:D18) | F18: =B18*INDEX('01_ASSUMPTIONS'!$J$5:$J$39,MATCH("starter_studies_per_customer",'01_ASSUMPTIONS'!$B$5:$B$39,0)) | G18: =C18*INDEX('01_ASSUMPTIONS'!$J$5:$J$39,MATCH("professional_studies_per_customer",'01_ASSUMPTIONS'!$B$5:$B$39,0)) | H18: =D18*INDEX('01_ASSUMPTIONS'!$J$5:$J$39,MATCH("enterprise_studies_per_customer",'01_ASSUMPTIONS'!$B$5:$B$39,0)) | I18: =SUM(F18:H18) | J18: =B18*INDEX('01_ASSUMPTIONS'!$J$5:$J$39,MATCH("starter_fee",'01_ASSUMPTIONS'!$B$5:$B$39,0))+C18*INDEX('01_ASSUMPTIONS'!$J$5:$J$39,MATCH("professional_fee",'01_ASSUMPTIONS'!$B$5:$B$39,0))+D18*INDEX('01_ASSUMPTIONS'!$J$5:$J$39,MATCH("enterprise_fee",'01_ASSUMPTIONS'!$B$5:$B$39,0)) | K18: =MAX(F18-B18*INDEX('01_ASSUMPTIONS'!$J$5:$J$39,MATCH("starter_included_studies",'01_ASSUMPTIONS'!$B$5:$B$39,0)),0)*INDEX('01_ASSUMPTIONS'!$J$5:$J$39,MATCH("starter_overage_fee",'01_ASSUMPTIONS'!$B$5:$B$39,0))+MAX(G18-C18*INDEX('01_ASSUMPTIONS'!$J$5:$J$39,MATCH("professional_included_studies",'01_ASSUMPTIONS'!$B$5:$B$39,0)),0)*INDEX('01_ASSUMPTIONS'!$J$5:$J$39,MATCH("professional_overage_fee",'01_ASSUMPTIONS'!$B$5:$B$39,0))+MAX(H18-D18*INDEX('01_ASSUMPTIONS'!$J$5:$J$39,MATCH("enterprise_included_studies",'01_ASSUMPTIONS'!$B$5:$B$39,0)),0)*INDEX('01_ASSUMPTIONS'!$J$5:$J$39,MATCH("enterprise_overage_fee",'01_ASSUMPTIONS'!$B$5:$B$39,0)) | L18: =J18+K18 | M18: =I18*INDEX('01_ASSUMPTIONS'!$J$5:$J$39,MATCH("cloud_cost_per_study",'01_ASSUMPTIONS'!$B$5:$B$39,0)) | N18: =I18*INDEX('01_ASSUMPTIONS'!$J$5:$J$39,MATCH("storage_cost_per_study",'01_ASSUMPTIONS'!$B$5:$B$39,0)) | O18: =I18*INDEX('01_ASSUMPTIONS'!$J$5:$J$39,MATCH("ai_processing_cost_per_study",'01_ASSUMPTIONS'!$B$5:$B$39,0)) | P18: =E18*INDEX('01_ASSUMPTIONS'!$J$5:$J$39,MATCH("variable_support_per_customer",'01_ASSUMPTIONS'!$B$5:$B$39,0)) | Q18: =SUM(M18:P18) | R18: =INDEX('01_ASSUMPTIONS'!$J$5:$J$39,MATCH("fixed_infra",'01_ASSUMPTIONS'!$B$5:$B$39,0)) | S18: =INDEX('01_ASSUMPTIONS'!$J$5:$J$39,MATCH("software_maintenance",'01_ASSUMPTIONS'!$B$5:$B$39,0)) | T18: =INDEX('01_ASSUMPTIONS'!$J$5:$J$39,MATCH("base_support",'01_ASSUMPTIONS'!$B$5:$B$39,0)) | U18: =INDEX('01_ASSUMPTIONS'!$J$5:$J$39,MATCH("admin",'01_ASSUMPTIONS'!$B$5:$B$39,0)) | V18: =INDEX('01_ASSUMPTIONS'!$J$5:$J$39,MATCH("commercial_marketing",'01_ASSUMPTIONS'!$B$5:$B$39,0)) | W18: =INDEX('01_ASSUMPTIONS'!$J$5:$J$39,MATCH("other_fixed",'01_ASSUMPTIONS'!$B$5:$B$39,0)) | X18: =SUM(R18:W18) | Y18: =L18-Q18-X18 | Z18: =0 | AA18: =Y18-Z18 | AB18: =1/(1+'01_ASSUMPTIONS'!$E$2)^A18 | AC18: =AA18*AB18 | AD18: =AD17+AA18 | AE18: =IF(Y18>=0,"Yes","No") | AF18: =IF(AD18>=0,"Yes","No")
A19: =18 | B19: =B18*(1-INDEX('01_ASSUMPTIONS'!$J$5:$J$39,MATCH("monthly_churn",'01_ASSUMPTIONS'!$B$5:$B$39,0)))+INDEX('01_ASSUMPTIONS'!$J$5:$J$39,MATCH("starter_monthly_acquisition",'01_ASSUMPTIONS'!$B$5:$B$39,0)) | C19: =C18*(1-INDEX('01_ASSUMPTIONS'!$J$5:$J$39,MATCH("monthly_churn",'01_ASSUMPTIONS'!$B$5:$B$39,0)))+INDEX('01_ASSUMPTIONS'!$J$5:$J$39,MATCH("professional_monthly_acquisition",'01_ASSUMPTIONS'!$B$5:$B$39,0)) | D19: =D18*(1-INDEX('01_ASSUMPTIONS'!$J$5:$J$39,MATCH("monthly_churn",'01_ASSUMPTIONS'!$B$5:$B$39,0)))+INDEX('01_ASSUMPTIONS'!$J$5:$J$39,MATCH("enterprise_monthly_acquisition",'01_ASSUMPTIONS'!$B$5:$B$39,0)) | E19: =SUM(B19:D19) | F19: =B19*INDEX('01_ASSUMPTIONS'!$J$5:$J$39,MATCH("starter_studies_per_customer",'01_ASSUMPTIONS'!$B$5:$B$39,0)) | G19: =C19*INDEX('01_ASSUMPTIONS'!$J$5:$J$39,MATCH("professional_studies_per_customer",'01_ASSUMPTIONS'!$B$5:$B$39,0)) | H19: =D19*INDEX('01_ASSUMPTIONS'!$J$5:$J$39,MATCH("enterprise_studies_per_customer",'01_ASSUMPTIONS'!$B$5:$B$39,0)) | I19: =SUM(F19:H19) | J19: =B19*INDEX('01_ASSUMPTIONS'!$J$5:$J$39,MATCH("starter_fee",'01_ASSUMPTIONS'!$B$5:$B$39,0))+C19*INDEX('01_ASSUMPTIONS'!$J$5:$J$39,MATCH("professional_fee",'01_ASSUMPTIONS'!$B$5:$B$39,0))+D19*INDEX('01_ASSUMPTIONS'!$J$5:$J$39,MATCH("enterprise_fee",'01_ASSUMPTIONS'!$B$5:$B$39,0)) | K19: =MAX(F19-B19*INDEX('01_ASSUMPTIONS'!$J$5:$J$39,MATCH("starter_included_studies",'01_ASSUMPTIONS'!$B$5:$B$39,0)),0)*INDEX('01_ASSUMPTIONS'!$J$5:$J$39,MATCH("starter_overage_fee",'01_ASSUMPTIONS'!$B$5:$B$39,0))+MAX(G19-C19*INDEX('01_ASSUMPTIONS'!$J$5:$J$39,MATCH("professional_included_studies",'01_ASSUMPTIONS'!$B$5:$B$39,0)),0)*INDEX('01_ASSUMPTIONS'!$J$5:$J$39,MATCH("professional_overage_fee",'01_ASSUMPTIONS'!$B$5:$B$39,0))+MAX(H19-D19*INDEX('01_ASSUMPTIONS'!$J$5:$J$39,MATCH("enterprise_included_studies",'01_ASSUMPTIONS'!$B$5:$B$39,0)),0)*INDEX('01_ASSUMPTIONS'!$J$5:$J$39,MATCH("enterprise_overage_fee",'01_ASSUMPTIONS'!$B$5:$B$39,0)) | L19: =J19+K19 | M19: =I19*INDEX('01_ASSUMPTIONS'!$J$5:$J$39,MATCH("cloud_cost_per_study",'01_ASSUMPTIONS'!$B$5:$B$39,0)) | N19: =I19*INDEX('01_ASSUMPTIONS'!$J$5:$J$39,MATCH("storage_cost_per_study",'01_ASSUMPTIONS'!$B$5:$B$39,0)) | O19: =I19*INDEX('01_ASSUMPTIONS'!$J$5:$J$39,MATCH("ai_processing_cost_per_study",'01_ASSUMPTIONS'!$B$5:$B$39,0)) | P19: =E19*INDEX('01_ASSUMPTIONS'!$J$5:$J$39,MATCH("variable_support_per_customer",'01_ASSUMPTIONS'!$B$5:$B$39,0)) | Q19: =SUM(M19:P19) | R19: =INDEX('01_ASSUMPTIONS'!$J$5:$J$39,MATCH("fixed_infra",'01_ASSUMPTIONS'!$B$5:$B$39,0)) | S19: =INDEX('01_ASSUMPTIONS'!$J$5:$J$39,MATCH("software_maintenance",'01_ASSUMPTIONS'!$B$5:$B$39,0)) | T19: =INDEX('01_ASSUMPTIONS'!$J$5:$J$39,MATCH("base_support",'01_ASSUMPTIONS'!$B$5:$B$39,0)) | U19: =INDEX('01_ASSUMPTIONS'!$J$5:$J$39,MATCH("admin",'01_ASSUMPTIONS'!$B$5:$B$39,0)) | V19: =INDEX('01_ASSUMPTIONS'!$J$5:$J$39,MATCH("commercial_marketing",'01_ASSUMPTIONS'!$B$5:$B$39,0)) | W19: =INDEX('01_ASSUMPTIONS'!$J$5:$J$39,MATCH("other_fixed",'01_ASSUMPTIONS'!$B$5:$B$39,0)) | X19: =SUM(R19:W19) | Y19: =L19-Q19-X19 | Z19: =0 | AA19: =Y19-Z19 | AB19: =1/(1+'01_ASSUMPTIONS'!$E$2)^A19 | AC19: =AA19*AB19 | AD19: =AD18+AA19 | AE19: =IF(Y19>=0,"Yes","No") | AF19: =IF(AD19>=0,"Yes","No")
A20: =19 | B20: =B19*(1-INDEX('01_ASSUMPTIONS'!$J$5:$J$39,MATCH("monthly_churn",'01_ASSUMPTIONS'!$B$5:$B$39,0)))+INDEX('01_ASSUMPTIONS'!$J$5:$J$39,MATCH("starter_monthly_acquisition",'01_ASSUMPTIONS'!$B$5:$B$39,0)) | C20: =C19*(1-INDEX('01_ASSUMPTIONS'!$J$5:$J$39,MATCH("monthly_churn",'01_ASSUMPTIONS'!$B$5:$B$39,0)))+INDEX('01_ASSUMPTIONS'!$J$5:$J$39,MATCH("professional_monthly_acquisition",'01_ASSUMPTIONS'!$B$5:$B$39,0)) | D20: =D19*(1-INDEX('01_ASSUMPTIONS'!$J$5:$J$39,MATCH("monthly_churn",'01_ASSUMPTIONS'!$B$5:$B$39,0)))+INDEX('01_ASSUMPTIONS'!$J$5:$J$39,MATCH("enterprise_monthly_acquisition",'01_ASSUMPTIONS'!$B$5:$B$39,0)) | E20: =SUM(B20:D20) | F20: =B20*INDEX('01_ASSUMPTIONS'!$J$5:$J$39,MATCH("starter_studies_per_customer",'01_ASSUMPTIONS'!$B$5:$B$39,0)) | G20: =C20*INDEX('01_ASSUMPTIONS'!$J$5:$J$39,MATCH("professional_studies_per_customer",'01_ASSUMPTIONS'!$B$5:$B$39,0)) | H20: =D20*INDEX('01_ASSUMPTIONS'!$J$5:$J$39,MATCH("enterprise_studies_per_customer",'01_ASSUMPTIONS'!$B$5:$B$39,0)) | I20: =SUM(F20:H20) | J20: =B20*INDEX('01_ASSUMPTIONS'!$J$5:$J$39,MATCH("starter_fee",'01_ASSUMPTIONS'!$B$5:$B$39,0))+C20*INDEX('01_ASSUMPTIONS'!$J$5:$J$39,MATCH("professional_fee",'01_ASSUMPTIONS'!$B$5:$B$39,0))+D20*INDEX('01_ASSUMPTIONS'!$J$5:$J$39,MATCH("enterprise_fee",'01_ASSUMPTIONS'!$B$5:$B$39,0)) | K20: =MAX(F20-B20*INDEX('01_ASSUMPTIONS'!$J$5:$J$39,MATCH("starter_included_studies",'01_ASSUMPTIONS'!$B$5:$B$39,0)),0)*INDEX('01_ASSUMPTIONS'!$J$5:$J$39,MATCH("starter_overage_fee",'01_ASSUMPTIONS'!$B$5:$B$39,0))+MAX(G20-C20*INDEX('01_ASSUMPTIONS'!$J$5:$J$39,MATCH("professional_included_studies",'01_ASSUMPTIONS'!$B$5:$B$39,0)),0)*INDEX('01_ASSUMPTIONS'!$J$5:$J$39,MATCH("professional_overage_fee",'01_ASSUMPTIONS'!$B$5:$B$39,0))+MAX(H20-D20*INDEX('01_ASSUMPTIONS'!$J$5:$J$39,MATCH("enterprise_included_studies",'01_ASSUMPTIONS'!$B$5:$B$39,0)),0)*INDEX('01_ASSUMPTIONS'!$J$5:$J$39,MATCH("enterprise_overage_fee",'01_ASSUMPTIONS'!$B$5:$B$39,0)) | L20: =J20+K20 | M20: =I20*INDEX('01_ASSUMPTIONS'!$J$5:$J$39,MATCH("cloud_cost_per_study",'01_ASSUMPTIONS'!$B$5:$B$39,0)) | N20: =I20*INDEX('01_ASSUMPTIONS'!$J$5:$J$39,MATCH("storage_cost_per_study",'01_ASSUMPTIONS'!$B$5:$B$39,0)) | O20: =I20*INDEX('01_ASSUMPTIONS'!$J$5:$J$39,MATCH("ai_processing_cost_per_study",'01_ASSUMPTIONS'!$B$5:$B$39,0)) | P20: =E20*INDEX('01_ASSUMPTIONS'!$J$5:$J$39,MATCH("variable_support_per_customer",'01_ASSUMPTIONS'!$B$5:$B$39,0)) | Q20: =SUM(M20:P20) | R20: =INDEX('01_ASSUMPTIONS'!$J$5:$J$39,MATCH("fixed_infra",'01_ASSUMPTIONS'!$B$5:$B$39,0)) | S20: =INDEX('01_ASSUMPTIONS'!$J$5:$J$39,MATCH("software_maintenance",'01_ASSUMPTIONS'!$B$5:$B$39,0)) | T20: =INDEX('01_ASSUMPTIONS'!$J$5:$J$39,MATCH("base_support",'01_ASSUMPTIONS'!$B$5:$B$39,0)) | U20: =INDEX('01_ASSUMPTIONS'!$J$5:$J$39,MATCH("admin",'01_ASSUMPTIONS'!$B$5:$B$39,0)) | V20: =INDEX('01_ASSUMPTIONS'!$J$5:$J$39,MATCH("commercial_marketing",'01_ASSUMPTIONS'!$B$5:$B$39,0)) | W20: =INDEX('01_ASSUMPTIONS'!$J$5:$J$39,MATCH("other_fixed",'01_ASSUMPTIONS'!$B$5:$B$39,0)) | X20: =SUM(R20:W20) | Y20: =L20-Q20-X20 | Z20: =0 | AA20: =Y20-Z20 | AB20: =1/(1+'01_ASSUMPTIONS'!$E$2)^A20 | AC20: =AA20*AB20 | AD20: =AD19+AA20 | AE20: =IF(Y20>=0,"Yes","No") | AF20: =IF(AD20>=0,"Yes","No")
A21: =20 | B21: =B20*(1-INDEX('01_ASSUMPTIONS'!$J$5:$J$39,MATCH("monthly_churn",'01_ASSUMPTIONS'!$B$5:$B$39,0)))+INDEX('01_ASSUMPTIONS'!$J$5:$J$39,MATCH("starter_monthly_acquisition",'01_ASSUMPTIONS'!$B$5:$B$39,0)) | C21: =C20*(1-INDEX('01_ASSUMPTIONS'!$J$5:$J$39,MATCH("monthly_churn",'01_ASSUMPTIONS'!$B$5:$B$39,0)))+INDEX('01_ASSUMPTIONS'!$J$5:$J$39,MATCH("professional_monthly_acquisition",'01_ASSUMPTIONS'!$B$5:$B$39,0)) | D21: =D20*(1-INDEX('01_ASSUMPTIONS'!$J$5:$J$39,MATCH("monthly_churn",'01_ASSUMPTIONS'!$B$5:$B$39,0)))+INDEX('01_ASSUMPTIONS'!$J$5:$J$39,MATCH("enterprise_monthly_acquisition",'01_ASSUMPTIONS'!$B$5:$B$39,0)) | E21: =SUM(B21:D21) | F21: =B21*INDEX('01_ASSUMPTIONS'!$J$5:$J$39,MATCH("starter_studies_per_customer",'01_ASSUMPTIONS'!$B$5:$B$39,0)) | G21: =C21*INDEX('01_ASSUMPTIONS'!$J$5:$J$39,MATCH("professional_studies_per_customer",'01_ASSUMPTIONS'!$B$5:$B$39,0)) | H21: =D21*INDEX('01_ASSUMPTIONS'!$J$5:$J$39,MATCH("enterprise_studies_per_customer",'01_ASSUMPTIONS'!$B$5:$B$39,0)) | I21: =SUM(F21:H21) | J21: =B21*INDEX('01_ASSUMPTIONS'!$J$5:$J$39,MATCH("starter_fee",'01_ASSUMPTIONS'!$B$5:$B$39,0))+C21*INDEX('01_ASSUMPTIONS'!$J$5:$J$39,MATCH("professional_fee",'01_ASSUMPTIONS'!$B$5:$B$39,0))+D21*INDEX('01_ASSUMPTIONS'!$J$5:$J$39,MATCH("enterprise_fee",'01_ASSUMPTIONS'!$B$5:$B$39,0)) | K21: =MAX(F21-B21*INDEX('01_ASSUMPTIONS'!$J$5:$J$39,MATCH("starter_included_studies",'01_ASSUMPTIONS'!$B$5:$B$39,0)),0)*INDEX('01_ASSUMPTIONS'!$J$5:$J$39,MATCH("starter_overage_fee",'01_ASSUMPTIONS'!$B$5:$B$39,0))+MAX(G21-C21*INDEX('01_ASSUMPTIONS'!$J$5:$J$39,MATCH("professional_included_studies",'01_ASSUMPTIONS'!$B$5:$B$39,0)),0)*INDEX('01_ASSUMPTIONS'!$J$5:$J$39,MATCH("professional_overage_fee",'01_ASSUMPTIONS'!$B$5:$B$39,0))+MAX(H21-D21*INDEX('01_ASSUMPTIONS'!$J$5:$J$39,MATCH("enterprise_included_studies",'01_ASSUMPTIONS'!$B$5:$B$39,0)),0)*INDEX('01_ASSUMPTIONS'!$J$5:$J$39,MATCH("enterprise_overage_fee",'01_ASSUMPTIONS'!$B$5:$B$39,0)) | L21: =J21+K21 | M21: =I21*INDEX('01_ASSUMPTIONS'!$J$5:$J$39,MATCH("cloud_cost_per_study",'01_ASSUMPTIONS'!$B$5:$B$39,0)) | N21: =I21*INDEX('01_ASSUMPTIONS'!$J$5:$J$39,MATCH("storage_cost_per_study",'01_ASSUMPTIONS'!$B$5:$B$39,0)) | O21: =I21*INDEX('01_ASSUMPTIONS'!$J$5:$J$39,MATCH("ai_processing_cost_per_study",'01_ASSUMPTIONS'!$B$5:$B$39,0)) | P21: =E21*INDEX('01_ASSUMPTIONS'!$J$5:$J$39,MATCH("variable_support_per_customer",'01_ASSUMPTIONS'!$B$5:$B$39,0)) | Q21: =SUM(M21:P21) | R21: =INDEX('01_ASSUMPTIONS'!$J$5:$J$39,MATCH("fixed_infra",'01_ASSUMPTIONS'!$B$5:$B$39,0)) | S21: =INDEX('01_ASSUMPTIONS'!$J$5:$J$39,MATCH("software_maintenance",'01_ASSUMPTIONS'!$B$5:$B$39,0)) | T21: =INDEX('01_ASSUMPTIONS'!$J$5:$J$39,MATCH("base_support",'01_ASSUMPTIONS'!$B$5:$B$39,0)) | U21: =INDEX('01_ASSUMPTIONS'!$J$5:$J$39,MATCH("admin",'01_ASSUMPTIONS'!$B$5:$B$39,0)) | V21: =INDEX('01_ASSUMPTIONS'!$J$5:$J$39,MATCH("commercial_marketing",'01_ASSUMPTIONS'!$B$5:$B$39,0)) | W21: =INDEX('01_ASSUMPTIONS'!$J$5:$J$39,MATCH("other_fixed",'01_ASSUMPTIONS'!$B$5:$B$39,0)) | X21: =SUM(R21:W21) | Y21: =L21-Q21-X21 | Z21: =0 | AA21: =Y21-Z21 | AB21: =1/(1+'01_ASSUMPTIONS'!$E$2)^A21 | AC21: =AA21*AB21 | AD21: =AD20+AA21 | AE21: =IF(Y21>=0,"Yes","No") | AF21: =IF(AD21>=0,"Yes","No")
A22: =21 | B22: =B21*(1-INDEX('01_ASSUMPTIONS'!$J$5:$J$39,MATCH("monthly_churn",'01_ASSUMPTIONS'!$B$5:$B$39,0)))+INDEX('01_ASSUMPTIONS'!$J$5:$J$39,MATCH("starter_monthly_acquisition",'01_ASSUMPTIONS'!$B$5:$B$39,0)) | C22: =C21*(1-INDEX('01_ASSUMPTIONS'!$J$5:$J$39,MATCH("monthly_churn",'01_ASSUMPTIONS'!$B$5:$B$39,0)))+INDEX('01_ASSUMPTIONS'!$J$5:$J$39,MATCH("professional_monthly_acquisition",'01_ASSUMPTIONS'!$B$5:$B$39,0)) | D22: =D21*(1-INDEX('01_ASSUMPTIONS'!$J$5:$J$39,MATCH("monthly_churn",'01_ASSUMPTIONS'!$B$5:$B$39,0)))+INDEX('01_ASSUMPTIONS'!$J$5:$J$39,MATCH("enterprise_monthly_acquisition",'01_ASSUMPTIONS'!$B$5:$B$39,0)) | E22: =SUM(B22:D22) | F22: =B22*INDEX('01_ASSUMPTIONS'!$J$5:$J$39,MATCH("starter_studies_per_customer",'01_ASSUMPTIONS'!$B$5:$B$39,0)) | G22: =C22*INDEX('01_ASSUMPTIONS'!$J$5:$J$39,MATCH("professional_studies_per_customer",'01_ASSUMPTIONS'!$B$5:$B$39,0)) | H22: =D22*INDEX('01_ASSUMPTIONS'!$J$5:$J$39,MATCH("enterprise_studies_per_customer",'01_ASSUMPTIONS'!$B$5:$B$39,0)) | I22: =SUM(F22:H22) | J22: =B22*INDEX('01_ASSUMPTIONS'!$J$5:$J$39,MATCH("starter_fee",'01_ASSUMPTIONS'!$B$5:$B$39,0))+C22*INDEX('01_ASSUMPTIONS'!$J$5:$J$39,MATCH("professional_fee",'01_ASSUMPTIONS'!$B$5:$B$39,0))+D22*INDEX('01_ASSUMPTIONS'!$J$5:$J$39,MATCH("enterprise_fee",'01_ASSUMPTIONS'!$B$5:$B$39,0)) | K22: =MAX(F22-B22*INDEX('01_ASSUMPTIONS'!$J$5:$J$39,MATCH("starter_included_studies",'01_ASSUMPTIONS'!$B$5:$B$39,0)),0)*INDEX('01_ASSUMPTIONS'!$J$5:$J$39,MATCH("starter_overage_fee",'01_ASSUMPTIONS'!$B$5:$B$39,0))+MAX(G22-C22*INDEX('01_ASSUMPTIONS'!$J$5:$J$39,MATCH("professional_included_studies",'01_ASSUMPTIONS'!$B$5:$B$39,0)),0)*INDEX('01_ASSUMPTIONS'!$J$5:$J$39,MATCH("professional_overage_fee",'01_ASSUMPTIONS'!$B$5:$B$39,0))+MAX(H22-D22*INDEX('01_ASSUMPTIONS'!$J$5:$J$39,MATCH("enterprise_included_studies",'01_ASSUMPTIONS'!$B$5:$B$39,0)),0)*INDEX('01_ASSUMPTIONS'!$J$5:$J$39,MATCH("enterprise_overage_fee",'01_ASSUMPTIONS'!$B$5:$B$39,0)) | L22: =J22+K22 | M22: =I22*INDEX('01_ASSUMPTIONS'!$J$5:$J$39,MATCH("cloud_cost_per_study",'01_ASSUMPTIONS'!$B$5:$B$39,0)) | N22: =I22*INDEX('01_ASSUMPTIONS'!$J$5:$J$39,MATCH("storage_cost_per_study",'01_ASSUMPTIONS'!$B$5:$B$39,0)) | O22: =I22*INDEX('01_ASSUMPTIONS'!$J$5:$J$39,MATCH("ai_processing_cost_per_study",'01_ASSUMPTIONS'!$B$5:$B$39,0)) | P22: =E22*INDEX('01_ASSUMPTIONS'!$J$5:$J$39,MATCH("variable_support_per_customer",'01_ASSUMPTIONS'!$B$5:$B$39,0)) | Q22: =SUM(M22:P22) | R22: =INDEX('01_ASSUMPTIONS'!$J$5:$J$39,MATCH("fixed_infra",'01_ASSUMPTIONS'!$B$5:$B$39,0)) | S22: =INDEX('01_ASSUMPTIONS'!$J$5:$J$39,MATCH("software_maintenance",'01_ASSUMPTIONS'!$B$5:$B$39,0)) | T22: =INDEX('01_ASSUMPTIONS'!$J$5:$J$39,MATCH("base_support",'01_ASSUMPTIONS'!$B$5:$B$39,0)) | U22: =INDEX('01_ASSUMPTIONS'!$J$5:$J$39,MATCH("admin",'01_ASSUMPTIONS'!$B$5:$B$39,0)) | V22: =INDEX('01_ASSUMPTIONS'!$J$5:$J$39,MATCH("commercial_marketing",'01_ASSUMPTIONS'!$B$5:$B$39,0)) | W22: =INDEX('01_ASSUMPTIONS'!$J$5:$J$39,MATCH("other_fixed",'01_ASSUMPTIONS'!$B$5:$B$39,0)) | X22: =SUM(R22:W22) | Y22: =L22-Q22-X22 | Z22: =0 | AA22: =Y22-Z22 | AB22: =1/(1+'01_ASSUMPTIONS'!$E$2)^A22 | AC22: =AA22*AB22 | AD22: =AD21+AA22 | AE22: =IF(Y22>=0,"Yes","No") | AF22: =IF(AD22>=0,"Yes","No")
A23: =22 | B23: =B22*(1-INDEX('01_ASSUMPTIONS'!$J$5:$J$39,MATCH("monthly_churn",'01_ASSUMPTIONS'!$B$5:$B$39,0)))+INDEX('01_ASSUMPTIONS'!$J$5:$J$39,MATCH("starter_monthly_acquisition",'01_ASSUMPTIONS'!$B$5:$B$39,0)) | C23: =C22*(1-INDEX('01_ASSUMPTIONS'!$J$5:$J$39,MATCH("monthly_churn",'01_ASSUMPTIONS'!$B$5:$B$39,0)))+INDEX('01_ASSUMPTIONS'!$J$5:$J$39,MATCH("professional_monthly_acquisition",'01_ASSUMPTIONS'!$B$5:$B$39,0)) | D23: =D22*(1-INDEX('01_ASSUMPTIONS'!$J$5:$J$39,MATCH("monthly_churn",'01_ASSUMPTIONS'!$B$5:$B$39,0)))+INDEX('01_ASSUMPTIONS'!$J$5:$J$39,MATCH("enterprise_monthly_acquisition",'01_ASSUMPTIONS'!$B$5:$B$39,0)) | E23: =SUM(B23:D23) | F23: =B23*INDEX('01_ASSUMPTIONS'!$J$5:$J$39,MATCH("starter_studies_per_customer",'01_ASSUMPTIONS'!$B$5:$B$39,0)) | G23: =C23*INDEX('01_ASSUMPTIONS'!$J$5:$J$39,MATCH("professional_studies_per_customer",'01_ASSUMPTIONS'!$B$5:$B$39,0)) | H23: =D23*INDEX('01_ASSUMPTIONS'!$J$5:$J$39,MATCH("enterprise_studies_per_customer",'01_ASSUMPTIONS'!$B$5:$B$39,0)) | I23: =SUM(F23:H23) | J23: =B23*INDEX('01_ASSUMPTIONS'!$J$5:$J$39,MATCH("starter_fee",'01_ASSUMPTIONS'!$B$5:$B$39,0))+C23*INDEX('01_ASSUMPTIONS'!$J$5:$J$39,MATCH("professional_fee",'01_ASSUMPTIONS'!$B$5:$B$39,0))+D23*INDEX('01_ASSUMPTIONS'!$J$5:$J$39,MATCH("enterprise_fee",'01_ASSUMPTIONS'!$B$5:$B$39,0)) | K23: =MAX(F23-B23*INDEX('01_ASSUMPTIONS'!$J$5:$J$39,MATCH("starter_included_studies",'01_ASSUMPTIONS'!$B$5:$B$39,0)),0)*INDEX('01_ASSUMPTIONS'!$J$5:$J$39,MATCH("starter_overage_fee",'01_ASSUMPTIONS'!$B$5:$B$39,0))+MAX(G23-C23*INDEX('01_ASSUMPTIONS'!$J$5:$J$39,MATCH("professional_included_studies",'01_ASSUMPTIONS'!$B$5:$B$39,0)),0)*INDEX('01_ASSUMPTIONS'!$J$5:$J$39,MATCH("professional_overage_fee",'01_ASSUMPTIONS'!$B$5:$B$39,0))+MAX(H23-D23*INDEX('01_ASSUMPTIONS'!$J$5:$J$39,MATCH("enterprise_included_studies",'01_ASSUMPTIONS'!$B$5:$B$39,0)),0)*INDEX('01_ASSUMPTIONS'!$J$5:$J$39,MATCH("enterprise_overage_fee",'01_ASSUMPTIONS'!$B$5:$B$39,0)) | L23: =J23+K23 | M23: =I23*INDEX('01_ASSUMPTIONS'!$J$5:$J$39,MATCH("cloud_cost_per_study",'01_ASSUMPTIONS'!$B$5:$B$39,0)) | N23: =I23*INDEX('01_ASSUMPTIONS'!$J$5:$J$39,MATCH("storage_cost_per_study",'01_ASSUMPTIONS'!$B$5:$B$39,0)) | O23: =I23*INDEX('01_ASSUMPTIONS'!$J$5:$J$39,MATCH("ai_processing_cost_per_study",'01_ASSUMPTIONS'!$B$5:$B$39,0)) | P23: =E23*INDEX('01_ASSUMPTIONS'!$J$5:$J$39,MATCH("variable_support_per_customer",'01_ASSUMPTIONS'!$B$5:$B$39,0)) | Q23: =SUM(M23:P23) | R23: =INDEX('01_ASSUMPTIONS'!$J$5:$J$39,MATCH("fixed_infra",'01_ASSUMPTIONS'!$B$5:$B$39,0)) | S23: =INDEX('01_ASSUMPTIONS'!$J$5:$J$39,MATCH("software_maintenance",'01_ASSUMPTIONS'!$B$5:$B$39,0)) | T23: =INDEX('01_ASSUMPTIONS'!$J$5:$J$39,MATCH("base_support",'01_ASSUMPTIONS'!$B$5:$B$39,0)) | U23: =INDEX('01_ASSUMPTIONS'!$J$5:$J$39,MATCH("admin",'01_ASSUMPTIONS'!$B$5:$B$39,0)) | V23: =INDEX('01_ASSUMPTIONS'!$J$5:$J$39,MATCH("commercial_marketing",'01_ASSUMPTIONS'!$B$5:$B$39,0)) | W23: =INDEX('01_ASSUMPTIONS'!$J$5:$J$39,MATCH("other_fixed",'01_ASSUMPTIONS'!$B$5:$B$39,0)) | X23: =SUM(R23:W23) | Y23: =L23-Q23-X23 | Z23: =0 | AA23: =Y23-Z23 | AB23: =1/(1+'01_ASSUMPTIONS'!$E$2)^A23 | AC23: =AA23*AB23 | AD23: =AD22+AA23 | AE23: =IF(Y23>=0,"Yes","No") | AF23: =IF(AD23>=0,"Yes","No")
A24: =23 | B24: =B23*(1-INDEX('01_ASSUMPTIONS'!$J$5:$J$39,MATCH("monthly_churn",'01_ASSUMPTIONS'!$B$5:$B$39,0)))+INDEX('01_ASSUMPTIONS'!$J$5:$J$39,MATCH("starter_monthly_acquisition",'01_ASSUMPTIONS'!$B$5:$B$39,0)) | C24: =C23*(1-INDEX('01_ASSUMPTIONS'!$J$5:$J$39,MATCH("monthly_churn",'01_ASSUMPTIONS'!$B$5:$B$39,0)))+INDEX('01_ASSUMPTIONS'!$J$5:$J$39,MATCH("professional_monthly_acquisition",'01_ASSUMPTIONS'!$B$5:$B$39,0)) | D24: =D23*(1-INDEX('01_ASSUMPTIONS'!$J$5:$J$39,MATCH("monthly_churn",'01_ASSUMPTIONS'!$B$5:$B$39,0)))+INDEX('01_ASSUMPTIONS'!$J$5:$J$39,MATCH("enterprise_monthly_acquisition",'01_ASSUMPTIONS'!$B$5:$B$39,0)) | E24: =SUM(B24:D24) | F24: =B24*INDEX('01_ASSUMPTIONS'!$J$5:$J$39,MATCH("starter_studies_per_customer",'01_ASSUMPTIONS'!$B$5:$B$39,0)) | G24: =C24*INDEX('01_ASSUMPTIONS'!$J$5:$J$39,MATCH("professional_studies_per_customer",'01_ASSUMPTIONS'!$B$5:$B$39,0)) | H24: =D24*INDEX('01_ASSUMPTIONS'!$J$5:$J$39,MATCH("enterprise_studies_per_customer",'01_ASSUMPTIONS'!$B$5:$B$39,0)) | I24: =SUM(F24:H24) | J24: =B24*INDEX('01_ASSUMPTIONS'!$J$5:$J$39,MATCH("starter_fee",'01_ASSUMPTIONS'!$B$5:$B$39,0))+C24*INDEX('01_ASSUMPTIONS'!$J$5:$J$39,MATCH("professional_fee",'01_ASSUMPTIONS'!$B$5:$B$39,0))+D24*INDEX('01_ASSUMPTIONS'!$J$5:$J$39,MATCH("enterprise_fee",'01_ASSUMPTIONS'!$B$5:$B$39,0)) | K24: =MAX(F24-B24*INDEX('01_ASSUMPTIONS'!$J$5:$J$39,MATCH("starter_included_studies",'01_ASSUMPTIONS'!$B$5:$B$39,0)),0)*INDEX('01_ASSUMPTIONS'!$J$5:$J$39,MATCH("starter_overage_fee",'01_ASSUMPTIONS'!$B$5:$B$39,0))+MAX(G24-C24*INDEX('01_ASSUMPTIONS'!$J$5:$J$39,MATCH("professional_included_studies",'01_ASSUMPTIONS'!$B$5:$B$39,0)),0)*INDEX('01_ASSUMPTIONS'!$J$5:$J$39,MATCH("professional_overage_fee",'01_ASSUMPTIONS'!$B$5:$B$39,0))+MAX(H24-D24*INDEX('01_ASSUMPTIONS'!$J$5:$J$39,MATCH("enterprise_included_studies",'01_ASSUMPTIONS'!$B$5:$B$39,0)),0)*INDEX('01_ASSUMPTIONS'!$J$5:$J$39,MATCH("enterprise_overage_fee",'01_ASSUMPTIONS'!$B$5:$B$39,0)) | L24: =J24+K24 | M24: =I24*INDEX('01_ASSUMPTIONS'!$J$5:$J$39,MATCH("cloud_cost_per_study",'01_ASSUMPTIONS'!$B$5:$B$39,0)) | N24: =I24*INDEX('01_ASSUMPTIONS'!$J$5:$J$39,MATCH("storage_cost_per_study",'01_ASSUMPTIONS'!$B$5:$B$39,0)) | O24: =I24*INDEX('01_ASSUMPTIONS'!$J$5:$J$39,MATCH("ai_processing_cost_per_study",'01_ASSUMPTIONS'!$B$5:$B$39,0)) | P24: =E24*INDEX('01_ASSUMPTIONS'!$J$5:$J$39,MATCH("variable_support_per_customer",'01_ASSUMPTIONS'!$B$5:$B$39,0)) | Q24: =SUM(M24:P24) | R24: =INDEX('01_ASSUMPTIONS'!$J$5:$J$39,MATCH("fixed_infra",'01_ASSUMPTIONS'!$B$5:$B$39,0)) | S24: =INDEX('01_ASSUMPTIONS'!$J$5:$J$39,MATCH("software_maintenance",'01_ASSUMPTIONS'!$B$5:$B$39,0)) | T24: =INDEX('01_ASSUMPTIONS'!$J$5:$J$39,MATCH("base_support",'01_ASSUMPTIONS'!$B$5:$B$39,0)) | U24: =INDEX('01_ASSUMPTIONS'!$J$5:$J$39,MATCH("admin",'01_ASSUMPTIONS'!$B$5:$B$39,0)) | V24: =INDEX('01_ASSUMPTIONS'!$J$5:$J$39,MATCH("commercial_marketing",'01_ASSUMPTIONS'!$B$5:$B$39,0)) | W24: =INDEX('01_ASSUMPTIONS'!$J$5:$J$39,MATCH("other_fixed",'01_ASSUMPTIONS'!$B$5:$B$39,0)) | X24: =SUM(R24:W24) | Y24: =L24-Q24-X24 | Z24: =0 | AA24: =Y24-Z24 | AB24: =1/(1+'01_ASSUMPTIONS'!$E$2)^A24 | AC24: =AA24*AB24 | AD24: =AD23+AA24 | AE24: =IF(Y24>=0,"Yes","No") | AF24: =IF(AD24>=0,"Yes","No")
A25: =24 | B25: =B24*(1-INDEX('01_ASSUMPTIONS'!$J$5:$J$39,MATCH("monthly_churn",'01_ASSUMPTIONS'!$B$5:$B$39,0)))+INDEX('01_ASSUMPTIONS'!$J$5:$J$39,MATCH("starter_monthly_acquisition",'01_ASSUMPTIONS'!$B$5:$B$39,0)) | C25: =C24*(1-INDEX('01_ASSUMPTIONS'!$J$5:$J$39,MATCH("monthly_churn",'01_ASSUMPTIONS'!$B$5:$B$39,0)))+INDEX('01_ASSUMPTIONS'!$J$5:$J$39,MATCH("professional_monthly_acquisition",'01_ASSUMPTIONS'!$B$5:$B$39,0)) | D25: =D24*(1-INDEX('01_ASSUMPTIONS'!$J$5:$J$39,MATCH("monthly_churn",'01_ASSUMPTIONS'!$B$5:$B$39,0)))+INDEX('01_ASSUMPTIONS'!$J$5:$J$39,MATCH("enterprise_monthly_acquisition",'01_ASSUMPTIONS'!$B$5:$B$39,0)) | E25: =SUM(B25:D25) | F25: =B25*INDEX('01_ASSUMPTIONS'!$J$5:$J$39,MATCH("starter_studies_per_customer",'01_ASSUMPTIONS'!$B$5:$B$39,0)) | G25: =C25*INDEX('01_ASSUMPTIONS'!$J$5:$J$39,MATCH("professional_studies_per_customer",'01_ASSUMPTIONS'!$B$5:$B$39,0)) | H25: =D25*INDEX('01_ASSUMPTIONS'!$J$5:$J$39,MATCH("enterprise_studies_per_customer",'01_ASSUMPTIONS'!$B$5:$B$39,0)) | I25: =SUM(F25:H25) | J25: =B25*INDEX('01_ASSUMPTIONS'!$J$5:$J$39,MATCH("starter_fee",'01_ASSUMPTIONS'!$B$5:$B$39,0))+C25*INDEX('01_ASSUMPTIONS'!$J$5:$J$39,MATCH("professional_fee",'01_ASSUMPTIONS'!$B$5:$B$39,0))+D25*INDEX('01_ASSUMPTIONS'!$J$5:$J$39,MATCH("enterprise_fee",'01_ASSUMPTIONS'!$B$5:$B$39,0)) | K25: =MAX(F25-B25*INDEX('01_ASSUMPTIONS'!$J$5:$J$39,MATCH("starter_included_studies",'01_ASSUMPTIONS'!$B$5:$B$39,0)),0)*INDEX('01_ASSUMPTIONS'!$J$5:$J$39,MATCH("starter_overage_fee",'01_ASSUMPTIONS'!$B$5:$B$39,0))+MAX(G25-C25*INDEX('01_ASSUMPTIONS'!$J$5:$J$39,MATCH("professional_included_studies",'01_ASSUMPTIONS'!$B$5:$B$39,0)),0)*INDEX('01_ASSUMPTIONS'!$J$5:$J$39,MATCH("professional_overage_fee",'01_ASSUMPTIONS'!$B$5:$B$39,0))+MAX(H25-D25*INDEX('01_ASSUMPTIONS'!$J$5:$J$39,MATCH("enterprise_included_studies",'01_ASSUMPTIONS'!$B$5:$B$39,0)),0)*INDEX('01_ASSUMPTIONS'!$J$5:$J$39,MATCH("enterprise_overage_fee",'01_ASSUMPTIONS'!$B$5:$B$39,0)) | L25: =J25+K25 | M25: =I25*INDEX('01_ASSUMPTIONS'!$J$5:$J$39,MATCH("cloud_cost_per_study",'01_ASSUMPTIONS'!$B$5:$B$39,0)) | N25: =I25*INDEX('01_ASSUMPTIONS'!$J$5:$J$39,MATCH("storage_cost_per_study",'01_ASSUMPTIONS'!$B$5:$B$39,0)) | O25: =I25*INDEX('01_ASSUMPTIONS'!$J$5:$J$39,MATCH("ai_processing_cost_per_study",'01_ASSUMPTIONS'!$B$5:$B$39,0)) | P25: =E25*INDEX('01_ASSUMPTIONS'!$J$5:$J$39,MATCH("variable_support_per_customer",'01_ASSUMPTIONS'!$B$5:$B$39,0)) | Q25: =SUM(M25:P25) | R25: =INDEX('01_ASSUMPTIONS'!$J$5:$J$39,MATCH("fixed_infra",'01_ASSUMPTIONS'!$B$5:$B$39,0)) | S25: =INDEX('01_ASSUMPTIONS'!$J$5:$J$39,MATCH("software_maintenance",'01_ASSUMPTIONS'!$B$5:$B$39,0)) | T25: =INDEX('01_ASSUMPTIONS'!$J$5:$J$39,MATCH("base_support",'01_ASSUMPTIONS'!$B$5:$B$39,0)) | U25: =INDEX('01_ASSUMPTIONS'!$J$5:$J$39,MATCH("admin",'01_ASSUMPTIONS'!$B$5:$B$39,0)) | V25: =INDEX('01_ASSUMPTIONS'!$J$5:$J$39,MATCH("commercial_marketing",'01_ASSUMPTIONS'!$B$5:$B$39,0)) | W25: =INDEX('01_ASSUMPTIONS'!$J$5:$J$39,MATCH("other_fixed",'01_ASSUMPTIONS'!$B$5:$B$39,0)) | X25: =SUM(R25:W25) | Y25: =L25-Q25-X25 | Z25: =0 | AA25: =Y25-Z25 | AB25: =1/(1+'01_ASSUMPTIONS'!$E$2)^A25 | AC25: =AA25*AB25 | AD25: =AD24+AA25 | AE25: =IF(Y25>=0,"Yes","No") | AF25: =IF(AD25>=0,"Yes","No")
A26: =25 | B26: =B25*(1-INDEX('01_ASSUMPTIONS'!$J$5:$J$39,MATCH("monthly_churn",'01_ASSUMPTIONS'!$B$5:$B$39,0)))+INDEX('01_ASSUMPTIONS'!$J$5:$J$39,MATCH("starter_monthly_acquisition",'01_ASSUMPTIONS'!$B$5:$B$39,0)) | C26: =C25*(1-INDEX('01_ASSUMPTIONS'!$J$5:$J$39,MATCH("monthly_churn",'01_ASSUMPTIONS'!$B$5:$B$39,0)))+INDEX('01_ASSUMPTIONS'!$J$5:$J$39,MATCH("professional_monthly_acquisition",'01_ASSUMPTIONS'!$B$5:$B$39,0)) | D26: =D25*(1-INDEX('01_ASSUMPTIONS'!$J$5:$J$39,MATCH("monthly_churn",'01_ASSUMPTIONS'!$B$5:$B$39,0)))+INDEX('01_ASSUMPTIONS'!$J$5:$J$39,MATCH("enterprise_monthly_acquisition",'01_ASSUMPTIONS'!$B$5:$B$39,0)) | E26: =SUM(B26:D26) | F26: =B26*INDEX('01_ASSUMPTIONS'!$J$5:$J$39,MATCH("starter_studies_per_customer",'01_ASSUMPTIONS'!$B$5:$B$39,0)) | G26: =C26*INDEX('01_ASSUMPTIONS'!$J$5:$J$39,MATCH("professional_studies_per_customer",'01_ASSUMPTIONS'!$B$5:$B$39,0)) | H26: =D26*INDEX('01_ASSUMPTIONS'!$J$5:$J$39,MATCH("enterprise_studies_per_customer",'01_ASSUMPTIONS'!$B$5:$B$39,0)) | I26: =SUM(F26:H26) | J26: =B26*INDEX('01_ASSUMPTIONS'!$J$5:$J$39,MATCH("starter_fee",'01_ASSUMPTIONS'!$B$5:$B$39,0))+C26*INDEX('01_ASSUMPTIONS'!$J$5:$J$39,MATCH("professional_fee",'01_ASSUMPTIONS'!$B$5:$B$39,0))+D26*INDEX('01_ASSUMPTIONS'!$J$5:$J$39,MATCH("enterprise_fee",'01_ASSUMPTIONS'!$B$5:$B$39,0)) | K26: =MAX(F26-B26*INDEX('01_ASSUMPTIONS'!$J$5:$J$39,MATCH("starter_included_studies",'01_ASSUMPTIONS'!$B$5:$B$39,0)),0)*INDEX('01_ASSUMPTIONS'!$J$5:$J$39,MATCH("starter_overage_fee",'01_ASSUMPTIONS'!$B$5:$B$39,0))+MAX(G26-C26*INDEX('01_ASSUMPTIONS'!$J$5:$J$39,MATCH("professional_included_studies",'01_ASSUMPTIONS'!$B$5:$B$39,0)),0)*INDEX('01_ASSUMPTIONS'!$J$5:$J$39,MATCH("professional_overage_fee",'01_ASSUMPTIONS'!$B$5:$B$39,0))+MAX(H26-D26*INDEX('01_ASSUMPTIONS'!$J$5:$J$39,MATCH("enterprise_included_studies",'01_ASSUMPTIONS'!$B$5:$B$39,0)),0)*INDEX('01_ASSUMPTIONS'!$J$5:$J$39,MATCH("enterprise_overage_fee",'01_ASSUMPTIONS'!$B$5:$B$39,0)) | L26: =J26+K26 | M26: =I26*INDEX('01_ASSUMPTIONS'!$J$5:$J$39,MATCH("cloud_cost_per_study",'01_ASSUMPTIONS'!$B$5:$B$39,0)) | N26: =I26*INDEX('01_ASSUMPTIONS'!$J$5:$J$39,MATCH("storage_cost_per_study",'01_ASSUMPTIONS'!$B$5:$B$39,0)) | O26: =I26*INDEX('01_ASSUMPTIONS'!$J$5:$J$39,MATCH("ai_processing_cost_per_study",'01_ASSUMPTIONS'!$B$5:$B$39,0)) | P26: =E26*INDEX('01_ASSUMPTIONS'!$J$5:$J$39,MATCH("variable_support_per_customer",'01_ASSUMPTIONS'!$B$5:$B$39,0)) | Q26: =SUM(M26:P26) | R26: =INDEX('01_ASSUMPTIONS'!$J$5:$J$39,MATCH("fixed_infra",'01_ASSUMPTIONS'!$B$5:$B$39,0)) | S26: =INDEX('01_ASSUMPTIONS'!$J$5:$J$39,MATCH("software_maintenance",'01_ASSUMPTIONS'!$B$5:$B$39,0)) | T26: =INDEX('01_ASSUMPTIONS'!$J$5:$J$39,MATCH("base_support",'01_ASSUMPTIONS'!$B$5:$B$39,0)) | U26: =INDEX('01_ASSUMPTIONS'!$J$5:$J$39,MATCH("admin",'01_ASSUMPTIONS'!$B$5:$B$39,0)) | V26: =INDEX('01_ASSUMPTIONS'!$J$5:$J$39,MATCH("commercial_marketing",'01_ASSUMPTIONS'!$B$5:$B$39,0)) | W26: =INDEX('01_ASSUMPTIONS'!$J$5:$J$39,MATCH("other_fixed",'01_ASSUMPTIONS'!$B$5:$B$39,0)) | X26: =SUM(R26:W26) | Y26: =L26-Q26-X26 | Z26: =0 | AA26: =Y26-Z26 | AB26: =1/(1+'01_ASSUMPTIONS'!$E$2)^A26 | AC26: =AA26*AB26 | AD26: =AD25+AA26 | AE26: =IF(Y26>=0,"Yes","No") | AF26: =IF(AD26>=0,"Yes","No")
A27: =26 | B27: =B26*(1-INDEX('01_ASSUMPTIONS'!$J$5:$J$39,MATCH("monthly_churn",'01_ASSUMPTIONS'!$B$5:$B$39,0)))+INDEX('01_ASSUMPTIONS'!$J$5:$J$39,MATCH("starter_monthly_acquisition",'01_ASSUMPTIONS'!$B$5:$B$39,0)) | C27: =C26*(1-INDEX('01_ASSUMPTIONS'!$J$5:$J$39,MATCH("monthly_churn",'01_ASSUMPTIONS'!$B$5:$B$39,0)))+INDEX('01_ASSUMPTIONS'!$J$5:$J$39,MATCH("professional_monthly_acquisition",'01_ASSUMPTIONS'!$B$5:$B$39,0)) | D27: =D26*(1-INDEX('01_ASSUMPTIONS'!$J$5:$J$39,MATCH("monthly_churn",'01_ASSUMPTIONS'!$B$5:$B$39,0)))+INDEX('01_ASSUMPTIONS'!$J$5:$J$39,MATCH("enterprise_monthly_acquisition",'01_ASSUMPTIONS'!$B$5:$B$39,0)) | E27: =SUM(B27:D27) | F27: =B27*INDEX('01_ASSUMPTIONS'!$J$5:$J$39,MATCH("starter_studies_per_customer",'01_ASSUMPTIONS'!$B$5:$B$39,0)) | G27: =C27*INDEX('01_ASSUMPTIONS'!$J$5:$J$39,MATCH("professional_studies_per_customer",'01_ASSUMPTIONS'!$B$5:$B$39,0)) | H27: =D27*INDEX('01_ASSUMPTIONS'!$J$5:$J$39,MATCH("enterprise_studies_per_customer",'01_ASSUMPTIONS'!$B$5:$B$39,0)) | I27: =SUM(F27:H27) | J27: =B27*INDEX('01_ASSUMPTIONS'!$J$5:$J$39,MATCH("starter_fee",'01_ASSUMPTIONS'!$B$5:$B$39,0))+C27*INDEX('01_ASSUMPTIONS'!$J$5:$J$39,MATCH("professional_fee",'01_ASSUMPTIONS'!$B$5:$B$39,0))+D27*INDEX('01_ASSUMPTIONS'!$J$5:$J$39,MATCH("enterprise_fee",'01_ASSUMPTIONS'!$B$5:$B$39,0)) | K27: =MAX(F27-B27*INDEX('01_ASSUMPTIONS'!$J$5:$J$39,MATCH("starter_included_studies",'01_ASSUMPTIONS'!$B$5:$B$39,0)),0)*INDEX('01_ASSUMPTIONS'!$J$5:$J$39,MATCH("starter_overage_fee",'01_ASSUMPTIONS'!$B$5:$B$39,0))+MAX(G27-C27*INDEX('01_ASSUMPTIONS'!$J$5:$J$39,MATCH("professional_included_studies",'01_ASSUMPTIONS'!$B$5:$B$39,0)),0)*INDEX('01_ASSUMPTIONS'!$J$5:$J$39,MATCH("professional_overage_fee",'01_ASSUMPTIONS'!$B$5:$B$39,0))+MAX(H27-D27*INDEX('01_ASSUMPTIONS'!$J$5:$J$39,MATCH("enterprise_included_studies",'01_ASSUMPTIONS'!$B$5:$B$39,0)),0)*INDEX('01_ASSUMPTIONS'!$J$5:$J$39,MATCH("enterprise_overage_fee",'01_ASSUMPTIONS'!$B$5:$B$39,0)) | L27: =J27+K27 | M27: =I27*INDEX('01_ASSUMPTIONS'!$J$5:$J$39,MATCH("cloud_cost_per_study",'01_ASSUMPTIONS'!$B$5:$B$39,0)) | N27: =I27*INDEX('01_ASSUMPTIONS'!$J$5:$J$39,MATCH("storage_cost_per_study",'01_ASSUMPTIONS'!$B$5:$B$39,0)) | O27: =I27*INDEX('01_ASSUMPTIONS'!$J$5:$J$39,MATCH("ai_processing_cost_per_study",'01_ASSUMPTIONS'!$B$5:$B$39,0)) | P27: =E27*INDEX('01_ASSUMPTIONS'!$J$5:$J$39,MATCH("variable_support_per_customer",'01_ASSUMPTIONS'!$B$5:$B$39,0)) | Q27: =SUM(M27:P27) | R27: =INDEX('01_ASSUMPTIONS'!$J$5:$J$39,MATCH("fixed_infra",'01_ASSUMPTIONS'!$B$5:$B$39,0)) | S27: =INDEX('01_ASSUMPTIONS'!$J$5:$J$39,MATCH("software_maintenance",'01_ASSUMPTIONS'!$B$5:$B$39,0)) | T27: =INDEX('01_ASSUMPTIONS'!$J$5:$J$39,MATCH("base_support",'01_ASSUMPTIONS'!$B$5:$B$39,0)) | U27: =INDEX('01_ASSUMPTIONS'!$J$5:$J$39,MATCH("admin",'01_ASSUMPTIONS'!$B$5:$B$39,0)) | V27: =INDEX('01_ASSUMPTIONS'!$J$5:$J$39,MATCH("commercial_marketing",'01_ASSUMPTIONS'!$B$5:$B$39,0)) | W27: =INDEX('01_ASSUMPTIONS'!$J$5:$J$39,MATCH("other_fixed",'01_ASSUMPTIONS'!$B$5:$B$39,0)) | X27: =SUM(R27:W27) | Y27: =L27-Q27-X27 | Z27: =0 | AA27: =Y27-Z27 | AB27: =1/(1+'01_ASSUMPTIONS'!$E$2)^A27 | AC27: =AA27*AB27 | AD27: =AD26+AA27 | AE27: =IF(Y27>=0,"Yes","No") | AF27: =IF(AD27>=0,"Yes","No")
A28: =27 | B28: =B27*(1-INDEX('01_ASSUMPTIONS'!$J$5:$J$39,MATCH("monthly_churn",'01_ASSUMPTIONS'!$B$5:$B$39,0)))+INDEX('01_ASSUMPTIONS'!$J$5:$J$39,MATCH("starter_monthly_acquisition",'01_ASSUMPTIONS'!$B$5:$B$39,0)) | C28: =C27*(1-INDEX('01_ASSUMPTIONS'!$J$5:$J$39,MATCH("monthly_churn",'01_ASSUMPTIONS'!$B$5:$B$39,0)))+INDEX('01_ASSUMPTIONS'!$J$5:$J$39,MATCH("professional_monthly_acquisition",'01_ASSUMPTIONS'!$B$5:$B$39,0)) | D28: =D27*(1-INDEX('01_ASSUMPTIONS'!$J$5:$J$39,MATCH("monthly_churn",'01_ASSUMPTIONS'!$B$5:$B$39,0)))+INDEX('01_ASSUMPTIONS'!$J$5:$J$39,MATCH("enterprise_monthly_acquisition",'01_ASSUMPTIONS'!$B$5:$B$39,0)) | E28: =SUM(B28:D28) | F28: =B28*INDEX('01_ASSUMPTIONS'!$J$5:$J$39,MATCH("starter_studies_per_customer",'01_ASSUMPTIONS'!$B$5:$B$39,0)) | G28: =C28*INDEX('01_ASSUMPTIONS'!$J$5:$J$39,MATCH("professional_studies_per_customer",'01_ASSUMPTIONS'!$B$5:$B$39,0)) | H28: =D28*INDEX('01_ASSUMPTIONS'!$J$5:$J$39,MATCH("enterprise_studies_per_customer",'01_ASSUMPTIONS'!$B$5:$B$39,0)) | I28: =SUM(F28:H28) | J28: =B28*INDEX('01_ASSUMPTIONS'!$J$5:$J$39,MATCH("starter_fee",'01_ASSUMPTIONS'!$B$5:$B$39,0))+C28*INDEX('01_ASSUMPTIONS'!$J$5:$J$39,MATCH("professional_fee",'01_ASSUMPTIONS'!$B$5:$B$39,0))+D28*INDEX('01_ASSUMPTIONS'!$J$5:$J$39,MATCH("enterprise_fee",'01_ASSUMPTIONS'!$B$5:$B$39,0)) | K28: =MAX(F28-B28*INDEX('01_ASSUMPTIONS'!$J$5:$J$39,MATCH("starter_included_studies",'01_ASSUMPTIONS'!$B$5:$B$39,0)),0)*INDEX('01_ASSUMPTIONS'!$J$5:$J$39,MATCH("starter_overage_fee",'01_ASSUMPTIONS'!$B$5:$B$39,0))+MAX(G28-C28*INDEX('01_ASSUMPTIONS'!$J$5:$J$39,MATCH("professional_included_studies",'01_ASSUMPTIONS'!$B$5:$B$39,0)),0)*INDEX('01_ASSUMPTIONS'!$J$5:$J$39,MATCH("professional_overage_fee",'01_ASSUMPTIONS'!$B$5:$B$39,0))+MAX(H28-D28*INDEX('01_ASSUMPTIONS'!$J$5:$J$39,MATCH("enterprise_included_studies",'01_ASSUMPTIONS'!$B$5:$B$39,0)),0)*INDEX('01_ASSUMPTIONS'!$J$5:$J$39,MATCH("enterprise_overage_fee",'01_ASSUMPTIONS'!$B$5:$B$39,0)) | L28: =J28+K28 | M28: =I28*INDEX('01_ASSUMPTIONS'!$J$5:$J$39,MATCH("cloud_cost_per_study",'01_ASSUMPTIONS'!$B$5:$B$39,0)) | N28: =I28*INDEX('01_ASSUMPTIONS'!$J$5:$J$39,MATCH("storage_cost_per_study",'01_ASSUMPTIONS'!$B$5:$B$39,0)) | O28: =I28*INDEX('01_ASSUMPTIONS'!$J$5:$J$39,MATCH("ai_processing_cost_per_study",'01_ASSUMPTIONS'!$B$5:$B$39,0)) | P28: =E28*INDEX('01_ASSUMPTIONS'!$J$5:$J$39,MATCH("variable_support_per_customer",'01_ASSUMPTIONS'!$B$5:$B$39,0)) | Q28: =SUM(M28:P28) | R28: =INDEX('01_ASSUMPTIONS'!$J$5:$J$39,MATCH("fixed_infra",'01_ASSUMPTIONS'!$B$5:$B$39,0)) | S28: =INDEX('01_ASSUMPTIONS'!$J$5:$J$39,MATCH("software_maintenance",'01_ASSUMPTIONS'!$B$5:$B$39,0)) | T28: =INDEX('01_ASSUMPTIONS'!$J$5:$J$39,MATCH("base_support",'01_ASSUMPTIONS'!$B$5:$B$39,0)) | U28: =INDEX('01_ASSUMPTIONS'!$J$5:$J$39,MATCH("admin",'01_ASSUMPTIONS'!$B$5:$B$39,0)) | V28: =INDEX('01_ASSUMPTIONS'!$J$5:$J$39,MATCH("commercial_marketing",'01_ASSUMPTIONS'!$B$5:$B$39,0)) | W28: =INDEX('01_ASSUMPTIONS'!$J$5:$J$39,MATCH("other_fixed",'01_ASSUMPTIONS'!$B$5:$B$39,0)) | X28: =SUM(R28:W28) | Y28: =L28-Q28-X28 | Z28: =0 | AA28: =Y28-Z28 | AB28: =1/(1+'01_ASSUMPTIONS'!$E$2)^A28 | AC28: =AA28*AB28 | AD28: =AD27+AA28 | AE28: =IF(Y28>=0,"Yes","No") | AF28: =IF(AD28>=0,"Yes","No")
A29: =28 | B29: =B28*(1-INDEX('01_ASSUMPTIONS'!$J$5:$J$39,MATCH("monthly_churn",'01_ASSUMPTIONS'!$B$5:$B$39,0)))+INDEX('01_ASSUMPTIONS'!$J$5:$J$39,MATCH("starter_monthly_acquisition",'01_ASSUMPTIONS'!$B$5:$B$39,0)) | C29: =C28*(1-INDEX('01_ASSUMPTIONS'!$J$5:$J$39,MATCH("monthly_churn",'01_ASSUMPTIONS'!$B$5:$B$39,0)))+INDEX('01_ASSUMPTIONS'!$J$5:$J$39,MATCH("professional_monthly_acquisition",'01_ASSUMPTIONS'!$B$5:$B$39,0)) | D29: =D28*(1-INDEX('01_ASSUMPTIONS'!$J$5:$J$39,MATCH("monthly_churn",'01_ASSUMPTIONS'!$B$5:$B$39,0)))+INDEX('01_ASSUMPTIONS'!$J$5:$J$39,MATCH("enterprise_monthly_acquisition",'01_ASSUMPTIONS'!$B$5:$B$39,0)) | E29: =SUM(B29:D29) | F29: =B29*INDEX('01_ASSUMPTIONS'!$J$5:$J$39,MATCH("starter_studies_per_customer",'01_ASSUMPTIONS'!$B$5:$B$39,0)) | G29: =C29*INDEX('01_ASSUMPTIONS'!$J$5:$J$39,MATCH("professional_studies_per_customer",'01_ASSUMPTIONS'!$B$5:$B$39,0)) | H29: =D29*INDEX('01_ASSUMPTIONS'!$J$5:$J$39,MATCH("enterprise_studies_per_customer",'01_ASSUMPTIONS'!$B$5:$B$39,0)) | I29: =SUM(F29:H29) | J29: =B29*INDEX('01_ASSUMPTIONS'!$J$5:$J$39,MATCH("starter_fee",'01_ASSUMPTIONS'!$B$5:$B$39,0))+C29*INDEX('01_ASSUMPTIONS'!$J$5:$J$39,MATCH("professional_fee",'01_ASSUMPTIONS'!$B$5:$B$39,0))+D29*INDEX('01_ASSUMPTIONS'!$J$5:$J$39,MATCH("enterprise_fee",'01_ASSUMPTIONS'!$B$5:$B$39,0)) | K29: =MAX(F29-B29*INDEX('01_ASSUMPTIONS'!$J$5:$J$39,MATCH("starter_included_studies",'01_ASSUMPTIONS'!$B$5:$B$39,0)),0)*INDEX('01_ASSUMPTIONS'!$J$5:$J$39,MATCH("starter_overage_fee",'01_ASSUMPTIONS'!$B$5:$B$39,0))+MAX(G29-C29*INDEX('01_ASSUMPTIONS'!$J$5:$J$39,MATCH("professional_included_studies",'01_ASSUMPTIONS'!$B$5:$B$39,0)),0)*INDEX('01_ASSUMPTIONS'!$J$5:$J$39,MATCH("professional_overage_fee",'01_ASSUMPTIONS'!$B$5:$B$39,0))+MAX(H29-D29*INDEX('01_ASSUMPTIONS'!$J$5:$J$39,MATCH("enterprise_included_studies",'01_ASSUMPTIONS'!$B$5:$B$39,0)),0)*INDEX('01_ASSUMPTIONS'!$J$5:$J$39,MATCH("enterprise_overage_fee",'01_ASSUMPTIONS'!$B$5:$B$39,0)) | L29: =J29+K29 | M29: =I29*INDEX('01_ASSUMPTIONS'!$J$5:$J$39,MATCH("cloud_cost_per_study",'01_ASSUMPTIONS'!$B$5:$B$39,0)) | N29: =I29*INDEX('01_ASSUMPTIONS'!$J$5:$J$39,MATCH("storage_cost_per_study",'01_ASSUMPTIONS'!$B$5:$B$39,0)) | O29: =I29*INDEX('01_ASSUMPTIONS'!$J$5:$J$39,MATCH("ai_processing_cost_per_study",'01_ASSUMPTIONS'!$B$5:$B$39,0)) | P29: =E29*INDEX('01_ASSUMPTIONS'!$J$5:$J$39,MATCH("variable_support_per_customer",'01_ASSUMPTIONS'!$B$5:$B$39,0)) | Q29: =SUM(M29:P29) | R29: =INDEX('01_ASSUMPTIONS'!$J$5:$J$39,MATCH("fixed_infra",'01_ASSUMPTIONS'!$B$5:$B$39,0)) | S29: =INDEX('01_ASSUMPTIONS'!$J$5:$J$39,MATCH("software_maintenance",'01_ASSUMPTIONS'!$B$5:$B$39,0)) | T29: =INDEX('01_ASSUMPTIONS'!$J$5:$J$39,MATCH("base_support",'01_ASSUMPTIONS'!$B$5:$B$39,0)) | U29: =INDEX('01_ASSUMPTIONS'!$J$5:$J$39,MATCH("admin",'01_ASSUMPTIONS'!$B$5:$B$39,0)) | V29: =INDEX('01_ASSUMPTIONS'!$J$5:$J$39,MATCH("commercial_marketing",'01_ASSUMPTIONS'!$B$5:$B$39,0)) | W29: =INDEX('01_ASSUMPTIONS'!$J$5:$J$39,MATCH("other_fixed",'01_ASSUMPTIONS'!$B$5:$B$39,0)) | X29: =SUM(R29:W29) | Y29: =L29-Q29-X29 | Z29: =0 | AA29: =Y29-Z29 | AB29: =1/(1+'01_ASSUMPTIONS'!$E$2)^A29 | AC29: =AA29*AB29 | AD29: =AD28+AA29 | AE29: =IF(Y29>=0,"Yes","No") | AF29: =IF(AD29>=0,"Yes","No")
A30: =29 | B30: =B29*(1-INDEX('01_ASSUMPTIONS'!$J$5:$J$39,MATCH("monthly_churn",'01_ASSUMPTIONS'!$B$5:$B$39,0)))+INDEX('01_ASSUMPTIONS'!$J$5:$J$39,MATCH("starter_monthly_acquisition",'01_ASSUMPTIONS'!$B$5:$B$39,0)) | C30: =C29*(1-INDEX('01_ASSUMPTIONS'!$J$5:$J$39,MATCH("monthly_churn",'01_ASSUMPTIONS'!$B$5:$B$39,0)))+INDEX('01_ASSUMPTIONS'!$J$5:$J$39,MATCH("professional_monthly_acquisition",'01_ASSUMPTIONS'!$B$5:$B$39,0)) | D30: =D29*(1-INDEX('01_ASSUMPTIONS'!$J$5:$J$39,MATCH("monthly_churn",'01_ASSUMPTIONS'!$B$5:$B$39,0)))+INDEX('01_ASSUMPTIONS'!$J$5:$J$39,MATCH("enterprise_monthly_acquisition",'01_ASSUMPTIONS'!$B$5:$B$39,0)) | E30: =SUM(B30:D30) | F30: =B30*INDEX('01_ASSUMPTIONS'!$J$5:$J$39,MATCH("starter_studies_per_customer",'01_ASSUMPTIONS'!$B$5:$B$39,0)) | G30: =C30*INDEX('01_ASSUMPTIONS'!$J$5:$J$39,MATCH("professional_studies_per_customer",'01_ASSUMPTIONS'!$B$5:$B$39,0)) | H30: =D30*INDEX('01_ASSUMPTIONS'!$J$5:$J$39,MATCH("enterprise_studies_per_customer",'01_ASSUMPTIONS'!$B$5:$B$39,0)) | I30: =SUM(F30:H30) | J30: =B30*INDEX('01_ASSUMPTIONS'!$J$5:$J$39,MATCH("starter_fee",'01_ASSUMPTIONS'!$B$5:$B$39,0))+C30*INDEX('01_ASSUMPTIONS'!$J$5:$J$39,MATCH("professional_fee",'01_ASSUMPTIONS'!$B$5:$B$39,0))+D30*INDEX('01_ASSUMPTIONS'!$J$5:$J$39,MATCH("enterprise_fee",'01_ASSUMPTIONS'!$B$5:$B$39,0)) | K30: =MAX(F30-B30*INDEX('01_ASSUMPTIONS'!$J$5:$J$39,MATCH("starter_included_studies",'01_ASSUMPTIONS'!$B$5:$B$39,0)),0)*INDEX('01_ASSUMPTIONS'!$J$5:$J$39,MATCH("starter_overage_fee",'01_ASSUMPTIONS'!$B$5:$B$39,0))+MAX(G30-C30*INDEX('01_ASSUMPTIONS'!$J$5:$J$39,MATCH("professional_included_studies",'01_ASSUMPTIONS'!$B$5:$B$39,0)),0)*INDEX('01_ASSUMPTIONS'!$J$5:$J$39,MATCH("professional_overage_fee",'01_ASSUMPTIONS'!$B$5:$B$39,0))+MAX(H30-D30*INDEX('01_ASSUMPTIONS'!$J$5:$J$39,MATCH("enterprise_included_studies",'01_ASSUMPTIONS'!$B$5:$B$39,0)),0)*INDEX('01_ASSUMPTIONS'!$J$5:$J$39,MATCH("enterprise_overage_fee",'01_ASSUMPTIONS'!$B$5:$B$39,0)) | L30: =J30+K30 | M30: =I30*INDEX('01_ASSUMPTIONS'!$J$5:$J$39,MATCH("cloud_cost_per_study",'01_ASSUMPTIONS'!$B$5:$B$39,0)) | N30: =I30*INDEX('01_ASSUMPTIONS'!$J$5:$J$39,MATCH("storage_cost_per_study",'01_ASSUMPTIONS'!$B$5:$B$39,0)) | O30: =I30*INDEX('01_ASSUMPTIONS'!$J$5:$J$39,MATCH("ai_processing_cost_per_study",'01_ASSUMPTIONS'!$B$5:$B$39,0)) | P30: =E30*INDEX('01_ASSUMPTIONS'!$J$5:$J$39,MATCH("variable_support_per_customer",'01_ASSUMPTIONS'!$B$5:$B$39,0)) | Q30: =SUM(M30:P30) | R30: =INDEX('01_ASSUMPTIONS'!$J$5:$J$39,MATCH("fixed_infra",'01_ASSUMPTIONS'!$B$5:$B$39,0)) | S30: =INDEX('01_ASSUMPTIONS'!$J$5:$J$39,MATCH("software_maintenance",'01_ASSUMPTIONS'!$B$5:$B$39,0)) | T30: =INDEX('01_ASSUMPTIONS'!$J$5:$J$39,MATCH("base_support",'01_ASSUMPTIONS'!$B$5:$B$39,0)) | U30: =INDEX('01_ASSUMPTIONS'!$J$5:$J$39,MATCH("admin",'01_ASSUMPTIONS'!$B$5:$B$39,0)) | V30: =INDEX('01_ASSUMPTIONS'!$J$5:$J$39,MATCH("commercial_marketing",'01_ASSUMPTIONS'!$B$5:$B$39,0)) | W30: =INDEX('01_ASSUMPTIONS'!$J$5:$J$39,MATCH("other_fixed",'01_ASSUMPTIONS'!$B$5:$B$39,0)) | X30: =SUM(R30:W30) | Y30: =L30-Q30-X30 | Z30: =0 | AA30: =Y30-Z30 | AB30: =1/(1+'01_ASSUMPTIONS'!$E$2)^A30 | AC30: =AA30*AB30 | AD30: =AD29+AA30 | AE30: =IF(Y30>=0,"Yes","No") | AF30: =IF(AD30>=0,"Yes","No")
A31: =30 | B31: =B30*(1-INDEX('01_ASSUMPTIONS'!$J$5:$J$39,MATCH("monthly_churn",'01_ASSUMPTIONS'!$B$5:$B$39,0)))+INDEX('01_ASSUMPTIONS'!$J$5:$J$39,MATCH("starter_monthly_acquisition",'01_ASSUMPTIONS'!$B$5:$B$39,0)) | C31: =C30*(1-INDEX('01_ASSUMPTIONS'!$J$5:$J$39,MATCH("monthly_churn",'01_ASSUMPTIONS'!$B$5:$B$39,0)))+INDEX('01_ASSUMPTIONS'!$J$5:$J$39,MATCH("professional_monthly_acquisition",'01_ASSUMPTIONS'!$B$5:$B$39,0)) | D31: =D30*(1-INDEX('01_ASSUMPTIONS'!$J$5:$J$39,MATCH("monthly_churn",'01_ASSUMPTIONS'!$B$5:$B$39,0)))+INDEX('01_ASSUMPTIONS'!$J$5:$J$39,MATCH("enterprise_monthly_acquisition",'01_ASSUMPTIONS'!$B$5:$B$39,0)) | E31: =SUM(B31:D31) | F31: =B31*INDEX('01_ASSUMPTIONS'!$J$5:$J$39,MATCH("starter_studies_per_customer",'01_ASSUMPTIONS'!$B$5:$B$39,0)) | G31: =C31*INDEX('01_ASSUMPTIONS'!$J$5:$J$39,MATCH("professional_studies_per_customer",'01_ASSUMPTIONS'!$B$5:$B$39,0)) | H31: =D31*INDEX('01_ASSUMPTIONS'!$J$5:$J$39,MATCH("enterprise_studies_per_customer",'01_ASSUMPTIONS'!$B$5:$B$39,0)) | I31: =SUM(F31:H31) | J31: =B31*INDEX('01_ASSUMPTIONS'!$J$5:$J$39,MATCH("starter_fee",'01_ASSUMPTIONS'!$B$5:$B$39,0))+C31*INDEX('01_ASSUMPTIONS'!$J$5:$J$39,MATCH("professional_fee",'01_ASSUMPTIONS'!$B$5:$B$39,0))+D31*INDEX('01_ASSUMPTIONS'!$J$5:$J$39,MATCH("enterprise_fee",'01_ASSUMPTIONS'!$B$5:$B$39,0)) | K31: =MAX(F31-B31*INDEX('01_ASSUMPTIONS'!$J$5:$J$39,MATCH("starter_included_studies",'01_ASSUMPTIONS'!$B$5:$B$39,0)),0)*INDEX('01_ASSUMPTIONS'!$J$5:$J$39,MATCH("starter_overage_fee",'01_ASSUMPTIONS'!$B$5:$B$39,0))+MAX(G31-C31*INDEX('01_ASSUMPTIONS'!$J$5:$J$39,MATCH("professional_included_studies",'01_ASSUMPTIONS'!$B$5:$B$39,0)),0)*INDEX('01_ASSUMPTIONS'!$J$5:$J$39,MATCH("professional_overage_fee",'01_ASSUMPTIONS'!$B$5:$B$39,0))+MAX(H31-D31*INDEX('01_ASSUMPTIONS'!$J$5:$J$39,MATCH("enterprise_included_studies",'01_ASSUMPTIONS'!$B$5:$B$39,0)),0)*INDEX('01_ASSUMPTIONS'!$J$5:$J$39,MATCH("enterprise_overage_fee",'01_ASSUMPTIONS'!$B$5:$B$39,0)) | L31: =J31+K31 | M31: =I31*INDEX('01_ASSUMPTIONS'!$J$5:$J$39,MATCH("cloud_cost_per_study",'01_ASSUMPTIONS'!$B$5:$B$39,0)) | N31: =I31*INDEX('01_ASSUMPTIONS'!$J$5:$J$39,MATCH("storage_cost_per_study",'01_ASSUMPTIONS'!$B$5:$B$39,0)) | O31: =I31*INDEX('01_ASSUMPTIONS'!$J$5:$J$39,MATCH("ai_processing_cost_per_study",'01_ASSUMPTIONS'!$B$5:$B$39,0)) | P31: =E31*INDEX('01_ASSUMPTIONS'!$J$5:$J$39,MATCH("variable_support_per_customer",'01_ASSUMPTIONS'!$B$5:$B$39,0)) | Q31: =SUM(M31:P31) | R31: =INDEX('01_ASSUMPTIONS'!$J$5:$J$39,MATCH("fixed_infra",'01_ASSUMPTIONS'!$B$5:$B$39,0)) | S31: =INDEX('01_ASSUMPTIONS'!$J$5:$J$39,MATCH("software_maintenance",'01_ASSUMPTIONS'!$B$5:$B$39,0)) | T31: =INDEX('01_ASSUMPTIONS'!$J$5:$J$39,MATCH("base_support",'01_ASSUMPTIONS'!$B$5:$B$39,0)) | U31: =INDEX('01_ASSUMPTIONS'!$J$5:$J$39,MATCH("admin",'01_ASSUMPTIONS'!$B$5:$B$39,0)) | V31: =INDEX('01_ASSUMPTIONS'!$J$5:$J$39,MATCH("commercial_marketing",'01_ASSUMPTIONS'!$B$5:$B$39,0)) | W31: =INDEX('01_ASSUMPTIONS'!$J$5:$J$39,MATCH("other_fixed",'01_ASSUMPTIONS'!$B$5:$B$39,0)) | X31: =SUM(R31:W31) | Y31: =L31-Q31-X31 | Z31: =0 | AA31: =Y31-Z31 | AB31: =1/(1+'01_ASSUMPTIONS'!$E$2)^A31 | AC31: =AA31*AB31 | AD31: =AD30+AA31 | AE31: =IF(Y31>=0,"Yes","No") | AF31: =IF(AD31>=0,"Yes","No")
A32: =31 | B32: =B31*(1-INDEX('01_ASSUMPTIONS'!$J$5:$J$39,MATCH("monthly_churn",'01_ASSUMPTIONS'!$B$5:$B$39,0)))+INDEX('01_ASSUMPTIONS'!$J$5:$J$39,MATCH("starter_monthly_acquisition",'01_ASSUMPTIONS'!$B$5:$B$39,0)) | C32: =C31*(1-INDEX('01_ASSUMPTIONS'!$J$5:$J$39,MATCH("monthly_churn",'01_ASSUMPTIONS'!$B$5:$B$39,0)))+INDEX('01_ASSUMPTIONS'!$J$5:$J$39,MATCH("professional_monthly_acquisition",'01_ASSUMPTIONS'!$B$5:$B$39,0)) | D32: =D31*(1-INDEX('01_ASSUMPTIONS'!$J$5:$J$39,MATCH("monthly_churn",'01_ASSUMPTIONS'!$B$5:$B$39,0)))+INDEX('01_ASSUMPTIONS'!$J$5:$J$39,MATCH("enterprise_monthly_acquisition",'01_ASSUMPTIONS'!$B$5:$B$39,0)) | E32: =SUM(B32:D32) | F32: =B32*INDEX('01_ASSUMPTIONS'!$J$5:$J$39,MATCH("starter_studies_per_customer",'01_ASSUMPTIONS'!$B$5:$B$39,0)) | G32: =C32*INDEX('01_ASSUMPTIONS'!$J$5:$J$39,MATCH("professional_studies_per_customer",'01_ASSUMPTIONS'!$B$5:$B$39,0)) | H32: =D32*INDEX('01_ASSUMPTIONS'!$J$5:$J$39,MATCH("enterprise_studies_per_customer",'01_ASSUMPTIONS'!$B$5:$B$39,0)) | I32: =SUM(F32:H32) | J32: =B32*INDEX('01_ASSUMPTIONS'!$J$5:$J$39,MATCH("starter_fee",'01_ASSUMPTIONS'!$B$5:$B$39,0))+C32*INDEX('01_ASSUMPTIONS'!$J$5:$J$39,MATCH("professional_fee",'01_ASSUMPTIONS'!$B$5:$B$39,0))+D32*INDEX('01_ASSUMPTIONS'!$J$5:$J$39,MATCH("enterprise_fee",'01_ASSUMPTIONS'!$B$5:$B$39,0)) | K32: =MAX(F32-B32*INDEX('01_ASSUMPTIONS'!$J$5:$J$39,MATCH("starter_included_studies",'01_ASSUMPTIONS'!$B$5:$B$39,0)),0)*INDEX('01_ASSUMPTIONS'!$J$5:$J$39,MATCH("starter_overage_fee",'01_ASSUMPTIONS'!$B$5:$B$39,0))+MAX(G32-C32*INDEX('01_ASSUMPTIONS'!$J$5:$J$39,MATCH("professional_included_studies",'01_ASSUMPTIONS'!$B$5:$B$39,0)),0)*INDEX('01_ASSUMPTIONS'!$J$5:$J$39,MATCH("professional_overage_fee",'01_ASSUMPTIONS'!$B$5:$B$39,0))+MAX(H32-D32*INDEX('01_ASSUMPTIONS'!$J$5:$J$39,MATCH("enterprise_included_studies",'01_ASSUMPTIONS'!$B$5:$B$39,0)),0)*INDEX('01_ASSUMPTIONS'!$J$5:$J$39,MATCH("enterprise_overage_fee",'01_ASSUMPTIONS'!$B$5:$B$39,0)) | L32: =J32+K32 | M32: =I32*INDEX('01_ASSUMPTIONS'!$J$5:$J$39,MATCH("cloud_cost_per_study",'01_ASSUMPTIONS'!$B$5:$B$39,0)) | N32: =I32*INDEX('01_ASSUMPTIONS'!$J$5:$J$39,MATCH("storage_cost_per_study",'01_ASSUMPTIONS'!$B$5:$B$39,0)) | O32: =I32*INDEX('01_ASSUMPTIONS'!$J$5:$J$39,MATCH("ai_processing_cost_per_study",'01_ASSUMPTIONS'!$B$5:$B$39,0)) | P32: =E32*INDEX('01_ASSUMPTIONS'!$J$5:$J$39,MATCH("variable_support_per_customer",'01_ASSUMPTIONS'!$B$5:$B$39,0)) | Q32: =SUM(M32:P32) | R32: =INDEX('01_ASSUMPTIONS'!$J$5:$J$39,MATCH("fixed_infra",'01_ASSUMPTIONS'!$B$5:$B$39,0)) | S32: =INDEX('01_ASSUMPTIONS'!$J$5:$J$39,MATCH("software_maintenance",'01_ASSUMPTIONS'!$B$5:$B$39,0)) | T32: =INDEX('01_ASSUMPTIONS'!$J$5:$J$39,MATCH("base_support",'01_ASSUMPTIONS'!$B$5:$B$39,0)) | U32: =INDEX('01_ASSUMPTIONS'!$J$5:$J$39,MATCH("admin",'01_ASSUMPTIONS'!$B$5:$B$39,0)) | V32: =INDEX('01_ASSUMPTIONS'!$J$5:$J$39,MATCH("commercial_marketing",'01_ASSUMPTIONS'!$B$5:$B$39,0)) | W32: =INDEX('01_ASSUMPTIONS'!$J$5:$J$39,MATCH("other_fixed",'01_ASSUMPTIONS'!$B$5:$B$39,0)) | X32: =SUM(R32:W32) | Y32: =L32-Q32-X32 | Z32: =0 | AA32: =Y32-Z32 | AB32: =1/(1+'01_ASSUMPTIONS'!$E$2)^A32 | AC32: =AA32*AB32 | AD32: =AD31+AA32 | AE32: =IF(Y32>=0,"Yes","No") | AF32: =IF(AD32>=0,"Yes","No")
A33: =32 | B33: =B32*(1-INDEX('01_ASSUMPTIONS'!$J$5:$J$39,MATCH("monthly_churn",'01_ASSUMPTIONS'!$B$5:$B$39,0)))+INDEX('01_ASSUMPTIONS'!$J$5:$J$39,MATCH("starter_monthly_acquisition",'01_ASSUMPTIONS'!$B$5:$B$39,0)) | C33: =C32*(1-INDEX('01_ASSUMPTIONS'!$J$5:$J$39,MATCH("monthly_churn",'01_ASSUMPTIONS'!$B$5:$B$39,0)))+INDEX('01_ASSUMPTIONS'!$J$5:$J$39,MATCH("professional_monthly_acquisition",'01_ASSUMPTIONS'!$B$5:$B$39,0)) | D33: =D32*(1-INDEX('01_ASSUMPTIONS'!$J$5:$J$39,MATCH("monthly_churn",'01_ASSUMPTIONS'!$B$5:$B$39,0)))+INDEX('01_ASSUMPTIONS'!$J$5:$J$39,MATCH("enterprise_monthly_acquisition",'01_ASSUMPTIONS'!$B$5:$B$39,0)) | E33: =SUM(B33:D33) | F33: =B33*INDEX('01_ASSUMPTIONS'!$J$5:$J$39,MATCH("starter_studies_per_customer",'01_ASSUMPTIONS'!$B$5:$B$39,0)) | G33: =C33*INDEX('01_ASSUMPTIONS'!$J$5:$J$39,MATCH("professional_studies_per_customer",'01_ASSUMPTIONS'!$B$5:$B$39,0)) | H33: =D33*INDEX('01_ASSUMPTIONS'!$J$5:$J$39,MATCH("enterprise_studies_per_customer",'01_ASSUMPTIONS'!$B$5:$B$39,0)) | I33: =SUM(F33:H33) | J33: =B33*INDEX('01_ASSUMPTIONS'!$J$5:$J$39,MATCH("starter_fee",'01_ASSUMPTIONS'!$B$5:$B$39,0))+C33*INDEX('01_ASSUMPTIONS'!$J$5:$J$39,MATCH("professional_fee",'01_ASSUMPTIONS'!$B$5:$B$39,0))+D33*INDEX('01_ASSUMPTIONS'!$J$5:$J$39,MATCH("enterprise_fee",'01_ASSUMPTIONS'!$B$5:$B$39,0)) | K33: =MAX(F33-B33*INDEX('01_ASSUMPTIONS'!$J$5:$J$39,MATCH("starter_included_studies",'01_ASSUMPTIONS'!$B$5:$B$39,0)),0)*INDEX('01_ASSUMPTIONS'!$J$5:$J$39,MATCH("starter_overage_fee",'01_ASSUMPTIONS'!$B$5:$B$39,0))+MAX(G33-C33*INDEX('01_ASSUMPTIONS'!$J$5:$J$39,MATCH("professional_included_studies",'01_ASSUMPTIONS'!$B$5:$B$39,0)),0)*INDEX('01_ASSUMPTIONS'!$J$5:$J$39,MATCH("professional_overage_fee",'01_ASSUMPTIONS'!$B$5:$B$39,0))+MAX(H33-D33*INDEX('01_ASSUMPTIONS'!$J$5:$J$39,MATCH("enterprise_included_studies",'01_ASSUMPTIONS'!$B$5:$B$39,0)),0)*INDEX('01_ASSUMPTIONS'!$J$5:$J$39,MATCH("enterprise_overage_fee",'01_ASSUMPTIONS'!$B$5:$B$39,0)) | L33: =J33+K33 | M33: =I33*INDEX('01_ASSUMPTIONS'!$J$5:$J$39,MATCH("cloud_cost_per_study",'01_ASSUMPTIONS'!$B$5:$B$39,0)) | N33: =I33*INDEX('01_ASSUMPTIONS'!$J$5:$J$39,MATCH("storage_cost_per_study",'01_ASSUMPTIONS'!$B$5:$B$39,0)) | O33: =I33*INDEX('01_ASSUMPTIONS'!$J$5:$J$39,MATCH("ai_processing_cost_per_study",'01_ASSUMPTIONS'!$B$5:$B$39,0)) | P33: =E33*INDEX('01_ASSUMPTIONS'!$J$5:$J$39,MATCH("variable_support_per_customer",'01_ASSUMPTIONS'!$B$5:$B$39,0)) | Q33: =SUM(M33:P33) | R33: =INDEX('01_ASSUMPTIONS'!$J$5:$J$39,MATCH("fixed_infra",'01_ASSUMPTIONS'!$B$5:$B$39,0)) | S33: =INDEX('01_ASSUMPTIONS'!$J$5:$J$39,MATCH("software_maintenance",'01_ASSUMPTIONS'!$B$5:$B$39,0)) | T33: =INDEX('01_ASSUMPTIONS'!$J$5:$J$39,MATCH("base_support",'01_ASSUMPTIONS'!$B$5:$B$39,0)) | U33: =INDEX('01_ASSUMPTIONS'!$J$5:$J$39,MATCH("admin",'01_ASSUMPTIONS'!$B$5:$B$39,0)) | V33: =INDEX('01_ASSUMPTIONS'!$J$5:$J$39,MATCH("commercial_marketing",'01_ASSUMPTIONS'!$B$5:$B$39,0)) | W33: =INDEX('01_ASSUMPTIONS'!$J$5:$J$39,MATCH("other_fixed",'01_ASSUMPTIONS'!$B$5:$B$39,0)) | X33: =SUM(R33:W33) | Y33: =L33-Q33-X33 | Z33: =0 | AA33: =Y33-Z33 | AB33: =1/(1+'01_ASSUMPTIONS'!$E$2)^A33 | AC33: =AA33*AB33 | AD33: =AD32+AA33 | AE33: =IF(Y33>=0,"Yes","No") | AF33: =IF(AD33>=0,"Yes","No")
A34: =33 | B34: =B33*(1-INDEX('01_ASSUMPTIONS'!$J$5:$J$39,MATCH("monthly_churn",'01_ASSUMPTIONS'!$B$5:$B$39,0)))+INDEX('01_ASSUMPTIONS'!$J$5:$J$39,MATCH("starter_monthly_acquisition",'01_ASSUMPTIONS'!$B$5:$B$39,0)) | C34: =C33*(1-INDEX('01_ASSUMPTIONS'!$J$5:$J$39,MATCH("monthly_churn",'01_ASSUMPTIONS'!$B$5:$B$39,0)))+INDEX('01_ASSUMPTIONS'!$J$5:$J$39,MATCH("professional_monthly_acquisition",'01_ASSUMPTIONS'!$B$5:$B$39,0)) | D34: =D33*(1-INDEX('01_ASSUMPTIONS'!$J$5:$J$39,MATCH("monthly_churn",'01_ASSUMPTIONS'!$B$5:$B$39,0)))+INDEX('01_ASSUMPTIONS'!$J$5:$J$39,MATCH("enterprise_monthly_acquisition",'01_ASSUMPTIONS'!$B$5:$B$39,0)) | E34: =SUM(B34:D34) | F34: =B34*INDEX('01_ASSUMPTIONS'!$J$5:$J$39,MATCH("starter_studies_per_customer",'01_ASSUMPTIONS'!$B$5:$B$39,0)) | G34: =C34*INDEX('01_ASSUMPTIONS'!$J$5:$J$39,MATCH("professional_studies_per_customer",'01_ASSUMPTIONS'!$B$5:$B$39,0)) | H34: =D34*INDEX('01_ASSUMPTIONS'!$J$5:$J$39,MATCH("enterprise_studies_per_customer",'01_ASSUMPTIONS'!$B$5:$B$39,0)) | I34: =SUM(F34:H34) | J34: =B34*INDEX('01_ASSUMPTIONS'!$J$5:$J$39,MATCH("starter_fee",'01_ASSUMPTIONS'!$B$5:$B$39,0))+C34*INDEX('01_ASSUMPTIONS'!$J$5:$J$39,MATCH("professional_fee",'01_ASSUMPTIONS'!$B$5:$B$39,0))+D34*INDEX('01_ASSUMPTIONS'!$J$5:$J$39,MATCH("enterprise_fee",'01_ASSUMPTIONS'!$B$5:$B$39,0)) | K34: =MAX(F34-B34*INDEX('01_ASSUMPTIONS'!$J$5:$J$39,MATCH("starter_included_studies",'01_ASSUMPTIONS'!$B$5:$B$39,0)),0)*INDEX('01_ASSUMPTIONS'!$J$5:$J$39,MATCH("starter_overage_fee",'01_ASSUMPTIONS'!$B$5:$B$39,0))+MAX(G34-C34*INDEX('01_ASSUMPTIONS'!$J$5:$J$39,MATCH("professional_included_studies",'01_ASSUMPTIONS'!$B$5:$B$39,0)),0)*INDEX('01_ASSUMPTIONS'!$J$5:$J$39,MATCH("professional_overage_fee",'01_ASSUMPTIONS'!$B$5:$B$39,0))+MAX(H34-D34*INDEX('01_ASSUMPTIONS'!$J$5:$J$39,MATCH("enterprise_included_studies",'01_ASSUMPTIONS'!$B$5:$B$39,0)),0)*INDEX('01_ASSUMPTIONS'!$J$5:$J$39,MATCH("enterprise_overage_fee",'01_ASSUMPTIONS'!$B$5:$B$39,0)) | L34: =J34+K34 | M34: =I34*INDEX('01_ASSUMPTIONS'!$J$5:$J$39,MATCH("cloud_cost_per_study",'01_ASSUMPTIONS'!$B$5:$B$39,0)) | N34: =I34*INDEX('01_ASSUMPTIONS'!$J$5:$J$39,MATCH("storage_cost_per_study",'01_ASSUMPTIONS'!$B$5:$B$39,0)) | O34: =I34*INDEX('01_ASSUMPTIONS'!$J$5:$J$39,MATCH("ai_processing_cost_per_study",'01_ASSUMPTIONS'!$B$5:$B$39,0)) | P34: =E34*INDEX('01_ASSUMPTIONS'!$J$5:$J$39,MATCH("variable_support_per_customer",'01_ASSUMPTIONS'!$B$5:$B$39,0)) | Q34: =SUM(M34:P34) | R34: =INDEX('01_ASSUMPTIONS'!$J$5:$J$39,MATCH("fixed_infra",'01_ASSUMPTIONS'!$B$5:$B$39,0)) | S34: =INDEX('01_ASSUMPTIONS'!$J$5:$J$39,MATCH("software_maintenance",'01_ASSUMPTIONS'!$B$5:$B$39,0)) | T34: =INDEX('01_ASSUMPTIONS'!$J$5:$J$39,MATCH("base_support",'01_ASSUMPTIONS'!$B$5:$B$39,0)) | U34: =INDEX('01_ASSUMPTIONS'!$J$5:$J$39,MATCH("admin",'01_ASSUMPTIONS'!$B$5:$B$39,0)) | V34: =INDEX('01_ASSUMPTIONS'!$J$5:$J$39,MATCH("commercial_marketing",'01_ASSUMPTIONS'!$B$5:$B$39,0)) | W34: =INDEX('01_ASSUMPTIONS'!$J$5:$J$39,MATCH("other_fixed",'01_ASSUMPTIONS'!$B$5:$B$39,0)) | X34: =SUM(R34:W34) | Y34: =L34-Q34-X34 | Z34: =0 | AA34: =Y34-Z34 | AB34: =1/(1+'01_ASSUMPTIONS'!$E$2)^A34 | AC34: =AA34*AB34 | AD34: =AD33+AA34 | AE34: =IF(Y34>=0,"Yes","No") | AF34: =IF(AD34>=0,"Yes","No")
A35: =34 | B35: =B34*(1-INDEX('01_ASSUMPTIONS'!$J$5:$J$39,MATCH("monthly_churn",'01_ASSUMPTIONS'!$B$5:$B$39,0)))+INDEX('01_ASSUMPTIONS'!$J$5:$J$39,MATCH("starter_monthly_acquisition",'01_ASSUMPTIONS'!$B$5:$B$39,0)) | C35: =C34*(1-INDEX('01_ASSUMPTIONS'!$J$5:$J$39,MATCH("monthly_churn",'01_ASSUMPTIONS'!$B$5:$B$39,0)))+INDEX('01_ASSUMPTIONS'!$J$5:$J$39,MATCH("professional_monthly_acquisition",'01_ASSUMPTIONS'!$B$5:$B$39,0)) | D35: =D34*(1-INDEX('01_ASSUMPTIONS'!$J$5:$J$39,MATCH("monthly_churn",'01_ASSUMPTIONS'!$B$5:$B$39,0)))+INDEX('01_ASSUMPTIONS'!$J$5:$J$39,MATCH("enterprise_monthly_acquisition",'01_ASSUMPTIONS'!$B$5:$B$39,0)) | E35: =SUM(B35:D35) | F35: =B35*INDEX('01_ASSUMPTIONS'!$J$5:$J$39,MATCH("starter_studies_per_customer",'01_ASSUMPTIONS'!$B$5:$B$39,0)) | G35: =C35*INDEX('01_ASSUMPTIONS'!$J$5:$J$39,MATCH("professional_studies_per_customer",'01_ASSUMPTIONS'!$B$5:$B$39,0)) | H35: =D35*INDEX('01_ASSUMPTIONS'!$J$5:$J$39,MATCH("enterprise_studies_per_customer",'01_ASSUMPTIONS'!$B$5:$B$39,0)) | I35: =SUM(F35:H35) | J35: =B35*INDEX('01_ASSUMPTIONS'!$J$5:$J$39,MATCH("starter_fee",'01_ASSUMPTIONS'!$B$5:$B$39,0))+C35*INDEX('01_ASSUMPTIONS'!$J$5:$J$39,MATCH("professional_fee",'01_ASSUMPTIONS'!$B$5:$B$39,0))+D35*INDEX('01_ASSUMPTIONS'!$J$5:$J$39,MATCH("enterprise_fee",'01_ASSUMPTIONS'!$B$5:$B$39,0)) | K35: =MAX(F35-B35*INDEX('01_ASSUMPTIONS'!$J$5:$J$39,MATCH("starter_included_studies",'01_ASSUMPTIONS'!$B$5:$B$39,0)),0)*INDEX('01_ASSUMPTIONS'!$J$5:$J$39,MATCH("starter_overage_fee",'01_ASSUMPTIONS'!$B$5:$B$39,0))+MAX(G35-C35*INDEX('01_ASSUMPTIONS'!$J$5:$J$39,MATCH("professional_included_studies",'01_ASSUMPTIONS'!$B$5:$B$39,0)),0)*INDEX('01_ASSUMPTIONS'!$J$5:$J$39,MATCH("professional_overage_fee",'01_ASSUMPTIONS'!$B$5:$B$39,0))+MAX(H35-D35*INDEX('01_ASSUMPTIONS'!$J$5:$J$39,MATCH("enterprise_included_studies",'01_ASSUMPTIONS'!$B$5:$B$39,0)),0)*INDEX('01_ASSUMPTIONS'!$J$5:$J$39,MATCH("enterprise_overage_fee",'01_ASSUMPTIONS'!$B$5:$B$39,0)) | L35: =J35+K35 | M35: =I35*INDEX('01_ASSUMPTIONS'!$J$5:$J$39,MATCH("cloud_cost_per_study",'01_ASSUMPTIONS'!$B$5:$B$39,0)) | N35: =I35*INDEX('01_ASSUMPTIONS'!$J$5:$J$39,MATCH("storage_cost_per_study",'01_ASSUMPTIONS'!$B$5:$B$39,0)) | O35: =I35*INDEX('01_ASSUMPTIONS'!$J$5:$J$39,MATCH("ai_processing_cost_per_study",'01_ASSUMPTIONS'!$B$5:$B$39,0)) | P35: =E35*INDEX('01_ASSUMPTIONS'!$J$5:$J$39,MATCH("variable_support_per_customer",'01_ASSUMPTIONS'!$B$5:$B$39,0)) | Q35: =SUM(M35:P35) | R35: =INDEX('01_ASSUMPTIONS'!$J$5:$J$39,MATCH("fixed_infra",'01_ASSUMPTIONS'!$B$5:$B$39,0)) | S35: =INDEX('01_ASSUMPTIONS'!$J$5:$J$39,MATCH("software_maintenance",'01_ASSUMPTIONS'!$B$5:$B$39,0)) | T35: =INDEX('01_ASSUMPTIONS'!$J$5:$J$39,MATCH("base_support",'01_ASSUMPTIONS'!$B$5:$B$39,0)) | U35: =INDEX('01_ASSUMPTIONS'!$J$5:$J$39,MATCH("admin",'01_ASSUMPTIONS'!$B$5:$B$39,0)) | V35: =INDEX('01_ASSUMPTIONS'!$J$5:$J$39,MATCH("commercial_marketing",'01_ASSUMPTIONS'!$B$5:$B$39,0)) | W35: =INDEX('01_ASSUMPTIONS'!$J$5:$J$39,MATCH("other_fixed",'01_ASSUMPTIONS'!$B$5:$B$39,0)) | X35: =SUM(R35:W35) | Y35: =L35-Q35-X35 | Z35: =0 | AA35: =Y35-Z35 | AB35: =1/(1+'01_ASSUMPTIONS'!$E$2)^A35 | AC35: =AA35*AB35 | AD35: =AD34+AA35 | AE35: =IF(Y35>=0,"Yes","No") | AF35: =IF(AD35>=0,"Yes","No")
A36: =35 | B36: =B35*(1-INDEX('01_ASSUMPTIONS'!$J$5:$J$39,MATCH("monthly_churn",'01_ASSUMPTIONS'!$B$5:$B$39,0)))+INDEX('01_ASSUMPTIONS'!$J$5:$J$39,MATCH("starter_monthly_acquisition",'01_ASSUMPTIONS'!$B$5:$B$39,0)) | C36: =C35*(1-INDEX('01_ASSUMPTIONS'!$J$5:$J$39,MATCH("monthly_churn",'01_ASSUMPTIONS'!$B$5:$B$39,0)))+INDEX('01_ASSUMPTIONS'!$J$5:$J$39,MATCH("professional_monthly_acquisition",'01_ASSUMPTIONS'!$B$5:$B$39,0)) | D36: =D35*(1-INDEX('01_ASSUMPTIONS'!$J$5:$J$39,MATCH("monthly_churn",'01_ASSUMPTIONS'!$B$5:$B$39,0)))+INDEX('01_ASSUMPTIONS'!$J$5:$J$39,MATCH("enterprise_monthly_acquisition",'01_ASSUMPTIONS'!$B$5:$B$39,0)) | E36: =SUM(B36:D36) | F36: =B36*INDEX('01_ASSUMPTIONS'!$J$5:$J$39,MATCH("starter_studies_per_customer",'01_ASSUMPTIONS'!$B$5:$B$39,0)) | G36: =C36*INDEX('01_ASSUMPTIONS'!$J$5:$J$39,MATCH("professional_studies_per_customer",'01_ASSUMPTIONS'!$B$5:$B$39,0)) | H36: =D36*INDEX('01_ASSUMPTIONS'!$J$5:$J$39,MATCH("enterprise_studies_per_customer",'01_ASSUMPTIONS'!$B$5:$B$39,0)) | I36: =SUM(F36:H36) | J36: =B36*INDEX('01_ASSUMPTIONS'!$J$5:$J$39,MATCH("starter_fee",'01_ASSUMPTIONS'!$B$5:$B$39,0))+C36*INDEX('01_ASSUMPTIONS'!$J$5:$J$39,MATCH("professional_fee",'01_ASSUMPTIONS'!$B$5:$B$39,0))+D36*INDEX('01_ASSUMPTIONS'!$J$5:$J$39,MATCH("enterprise_fee",'01_ASSUMPTIONS'!$B$5:$B$39,0)) | K36: =MAX(F36-B36*INDEX('01_ASSUMPTIONS'!$J$5:$J$39,MATCH("starter_included_studies",'01_ASSUMPTIONS'!$B$5:$B$39,0)),0)*INDEX('01_ASSUMPTIONS'!$J$5:$J$39,MATCH("starter_overage_fee",'01_ASSUMPTIONS'!$B$5:$B$39,0))+MAX(G36-C36*INDEX('01_ASSUMPTIONS'!$J$5:$J$39,MATCH("professional_included_studies",'01_ASSUMPTIONS'!$B$5:$B$39,0)),0)*INDEX('01_ASSUMPTIONS'!$J$5:$J$39,MATCH("professional_overage_fee",'01_ASSUMPTIONS'!$B$5:$B$39,0))+MAX(H36-D36*INDEX('01_ASSUMPTIONS'!$J$5:$J$39,MATCH("enterprise_included_studies",'01_ASSUMPTIONS'!$B$5:$B$39,0)),0)*INDEX('01_ASSUMPTIONS'!$J$5:$J$39,MATCH("enterprise_overage_fee",'01_ASSUMPTIONS'!$B$5:$B$39,0)) | L36: =J36+K36 | M36: =I36*INDEX('01_ASSUMPTIONS'!$J$5:$J$39,MATCH("cloud_cost_per_study",'01_ASSUMPTIONS'!$B$5:$B$39,0)) | N36: =I36*INDEX('01_ASSUMPTIONS'!$J$5:$J$39,MATCH("storage_cost_per_study",'01_ASSUMPTIONS'!$B$5:$B$39,0)) | O36: =I36*INDEX('01_ASSUMPTIONS'!$J$5:$J$39,MATCH("ai_processing_cost_per_study",'01_ASSUMPTIONS'!$B$5:$B$39,0)) | P36: =E36*INDEX('01_ASSUMPTIONS'!$J$5:$J$39,MATCH("variable_support_per_customer",'01_ASSUMPTIONS'!$B$5:$B$39,0)) | Q36: =SUM(M36:P36) | R36: =INDEX('01_ASSUMPTIONS'!$J$5:$J$39,MATCH("fixed_infra",'01_ASSUMPTIONS'!$B$5:$B$39,0)) | S36: =INDEX('01_ASSUMPTIONS'!$J$5:$J$39,MATCH("software_maintenance",'01_ASSUMPTIONS'!$B$5:$B$39,0)) | T36: =INDEX('01_ASSUMPTIONS'!$J$5:$J$39,MATCH("base_support",'01_ASSUMPTIONS'!$B$5:$B$39,0)) | U36: =INDEX('01_ASSUMPTIONS'!$J$5:$J$39,MATCH("admin",'01_ASSUMPTIONS'!$B$5:$B$39,0)) | V36: =INDEX('01_ASSUMPTIONS'!$J$5:$J$39,MATCH("commercial_marketing",'01_ASSUMPTIONS'!$B$5:$B$39,0)) | W36: =INDEX('01_ASSUMPTIONS'!$J$5:$J$39,MATCH("other_fixed",'01_ASSUMPTIONS'!$B$5:$B$39,0)) | X36: =SUM(R36:W36) | Y36: =L36-Q36-X36 | Z36: =0 | AA36: =Y36-Z36 | AB36: =1/(1+'01_ASSUMPTIONS'!$E$2)^A36 | AC36: =AA36*AB36 | AD36: =AD35+AA36 | AE36: =IF(Y36>=0,"Yes","No") | AF36: =IF(AD36>=0,"Yes","No")
A37: =36 | B37: =B36*(1-INDEX('01_ASSUMPTIONS'!$J$5:$J$39,MATCH("monthly_churn",'01_ASSUMPTIONS'!$B$5:$B$39,0)))+INDEX('01_ASSUMPTIONS'!$J$5:$J$39,MATCH("starter_monthly_acquisition",'01_ASSUMPTIONS'!$B$5:$B$39,0)) | C37: =C36*(1-INDEX('01_ASSUMPTIONS'!$J$5:$J$39,MATCH("monthly_churn",'01_ASSUMPTIONS'!$B$5:$B$39,0)))+INDEX('01_ASSUMPTIONS'!$J$5:$J$39,MATCH("professional_monthly_acquisition",'01_ASSUMPTIONS'!$B$5:$B$39,0)) | D37: =D36*(1-INDEX('01_ASSUMPTIONS'!$J$5:$J$39,MATCH("monthly_churn",'01_ASSUMPTIONS'!$B$5:$B$39,0)))+INDEX('01_ASSUMPTIONS'!$J$5:$J$39,MATCH("enterprise_monthly_acquisition",'01_ASSUMPTIONS'!$B$5:$B$39,0)) | E37: =SUM(B37:D37) | F37: =B37*INDEX('01_ASSUMPTIONS'!$J$5:$J$39,MATCH("starter_studies_per_customer",'01_ASSUMPTIONS'!$B$5:$B$39,0)) | G37: =C37*INDEX('01_ASSUMPTIONS'!$J$5:$J$39,MATCH("professional_studies_per_customer",'01_ASSUMPTIONS'!$B$5:$B$39,0)) | H37: =D37*INDEX('01_ASSUMPTIONS'!$J$5:$J$39,MATCH("enterprise_studies_per_customer",'01_ASSUMPTIONS'!$B$5:$B$39,0)) | I37: =SUM(F37:H37) | J37: =B37*INDEX('01_ASSUMPTIONS'!$J$5:$J$39,MATCH("starter_fee",'01_ASSUMPTIONS'!$B$5:$B$39,0))+C37*INDEX('01_ASSUMPTIONS'!$J$5:$J$39,MATCH("professional_fee",'01_ASSUMPTIONS'!$B$5:$B$39,0))+D37*INDEX('01_ASSUMPTIONS'!$J$5:$J$39,MATCH("enterprise_fee",'01_ASSUMPTIONS'!$B$5:$B$39,0)) | K37: =MAX(F37-B37*INDEX('01_ASSUMPTIONS'!$J$5:$J$39,MATCH("starter_included_studies",'01_ASSUMPTIONS'!$B$5:$B$39,0)),0)*INDEX('01_ASSUMPTIONS'!$J$5:$J$39,MATCH("starter_overage_fee",'01_ASSUMPTIONS'!$B$5:$B$39,0))+MAX(G37-C37*INDEX('01_ASSUMPTIONS'!$J$5:$J$39,MATCH("professional_included_studies",'01_ASSUMPTIONS'!$B$5:$B$39,0)),0)*INDEX('01_ASSUMPTIONS'!$J$5:$J$39,MATCH("professional_overage_fee",'01_ASSUMPTIONS'!$B$5:$B$39,0))+MAX(H37-D37*INDEX('01_ASSUMPTIONS'!$J$5:$J$39,MATCH("enterprise_included_studies",'01_ASSUMPTIONS'!$B$5:$B$39,0)),0)*INDEX('01_ASSUMPTIONS'!$J$5:$J$39,MATCH("enterprise_overage_fee",'01_ASSUMPTIONS'!$B$5:$B$39,0)) | L37: =J37+K37 | M37: =I37*INDEX('01_ASSUMPTIONS'!$J$5:$J$39,MATCH("cloud_cost_per_study",'01_ASSUMPTIONS'!$B$5:$B$39,0)) | N37: =I37*INDEX('01_ASSUMPTIONS'!$J$5:$J$39,MATCH("storage_cost_per_study",'01_ASSUMPTIONS'!$B$5:$B$39,0)) | O37: =I37*INDEX('01_ASSUMPTIONS'!$J$5:$J$39,MATCH("ai_processing_cost_per_study",'01_ASSUMPTIONS'!$B$5:$B$39,0)) | P37: =E37*INDEX('01_ASSUMPTIONS'!$J$5:$J$39,MATCH("variable_support_per_customer",'01_ASSUMPTIONS'!$B$5:$B$39,0)) | Q37: =SUM(M37:P37) | R37: =INDEX('01_ASSUMPTIONS'!$J$5:$J$39,MATCH("fixed_infra",'01_ASSUMPTIONS'!$B$5:$B$39,0)) | S37: =INDEX('01_ASSUMPTIONS'!$J$5:$J$39,MATCH("software_maintenance",'01_ASSUMPTIONS'!$B$5:$B$39,0)) | T37: =INDEX('01_ASSUMPTIONS'!$J$5:$J$39,MATCH("base_support",'01_ASSUMPTIONS'!$B$5:$B$39,0)) | U37: =INDEX('01_ASSUMPTIONS'!$J$5:$J$39,MATCH("admin",'01_ASSUMPTIONS'!$B$5:$B$39,0)) | V37: =INDEX('01_ASSUMPTIONS'!$J$5:$J$39,MATCH("commercial_marketing",'01_ASSUMPTIONS'!$B$5:$B$39,0)) | W37: =INDEX('01_ASSUMPTIONS'!$J$5:$J$39,MATCH("other_fixed",'01_ASSUMPTIONS'!$B$5:$B$39,0)) | X37: =SUM(R37:W37) | Y37: =L37-Q37-X37 | Z37: =0 | AA37: =Y37-Z37 | AB37: =1/(1+'01_ASSUMPTIONS'!$E$2)^A37 | AC37: =AA37*AB37 | AD37: =AD36+AA37 | AE37: =IF(Y37>=0,"Yes","No") | AF37: =IF(AD37>=0,"Yes","No")

Sheet 05_KPIS
A1: Metric | B1: Active scenario value | C1: Formula / interpretation
A2: Active scenario | B2: ='01_ASSUMPTIONS'!B2 | C2: Selected case
A3: MRR month 36 | B3: ='04_CASH_FLOW'!L37 | C3: Month 36 total revenue
A4: ARR run-rate month 36 | B4: =B3*12 | C4: MRR x 12
A5: Active customers month 36 | B5: ='04_CASH_FLOW'!E37 | C5: Total active customers
A6: Studies month 36 | B6: ='04_CASH_FLOW'!I37 | C6: Total processed studies
A7: Gross margin month 36 | B7: =('04_CASH_FLOW'!L37-'04_CASH_FLOW'!M37-'04_CASH_FLOW'!N37-'04_CASH_FLOW'!O37)/'04_CASH_FLOW'!L37 | C7: Revenue less compute/storage/AI variable costs
A8: Monthly burn month 1 | B8: =-MIN('04_CASH_FLOW'!AA2,0) | C8: Initial negative net cash flow if any
A9: Cumulative cash month 36 | B9: ='04_CASH_FLOW'!AD37 | C9: Cumulative net cash flow
A10: Revenue per study month 36 | B10: =B3/B6 | C10: MRR / studies
A11: Operating break-even month | B11: =IF(COUNTIF('04_CASH_FLOW'!AE2:AE37,"Yes")=0,">36 months",MATCH("Yes",'04_CASH_FLOW'!AE2:AE37,0)) | C11: First month with EBITDA >= 0
A12: Payback month | B12: =IF(COUNTIF('04_CASH_FLOW'!AF2:AF37,"Yes")=0,">36 months",MATCH("Yes",'04_CASH_FLOW'!AF2:AF37,0)) | C12: First month with cumulative cash >= 0
A13: VAN / NPV | B13: =SUM('04_CASH_FLOW'!AC2:AC37) | C13: Discounted net cash flow
A14: TIR monthly | B14: =IFERROR(IRR('04_CASH_FLOW'!AA2:AA37),"n.a.") | C14: Monthly IRR if sign pattern permits
A15: TIR annualized | B15: =IFERROR((1+B14)^12-1,"n.a.") | C15: Annualized monthly IRR
A16: Total revenue 36M | B16: =SUM('04_CASH_FLOW'!L2:L37) | C16: 36-month total revenue
A17: Total studies 36M | B17: =SUM('04_CASH_FLOW'!I2:I37) | C17: 36-month processed studies

Sheet 03_SCENARIOS
A1: Scenario | B1: MRR month 36 | C1: ARR run-rate | D1: Customers month 36 | E1: Studies month 36 | F1: Gross margin month 36 | G1: Break-even month | H1: Payback month | I1: VAN / NPV | J1: TIR annualized
A2: Pesimista | B2: 2147 | C2: 25769 | D2: 3.9231128 | E2: 431.5424 | F2: 0.88746154 | G2: >36 months | H2: >36 months | I2: -108823 | J2: n.a.
A3: Base | B3: 16175 | C3: 194098 | D3: 13.412746 | E3: 4185.475 | F3: 0.94565934 | G3: 17 | H3: >36 months | I3: -31692 | J3: -0.051907846
A4: Optimista | B4: 74020 | C4: 888237 | D4: 36.415649 | E4: 19247.42 | F4: 0.97789737 | G4: 4 | H4: 11 | I4: 652110 | J4: 5.0541724
A6: Note | B6: Scenario comparison is generated from the same documented assumptions as the active model. Use 01_ASSUMPTIONS!B2 to inspect a scenario month by month in 04_CASH_FLOW.

Sheet 06_BREAK_EVEN
A1: Break-even metric | B1: Value | C1: Formula / note
A2: Operating break-even month | B2: ='05_KPIS'!B11 | C2: First month with EBITDA >= 0
A3: Payback month | B3: ='05_KPIS'!B12 | C3: First month with cumulative cash >= 0
A4: Fixed monthly cost | B4: =INDEX('01_ASSUMPTIONS'!$J$5:$J$39,MATCH("fixed_infra",'01_ASSUMPTIONS'!$B$5:$B$39,0))+INDEX('01_ASSUMPTIONS'!$J$5:$J$39,MATCH("software_maintenance",'01_ASSUMPTIONS'!$B$5:$B$39,0))+INDEX('01_ASSUMPTIONS'!$J$5:$J$39,MATCH("base_support",'01_ASSUMPTIONS'!$B$5:$B$39,0))+INDEX('01_ASSUMPTIONS'!$J$5:$J$39,MATCH("admin",'01_ASSUMPTIONS'!$B$5:$B$39,0))+INDEX('01_ASSUMPTIONS'!$J$5:$J$39,MATCH("commercial_marketing",'01_ASSUMPTIONS'!$B$5:$B$39,0))+INDEX('01_ASSUMPTIONS'!$J$5:$J$39,MATCH("other_fixed",'01_ASSUMPTIONS'!$B$5:$B$39,0)) | C4: Monthly fixed operating cost
A5: Average revenue per study M36 | B5: ='05_KPIS'!B10 | C5: Month 36 revenue per study
A6: Variable cost per study | B6: =INDEX('01_ASSUMPTIONS'!$J$5:$J$39,MATCH("cloud_cost_per_study",'01_ASSUMPTIONS'!$B$5:$B$39,0))+INDEX('01_ASSUMPTIONS'!$J$5:$J$39,MATCH("storage_cost_per_study",'01_ASSUMPTIONS'!$B$5:$B$39,0))+INDEX('01_ASSUMPTIONS'!$J$5:$J$39,MATCH("ai_processing_cost_per_study",'01_ASSUMPTIONS'!$B$5:$B$39,0)) | C6: Compute + storage + AI
A7: Contribution per study | B7: =B5-B6 | C7: Revenue per study less study-variable cost
A8: Break-even studies/month | B8: =IF(B7<=0,"n.a.",B4/B7) | C8: Estimated study volume needed to cover fixed cost
A9: Break-even customers/month | B9: =IF('05_KPIS'!B6<=0,"n.a.",B8/('05_KPIS'!B6/'05_KPIS'!B5)) | C9: Estimated customers using month-36 study/customer mix

Sheet 07_SENSITIVITY
A1: Base sensitivity | B1: VAN / NPV | C1: Break-even month | D1: Payback month
A2: Pricing -20% | B2: -77095 | C2: 23 | D2: >36 months
A3: Pricing base | B3: -31692 | C3: 17 | D3: >36 months
A4: Pricing +20% | B4: 13711 | C4: 13 | D4: 29
A5: Cloud cost/study -30% | B5: -30296 | C5: 17 | D5: >36 months
A6: Cloud cost/study base | B6: -31692 | C6: 17 | D6: >36 months
A7: Cloud cost/study +30% | B7: -33088 | C7: 17 | D7: >36 months
A9: Sensitivity method | B9: Formula-consistent recalculation of the refined Base scenario, changing pricing or cloud unit cost while holding other assumptions constant.

Sheet 08_BASE_VIABLE
A1: Base Viable Exploratory
A3: Purpose | B3: Sensitivity-only scenario: not a forecast and not a replacement for Base.
A5: Lever | B5: Base | C5: Exploratory | D5: Reason
A6: Starter monthly acquisition | B6: 0.35 | C6: 0.35 | D6: Commercial funnel sensitivity
A7: Professional monthly acquisition | B7: 0.12 | C7: 0.12 | D7: Commercial funnel sensitivity
A8: Enterprise monthly acquisition | B8: 0.03 | C8: 0.03 | D8: Commercial funnel sensitivity
A9: Pricing multiplier | B9: 1 | C9: 1 | D9: Willingness-to-pay sensitivity, not validated price
A10: Fixed cost multiplier | B10: 1 | C10: 0.95 | D10: Operating efficiency sensitivity
A11: Cloud unit cost/study | B11: 0.21 | C11: 0.21 | D11: Uses refined technical cloud envelope
A14: Result | B14: Value
A15: VAN / NPV | B15: -21162
A16: Operating break-even | B16: 16
A17: Payback | B17: 36
A18: TIR annualized | B18: 0.041112593
A20: Interpretation | B20: This scenario shows a minimum viable direction under refined technical cloud costs; it must not be presented as validated market demand.
