Workbook

Sheet Hallazgos
A1: # | B1: Prioridad | C1: Tipo | D1: Apartado (pág.) | E1: Hallazgo | F1: Sugerencia | G1: Origen | H1: Estado
A2: 1 | B2: Alta | C2: Mejora | D2: Inicio (antes de p.2) | E2: No hay portada, resumen/abstract ni palabras clave. El documento arranca en 'Agradecimientos' y los autores solo se nombran en el Anexo D. | F2: Agregar portada (título, autores, tutor, carrera, fecha) y resumen ES/EN con palabras clave. | G2: Lectura del documento | H2: Pendiente
A3: 2 | B3: Alta | C3: Mejora | D3: Obj. 4.2 (p.18); caps. 13–15 (pp.137–154); Anexo A.2 (pp.155–158) | E3: No existe capítulo de Discusión, Conclusiones generales ni Trabajos futuros, solo cierres parciales por capítulo. El último objetivo específico los promete y el cronograma los deja pendientes para nov–dic. | F3: Capítulo final con matriz objetivo → evidencia → grado de cumplimiento, discusión y líneas futuras. | G3: Lectura del documento | H3: Pendiente
A4: 3 | B4: Alta | C4: Sintaxis | D4: 10.4.2 (p.84), 10.4.3 (p.86), 10.7.2 (pp.94–96), 12.3.1 (p.122) | E4: Quedaron cuatro marcadores '▣ FIGURA … INSERTAR' en lugar de las Figs. 10.4 (modelo de datos), 10.5 (clases), 10.7 (topología GCP) y 12.2 (WIF). El archivo tiene 24 imágenes para 28 figuras listadas. | F4: Insertar los diagramas o retirar figura y texto asociado, y ajustar la Lista de Figuras. | G4: Lectura del documento | H4: Pendiente
A5: 4 | B5: Alta | C5: Coherencia | D5: 11.4 (pp.105–106); 13.3–13.4 (pp.126–127); Anexo E.3 (p.189) | E5: El umbral es 'Dice macro de primer plano ≥ 0,70', pero el valor de las cuatro estructuras (0,811) lo supera y el que 'reprueba' (0,679) incluye una clase llamada 'fondo'. El cálculo (4×0,811+0,15)/5 = 0,679 sugiere que ese promedio abarca 5 clases (4 estructuras + raw_0), no 'dos fondos' como dicen 11.4 y la Tabla 13.2. La fila 3 de la Tabla 13.2 rotula 0,811 como 'cuatro estructuras y un fondo', contra el texto. | F5: Definir formalmente qué clases entran en la métrica, publicar Dice por clase (las 6) y corregir rótulos. Decidir con claridad si el módulo axial aprueba. | G5: Lectura del documento | H5: Pendiente
A6: 5 | B6: Alta | C6: Coherencia | D6: 5.4 (p.20) y 11.11.1 (p.116) vs. 7.11.3 (p.49), RF-22 (pp.72–73), Tabla 15.1 (p.153) | E6: Se afirma que los hallazgos degenerativos están fuera del producto y que 'ninguna de las ocho estimaciones se expone'. Pero 7.11.3 dice que 'el producto puede generar' hallazgos, RF-22 los marca Alta/Implementado y la Tabla 15.1 'implementado e integrado'. | F6: Unificar ('implementado en Backend+AI, deshabilitado en el producto') y corregir 7.11.3, RF-22 y Tabla 15.1. | G6: Lectura del documento | H6: Pendiente
A7: 6 | B7: Alta | C7: Coherencia | D7: 6.3.2 (p.24), Tabla 6.4 (p.32), Tabla A.3 (p.158) vs. 6.3.4 (p.25) y 11.11.1 (p.116) | E7: Se dice que LumbarDISC 'sirvió de base/habilitó' los hallazgos por nivel, pero 6.3.4 atribuye ese modelo a SPIDER. Las 8 etiquetas (Pfirrmann, Modic, listesis…) no son las de LumbarDISC (estenosis). Confirmado externamente: LumbarDISC está anotado solo para estenosis (canal, receso subarticular, foramen) y las gradaciones del modelo (Pfirrmann, Modic, platillos, listesis, hernia, estrechamiento, abombamiento) las publica SPIDER en su release. | F7: Explicitar por modelo: dataset, etiquetas y partición. | G7: Lectura del documento | H7: Pendiente
A8: 7 | B8: Alta | C8: Coherencia | D8: 9.6–9.10 (pp.67–77), 11.7 (p.111), 15.2 (p.153), A.3 (p.158), Anexo F (p.195) vs. 11.12 (p.118), 13.8 (p.128) | E8: El recorrido E2E con interfaz sobre stack real figura 'pendiente' en unos lugares y con 'Playwright 11/11 PASS / evidencia final' en otros (parte sobre Demo Mode). El Anexo F dice ambas cosas en el mismo apartado. | F8: Tabla única de qué se probó y dónde (demo / local real / Cloud V2), con evidencia. Ejecutar el recorrido real o declararlo fuera de alcance. | G8: Lectura del documento | H8: Pendiente
A9: 8 | B9: Alta | C9: Coherencia | D9: RV-02/03 (p.76), RF-21 y RNF-09 (pp.73–75), Tablas 13.5 y H.1 (pp.134, 208), A.1 (p.155), Tabla 15.1 (pp.152–153), Anexo F (p.195) | E9: Estados desactualizados en una entrega '100 %'. Validaciones 'En curso' aunque el cap. 13 las da por hechas. Tablas 13.5/H.1 admiten estar 'al 6 de octubre… requieren actualización'. Anexo A marca el 50 % 'En curso' y el 75 % 'Previsto'. Anexo F lista como 'Pendiente' la validación profesional, el negocio y Cloud, ya presentados. El archivo dice 'Tercera entrega 100 %' pero el cronograma deja el 75 % como futuro. | F9: Actualizar estados y fechas y aclarar a qué hito corresponde esta entrega. | G9: Lectura del documento | H9: Pendiente
A10: 9 | B10: Alta | C10: Coherencia | D10: 5.4 (p.20), RF-08/HU-14 (pp.68, 70), 5.5 (p.21), RNF-07 (p.75) vs. 11.12 (p.119), 13.8 (p.129) | E10: La comparación longitudinal es 'futura' en 5.4, RF-08 y HU-14, pero 'Parcial' en la Tabla 11.5 y 'PASS' en la 13.4. Se afirma que subjectRef no es la identidad longitudinal, mientras las tablas la describen 'basada principalmente en subjectRef/Demo Mode'. | F10: Fijar el estado real con su evidencia y explicar Patient/subjectRef en un solo lugar. | G10: Lectura del documento | H10: Pendiente
A11: 10 | B11: Alta | C11: Coherencia | D11: 13.8 (pp.128–129), 10.7.2 (p.96), 13.10 (p.132) | E11: Aparecen elementos que no están en alcance, requerimientos ni capacidades: chat contextual con LLM ('mock', Qwen, recurso pfi-llm-qwen-v2), Grad-CAM, export PDF/JSON, Demo Mode, '67B2/67C' y flags como productEnabled=false. Contrastan con el énfasis en 'no LLM' (7.10.4, p.48) y no se definen en el cuerpo. | F11: Incorporarlos formalmente (alcance, RF, capacidad) o retirarlos. Definir Demo Mode y los códigos internos. | G11: Lectura del documento | H11: Pendiente
A12: 11 | B12: Alta | C12: Coherencia | D12: 13.2 (p.125), 11.4 (p.106), 13.5 (p.127) | E12: Módulo axial: conteos de entrenamiento 'pendientes de recuperación', 'dos particiones que no coinciden' y partición de prueba ya usada antes. Los '81/102 casos' no cuadran con 515 pacientes y 1.545 máscaras (6.3.3). Hay riesgo de fuga y la evaluación no es reproducible. | F12: Reconstruir la partición o reevaluar con un split documentado (por paciente, con semilla) y publicar conteos. | G12: Lectura del documento | H12: Pendiente
A13: 12 | B13: Alta | C13: Coherencia | D13: 5.3 (p.20), RV-01 (p.76), 13.4 (p.127), E.3 (p.189), 13.12 (p.136) | E13: Se exige IoU como control 'no configurable', pero la Tabla 13.2 solo informa Dice. HD95 y NSD se desarrollan en 7.9 (pp.46–47) y no se usan. El proyecto incumple su propio criterio de promoción. | F13: Reportar IoU (y por clase) y, si es posible, HD95. Si no, recortar 7.9 y el objetivo. | G13: Lectura del documento | H13: Pendiente
... A68: 67 | B68: Baja | C68: Mejora | D68: Referencias (p.211) | E68: Verificadas por búsqueda: [1], [2], [3], [5], [6], [7], [8], [9], [10], [11], [12], [29]. [7] omite el n.º de artículo (14993). Sin verificar: [4], [13]–[28], [30]–[40]. No encontré referencias inexistentes. | F68: Completar [7] y verificar las restantes antes de la entrega. | G68: Verificación externa | H68: Pendiente

Sheet Resumen
A1: Resumen de hallazgos — PFI (revisión)
A3: Tipo | B3: Alta | C3: Media | D3: Baja | E3: Total
A4: Coherencia | B4: =COUNTIFS(Hallazgos!$C$2:$C$68,$A4,Hallazgos!$B$2:$B$68,B$3) -> 13 | C4: =COUNTIFS(Hallazgos!$C$2:$C$68,$A4,Hallazgos!$B$2:$B$68,C$3) -> 18 | D4: =COUNTIFS(Hallazgos!$C$2:$C$68,$A4,Hallazgos!$B$2:$B$68,D$3) -> 1 | E4: =SUM(B4:D4) -> 32
A5: Duplicidad | B5: =COUNTIFS(Hallazgos!$C$2:$C$68,$A5,Hallazgos!$B$2:$B$68,B$3) -> 0 | C5: =COUNTIFS(Hallazgos!$C$2:$C$68,$A5,Hallazgos!$B$2:$B$68,C$3) -> 10 | D5: =COUNTIFS(Hallazgos!$C$2:$C$68,$A5,Hallazgos!$B$2:$B$68,D$3) -> 0 | E5: =SUM(B5:D5) -> 10
A6: Sintaxis | B6: =COUNTIFS(Hallazgos!$C$2:$C$68,$A6,Hallazgos!$B$2:$B$68,B$3) -> 1 | C6: =COUNTIFS(Hallazgos!$C$2:$C$68,$A6,Hallazgos!$B$2:$B$68,C$3) -> 7 | D6: =COUNTIFS(Hallazgos!$C$2:$C$68,$A6,Hallazgos!$B$2:$B$68,D$3) -> 1 | E6: =SUM(B6:D6) -> 9
A7: Mejora | B7: =COUNTIFS(Hallazgos!$C$2:$C$68,$A7,Hallazgos!$B$2:$B$68,B$3) -> 5 | C7: =COUNTIFS(Hallazgos!$C$2:$C$68,$A7,Hallazgos!$B$2:$B$68,C$3) -> 7 | D7: =COUNTIFS(Hallazgos!$C$2:$C$68,$A7,Hallazgos!$B$2:$B$68,D$3) -> 4 | E7: =SUM(B7:D7) -> 16
A8: Total | B8: =SUM(B4:B7) -> 19 | C8: =SUM(C4:C7) -> 42 | D8: =SUM(D4:D7) -> 6 | E8: =SUM(E4:E7) -> 67
A10: Corregidos | B10: =COUNTIF(Hallazgos!$H$2:$H$68,"Corregido") -> 0
A11: Pendientes | B11: =COUNTIF(Hallazgos!$H$2:$H$68,"Pendiente") -> 67
A13: Nota: páginas según el índice del propio documento (Word), que está parcialmente desactualizado (±1–2 págs.). Anexo D contrastado con el cap. 8; referencias verificadas por búsqueda web (ver última fila de Referencias). No se inspeccionó el contenido de imágenes.
